<?xml version="1.0" encoding="UTF-8"?>

<CHAT xmlns:xsi="http://www.w3.org/2001/XMLSchema-instance"
      xmlns="http://www.talkbank.org/ns/talkbank"
      xsi:schemaLocation="http://www.talkbank.org/ns/talkbank https://talkbank.org/software/talkbank.xsd"
      Media="5561AC" Mediatypes="audio"
            DesignType="long"
            ActivityType="preverbal"
            GroupType="TD"
      PID="11312/c-00043425-1"
      Window="296_456_444_707_0_0_350_1_350_1"
      Version="2.16.0"
      Lang="eng"
      Options="bullets"
      Corpus="NewmanRatner"
      >
  <Participants>
    <participant
      id="MOT"
    name="5561AC18"
      role="Mother"
      language="eng"
      sex="female"
      education="College_Master&apos;s"

    />
    <participant
      id="CHI"
    name="5561AC18"
      role="Target_Child"
      language="eng"
      age="P1Y06M"
      sex="female"
      group="TD"
      education="UG"

    />
    <participant
      id="EXP"
    name="Clinician"
      role="Investigator"
      language="eng"

    />
  </Participants>
  <comment type="Transcriber">Elianna_Groskin</comment>
  <comment type="Types">long, preverbal, TD</comment>
  <u who="MOT" uID="u0">
    <w>Amira<mor type="mor"><mw><pos><c>n</c><s>prop</s></pos><stem>Amira</stem></mw><gra type="gra" index="1" head="2" relation="SUBJ"/></mor></w>
    <w>come<mor type="mor"><mw><pos><c>v</c></pos><stem>come</stem></mw><gra type="gra" index="2" head="0" relation="ROOT"/></mor></w>
    <g><w>on<mor type="mor"><mw><pos><c>adv</c></pos><stem>on</stem></mw><gra type="gra" index="3" head="2" relation="JCT"/></mor></w><ga type="paralinguistics">background noise</ga></g>
    <t type="p"><mor type="mor"><mt type="p"/><gra type="gra" index="4" head="2" relation="PUNCT"/></mor></t>

  </u>
  <u who="MOT" uID="u1">
    <w>come<mor type="mor"><mw><pos><c>v</c></pos><stem>come</stem></mw><gra type="gra" index="1" head="0" relation="ROOT"/></mor></w>
    <w>play<mor type="mor"><mw><pos><c>n</c></pos><stem>play</stem></mw><gra type="gra" index="2" head="1" relation="OBJ"/></mor></w>
    <t type="e"><mor type="mor"><mt type="e"/><gra type="gra" index="3" head="1" relation="PUNCT"/></mor></t>
    <media
      start="0.000"
      end="4.731"
      unit="s"
    />
  </u>
  <u who="EXP" uID="u2">
    <w>Amira<mor type="mor"><mw><pos><c>n</c><s>prop</s></pos><stem>Amira</stem></mw><gra type="gra" index="1" head="2" relation="NAME"/></mor></w>
    <w>Comision<mor type="mor"><mw><pos><c>n</c><s>prop</s></pos><stem>Comision</stem></mw><gra type="gra" index="2" head="3" relation="SUBJ"/></mor></w>
    <w>five<mor type="mor"><mw><pos><c>det</c><s>num</s></pos><stem>five</stem></mw><gra type="gra" index="3" head="6" relation="ENUM"/></mor></w>
    <w>five<mor type="mor"><mw><pos><c>det</c><s>num</s></pos><stem>five</stem></mw><gra type="gra" index="4" head="5" relation="DATE"/></mor></w>
    <w>six<mor type="mor"><mw><pos><c>det</c><s>num</s></pos><stem>six</stem></mw><gra type="gra" index="5" head="6" relation="DATE"/></mor></w>
    <w>one<mor type="mor"><mw><pos><c>det</c><s>num</s></pos><stem>one</stem></mw><gra type="gra" index="6" head="0" relation="INCROOT"/></mor></w>
    <t type="p"><mor type="mor"><mt type="p"/><gra type="gra" index="7" head="6" relation="PUNCT"/></mor></t>

  </u>
  <u who="MOT" uID="u3">
    <w>ooh<mor type="mor"><mw><pos><c>v</c></pos><stem>ooh</stem></mw><gra type="gra" index="1" head="0" relation="ROOT"/></mor></w>
    <t type="p"><mor type="mor"><mt type="p"/><gra type="gra" index="2" head="1" relation="PUNCT"/></mor></t>
    <media
      start="4.731"
      end="14.517"
      unit="s"
    />
  </u>
  <u who="MOT" uID="u4">
    <w>in<mor type="mor"><mw><pos><c>prep</c></pos><stem>in</stem></mw><gra type="gra" index="1" head="0" relation="INCROOT"/></mor></w>
    <w>the<mor type="mor"><mw><pos><c>det</c><s>art</s></pos><stem>the</stem></mw><gra type="gra" index="2" head="3" relation="DET"/></mor></w>
    <g><w>bird<mor type="mor"><mw><pos><c>n</c></pos><stem>bird</stem></mw><gra type="gra" index="3" head="1" relation="POBJ"/></mor></w><ga type="paralinguistics">bird noise</ga></g>
    <t type="p"><mor type="mor"><mt type="p"/><gra type="gra" index="4" head="1" relation="PUNCT"/></mor></t>
    <media
      start="14.517"
      end="18.489"
      unit="s"
    />
  </u>
  <u who="MOT" uID="u5">
    <w>come<mor type="mor"><mw><pos><c>v</c></pos><stem>come</stem></mw><gra type="gra" index="1" head="0" relation="ROOT"/></mor></w>
    <w>on<mor type="mor"><mw><pos><c>adv</c></pos><stem>on</stem></mw><gra type="gra" index="2" head="1" relation="JCT"/></mor></w>
    <t type="p"><mor type="mor"><mt type="p"/><gra type="gra" index="3" head="1" relation="PUNCT"/></mor></t>
    <media
      start="18.489"
      end="23.099"
      unit="s"
    />
  </u>
  <u who="MOT" uID="u6">
    <w>you<mor type="mor"><mw><pos><c>pro</c><s>per</s></pos><stem>you</stem></mw><gra type="gra" index="1" head="2" relation="SUBJ"/></mor></w>
    <w>gonna<mor type="mor"><mw><pos><c>part</c></pos><stem>go</stem><mk type="sfx">PRESP</mk></mw><gra type="gra" index="2" head="0" relation="ROOT"/><mor-post><mw><pos><c>inf</c></pos><stem>to</stem></mw><gra type="gra" index="3" head="2" relation="OM"/></mor-post></mor></w>
    <t type="self interruption"><mor type="mor"><mt type="self interruption"/><gra type="gra" index="4" head="2" relation="PUNCT"/></mor></t>

  </u>
  <u who="MOT" uID="u7">
    <e><action/><ga type="paralinguistics">clucking noises</ga></e>
    <w>can<mor type="mor"><mw><pos><c>mod</c></pos><stem>can</stem></mw><gra type="gra" index="1" head="4" relation="AUX"/></mor></w>
    <w>the<mor type="mor"><mw><pos><c>det</c><s>art</s></pos><stem>the</stem></mw><gra type="gra" index="2" head="3" relation="DET"/></mor></w>
    <w>baby<mor type="mor"><mw><pos><c>n</c></pos><stem>baby</stem></mw><gra type="gra" index="3" head="4" relation="SUBJ"/></mor></w>
    <w>have<mor type="mor"><mw><pos><c>v</c></pos><stem>have</stem></mw><gra type="gra" index="4" head="0" relation="ROOT"/></mor></w>
    <w>something<mor type="mor"><mw><pos><c>pro</c><s>indef</s></pos><stem>something</stem></mw><gra type="gra" index="5" head="7" relation="SUBJ"/></mor></w>
    <w>to<mor type="mor"><mw><pos><c>inf</c></pos><stem>to</stem></mw><gra type="gra" index="6" head="7" relation="INF"/></mor></w>
    <w>eat<mor type="mor"><mw><pos><c>v</c></pos><stem>eat</stem></mw><gra type="gra" index="7" head="4" relation="COMP"/></mor></w>
    <t type="q"><mor type="mor"><mt type="q"/><gra type="gra" index="8" head="4" relation="PUNCT"/></mor></t>
    <media
      start="23.099"
      end="27.446"
      unit="s"
    />
  </u>
  <u who="MOT" uID="u8">
    <w>can<mor type="mor"><mw><pos><c>mod</c></pos><stem>can</stem></mw><gra type="gra" index="1" head="4" relation="AUX"/></mor></w>
    <w>the<mor type="mor"><mw><pos><c>det</c><s>art</s></pos><stem>the</stem></mw><gra type="gra" index="2" head="3" relation="DET"/></mor></w>
    <w>baby<mor type="mor"><mw><pos><c>n</c></pos><stem>baby</stem></mw><gra type="gra" index="3" head="4" relation="SUBJ"/></mor></w>
    <w>have<mor type="mor"><mw><pos><c>v</c></pos><stem>have</stem></mw><gra type="gra" index="4" head="0" relation="ROOT"/></mor></w>
    <w>some<mor type="mor"><mw><pos><c>qn</c></pos><stem>some</stem></mw><gra type="gra" index="5" head="6" relation="QUANT"/></mor></w>
    <w formType="family-specific">numnums<mor type="mor"><mw><pos><c>fam</c></pos><stem>numnums</stem></mw><gra type="gra" index="6" head="4" relation="JCT"/></mor></w>
    <t type="q"><mor type="mor"><mt type="q"/><gra type="gra" index="7" head="4" relation="PUNCT"/></mor></t>
    <media
      start="27.446"
      end="30.049"
      unit="s"
    />
  </u>
  <u who="MOT" uID="u9">
    <w>mm<mor type="mor"><mw><pos><c>co</c></pos><stem>mm</stem></mw><gra type="gra" index="1" head="0" relation="INCROOT"/></mor></w>
    <t type="p"><mor type="mor"><mt type="p"/><gra type="gra" index="2" head="1" relation="PUNCT"/></mor></t>
    <media
      start="30.049"
      end="31.428"
      unit="s"
    />
  </u>
  <u who="MOT" uID="u10">
    <w>mm<mor type="mor"><mw><pos><c>co</c></pos><stem>mm</stem></mw><gra type="gra" index="1" head="5" relation="COM"/></mor></w>
    <w>how<mor type="mor"><mw><pos><c>pro</c><s>int</s></pos><stem>how</stem></mw><gra type="gra" index="2" head="4" relation="LINK"/></mor></w>
    <w><shortening>a</shortening>bout<mor type="mor"><mw><pos><c>prep</c></pos><stem>about</stem></mw><gra type="gra" index="3" head="4" relation="JCT"/></mor></w>
    <w>some<mor type="mor"><mw><pos><c>qn</c></pos><stem>some</stem></mw><gra type="gra" index="4" head="5" relation="QUANT"/></mor></w>
    <g><w>juice<mor type="mor"><mw><pos><c>n</c></pos><stem>juice</stem></mw><gra type="gra" index="5" head="0" relation="INCROOT"/></mor></w><ga type="paralinguistics">clucking noises</ga></g>
    <t type="q"><mor type="mor"><mt type="q"/><gra type="gra" index="6" head="5" relation="PUNCT"/></mor></t>
    <media
      start="31.428"
      end="35.604"
      unit="s"
    />
  </u>
  <u who="MOT" uID="u11">
    <w>can<mor type="mor"><mw><pos><c>mod</c></pos><stem>can</stem></mw><gra type="gra" index="1" head="4" relation="AUX"/></mor></w>
    <w>the<mor type="mor"><mw><pos><c>det</c><s>art</s></pos><stem>the</stem></mw><gra type="gra" index="2" head="3" relation="DET"/></mor></w>
    <w>baby<mor type="mor"><mw><pos><c>n</c></pos><stem>baby</stem></mw><gra type="gra" index="3" head="4" relation="SUBJ"/></mor></w>
    <w>have<mor type="mor"><mw><pos><c>v</c></pos><stem>have</stem></mw><gra type="gra" index="4" head="0" relation="ROOT"/></mor></w>
    <w>some<mor type="mor"><mw><pos><c>qn</c></pos><stem>some</stem></mw><gra type="gra" index="5" head="6" relation="QUANT"/></mor></w>
    <w>juice<mor type="mor"><mw><pos><c>n</c></pos><stem>juice</stem></mw><gra type="gra" index="6" head="4" relation="OBJ"/></mor></w>
    <t type="q"><mor type="mor"><mt type="q"/><gra type="gra" index="7" head="4" relation="PUNCT"/></mor></t>
    <media
      start="35.604"
      end="37.413"
      unit="s"
    />
  </u>
  <u who="MOT" uID="u12">
    <w>can<mor type="mor"><mw><pos><c>mod</c></pos><stem>can</stem></mw><gra type="gra" index="1" head="3" relation="AUX"/></mor></w>
    <w>she<mor type="mor"><mw><pos><c>pro</c><s>sub</s></pos><stem>she</stem></mw><gra type="gra" index="2" head="3" relation="SUBJ"/></mor></w>
    <w>have<mor type="mor"><mw><pos><c>v</c></pos><stem>have</stem></mw><gra type="gra" index="3" head="0" relation="ROOT"/></mor></w>
    <w>some<mor type="mor"><mw><pos><c>qn</c></pos><stem>some</stem></mw><gra type="gra" index="4" head="5" relation="QUANT"/></mor></w>
    <w>juice<mor type="mor"><mw><pos><c>n</c></pos><stem>juice</stem></mw><gra type="gra" index="5" head="3" relation="OBJ"/></mor></w>
    <t type="q"><mor type="mor"><mt type="q"/><gra type="gra" index="6" head="3" relation="PUNCT"/></mor></t>
    <media
      start="37.413"
      end="40.487"
      unit="s"
    />
  </u>
  <u who="MOT" uID="u13">
    <w>oh<mor type="mor"><mw><pos><c>co</c></pos><stem>oh</stem></mw><gra type="gra" index="1" head="3" relation="COM"/></mor></w>
    <w>you<mor type="mor"><mw><pos><c>pro</c><s>per</s></pos><stem>you</stem></mw><gra type="gra" index="2" head="3" relation="SUBJ"/></mor></w>
    <w>feed<mor type="mor"><mw><pos><c>v</c></pos><stem>feed</stem></mw><gra type="gra" index="3" head="0" relation="ROOT"/></mor></w>
    <w>the<mor type="mor"><mw><pos><c>det</c><s>art</s></pos><stem>the</stem></mw><gra type="gra" index="4" head="5" relation="DET"/></mor></w>
    <w>baby<mor type="mor"><mw><pos><c>n</c></pos><stem>baby</stem></mw><gra type="gra" index="5" head="3" relation="OBJ"/></mor></w>
    <t type="p"><mor type="mor"><mt type="p"/><gra type="gra" index="6" head="3" relation="PUNCT"/></mor></t>

  </u>
  <u who="MOT" uID="u14">
    <w>mm<mor type="mor"><mw><pos><c>co</c></pos><stem>mm</stem></mw><gra type="gra" index="1" head="3" relation="COM"/></mor></w>
    <w>look<mor type="mor"><mw><pos><c>co</c></pos><stem>look</stem></mw><gra type="gra" index="2" head="3" relation="COM"/></mor></w>
    <w>mm<mor type="mor"><mw><pos><c>co</c></pos><stem>mm</stem></mw><gra type="gra" index="3" head="0" relation="INCROOT"/></mor></w>
    <t type="p"><mor type="mor"><mt type="p"/><gra type="gra" index="4" head="3" relation="PUNCT"/></mor></t>
    <media
      start="40.487"
      end="46.998"
      unit="s"
    />
  </u>
  <u who="MOT" uID="u15">
    <w>here<mor type="mor"><mw><pos><c>adv</c></pos><stem>here</stem></mw><gra type="gra" index="1" head="3" relation="JCT"/></mor></w>
    <w>you<mor type="mor"><mw><pos><c>pro</c><s>per</s></pos><stem>you</stem></mw><gra type="gra" index="2" head="3" relation="SUBJ"/></mor></w>
    <w>feed<mor type="mor"><mw><pos><c>v</c></pos><stem>feed</stem></mw><gra type="gra" index="3" head="0" relation="ROOT"/></mor></w>
    <w>her<mor type="mor"><mw><pos><c>pro</c><s>obj</s></pos><stem>her</stem></mw><gra type="gra" index="4" head="3" relation="OBJ"/></mor></w>
    <t type="p"><mor type="mor"><mt type="p"/><gra type="gra" index="5" head="3" relation="PUNCT"/></mor></t>
    <media
      start="46.998"
      end="49.749"
      unit="s"
    />
  </u>
  <u who="MOT" uID="u16">
    <g><w>mm<mor type="mor"><mw><pos><c>co</c></pos><stem>mm</stem></mw><gra type="gra" index="1" head="0" relation="INCROOT"/></mor></w><ga type="paralinguistics">eating noises</ga></g>
    <t type="p"><mor type="mor"><mt type="p"/><gra type="gra" index="2" head="1" relation="PUNCT"/></mor></t>
    <media
      start="49.749"
      end="52.711"
      unit="s"
    />
  </u>
  <u who="MOT" uID="u17">
    <e><action/><ga type="paralinguistics">eating noises</ga></e>
    <t type="p"></t>
    <media
      start="52.711"
      end="56.170"
      unit="s"
    />
  </u>
  <u who="MOT" uID="u18">
    <w>mm<mor type="mor"><mw><pos><c>co</c></pos><stem>mm</stem></mw><gra type="gra" index="1" head="0" relation="INCROOT"/></mor></w>
    <t type="p"><mor type="mor"><mt type="p"/><gra type="gra" index="2" head="1" relation="PUNCT"/></mor></t>
    <media
      start="56.170"
      end="60.183"
      unit="s"
    />
  </u>
  <u who="MOT" uID="u19">
    <w>mm<mor type="mor"><mw><pos><c>co</c></pos><stem>mm</stem></mw><gra type="gra" index="1" head="2" relation="COM"/></mor></w>
    <w>num_num<mor type="mor"><mw><pos><c>on</c></pos><stem>num</stem><mk type="sfxf">DUP</mk></mw><gra type="gra" index="2" head="0" relation="INCROOT"/></mor></w>
    <t type="p"><mor type="mor"><mt type="p"/><gra type="gra" index="3" head="2" relation="PUNCT"/></mor></t>
    <media
      start="60.183"
      end="67.959"
      unit="s"
    />
  </u>
  <u who="MOT" uID="u20">
    <w>let's<mor type="mor"><mw><pos><c>v</c></pos><stem>let</stem></mw><gra type="gra" index="1" head="0" relation="ROOT"/><mor-post><mw><pos><c>pro</c><s>obj</s></pos><stem>us</stem></mw><gra type="gra" index="2" head="1" relation="OBJ"/></mor-post></mor></w>
    <w>see<mor type="mor"><mw><pos><c>v</c></pos><stem>see</stem></mw><gra type="gra" index="3" head="1" relation="COMP"/></mor></w>
    <w>what<mor type="mor"><mw><pos><c>pro</c><s>int</s></pos><stem>what</stem></mw><gra type="gra" index="4" head="7" relation="LINK"/></mor></w>
    <w>else<mor type="mor"><mw><pos><c>post</c></pos><stem>else</stem></mw><gra type="gra" index="5" head="4" relation="PQ"/></mor></w>
    <w>we<mor type="mor"><mw><pos><c>pro</c><s>sub</s></pos><stem>we</stem></mw><gra type="gra" index="6" head="7" relation="SUBJ"/></mor></w>
    <w>have<mor type="mor"><mw><pos><c>v</c></pos><stem>have</stem></mw><gra type="gra" index="7" head="3" relation="COMP"/></mor></w>
    <t type="p"><mor type="mor"><mt type="p"/><gra type="gra" index="8" head="1" relation="PUNCT"/></mor></t>
    <media
      start="67.959"
      end="69.925"
      unit="s"
    />
  </u>
  <u who="MOT" uID="u21">
    <w>I<mor type="mor"><mw><pos><c>pro</c><s>sub</s></pos><stem>I</stem></mw><gra type="gra" index="1" head="4" relation="SUBJ"/></mor></w>
    <w>don't<mor type="mor"><mw><pos><c>mod</c></pos><stem>do</stem></mw><gra type="gra" index="2" head="4" relation="AUX"/><mor-post><mw><pos><c>neg</c></pos><stem>not</stem></mw><gra type="gra" index="3" head="2" relation="NEG"/></mor-post></mor></w>
    <w>think<mor type="mor"><mw><pos><c>v</c></pos><stem>think</stem></mw><gra type="gra" index="4" head="0" relation="ROOT"/></mor></w>
    <w>she<mor type="mor"><mw><pos><c>pro</c><s>sub</s></pos><stem>she</stem></mw><gra type="gra" index="5" head="6" relation="SUBJ"/></mor></w>
    <w>wants<mor type="mor"><mw><pos><c>v</c></pos><stem>want</stem><mk type="sfx">3S</mk></mw><gra type="gra" index="6" head="4" relation="COMP"/></mor></w>
    <w>to<mor type="mor"><mw><pos><c>inf</c></pos><stem>to</stem></mw><gra type="gra" index="7" head="8" relation="INF"/></mor></w>
    <w>eat<mor type="mor"><mw><pos><c>v</c></pos><stem>eat</stem></mw><gra type="gra" index="8" head="6" relation="COMP"/></mor></w>
    <w>all<mor type="mor"><mw><pos><c>pro</c><s>indef</s></pos><stem>all</stem></mw><gra type="gra" index="9" head="8" relation="OBJ"/></mor></w>
    <w>of<mor type="mor"><mw><pos><c>prep</c></pos><stem>of</stem></mw><gra type="gra" index="10" head="9" relation="NJCT"/></mor></w>
    <w>this<mor type="mor"><mw><pos><c>pro</c><s>dem</s></pos><stem>this</stem></mw><gra type="gra" index="11" head="10" relation="POBJ"/></mor></w>
    <t type="p"><mor type="mor"><mt type="p"/><gra type="gra" index="12" head="4" relation="PUNCT"/></mor></t>
    <media
      start="69.925"
      end="73.706"
      unit="s"
    />
  </u>
  <u who="MOT" uID="u22">
    <w>you<mor type="mor"><mw><pos><c>pro</c><s>per</s></pos><stem>you</stem></mw><gra type="gra" index="1" head="2" relation="SUBJ"/></mor></w>
    <w>gonna<mor type="mor"><mw><pos><c>part</c></pos><stem>go</stem><mk type="sfx">PRESP</mk></mw><gra type="gra" index="2" head="0" relation="ROOT"/><mor-post><mw><pos><c>inf</c></pos><stem>to</stem></mw><gra type="gra" index="3" head="4" relation="INF"/></mor-post></mor></w>
    <w>feed<mor type="mor"><mw><pos><c>v</c></pos><stem>feed</stem></mw><gra type="gra" index="4" head="2" relation="COMP"/></mor></w>
    <w>her<mor type="mor"><mw><pos><c>pro</c><s>obj</s></pos><stem>her</stem></mw><gra type="gra" index="5" head="4" relation="OBJ"/></mor></w>
    <t type="q"><mor type="mor"><mt type="q"/><gra type="gra" index="6" head="2" relation="PUNCT"/></mor></t>

  </u>
  <u who="MOT" uID="u23">
    <w>here<mor type="mor"><mw><pos><c>adv</c></pos><stem>here</stem></mw><gra type="gra" index="1" head="0" relation="INCROOT"/></mor></w>
    <t type="p"><mor type="mor"><mt type="p"/><gra type="gra" index="2" head="1" relation="PUNCT"/></mor></t>
    <media
      start="73.706"
      end="84.767"
      unit="s"
    />
  </u>
  <u who="MOT" uID="u24">
    <w>I'll<mor type="mor"><mw><pos><c>pro</c><s>sub</s></pos><stem>I</stem></mw><gra type="gra" index="1" head="3" relation="SUBJ"/><mor-post><mw><pos><c>mod</c></pos><stem>will</stem></mw><gra type="gra" index="2" head="3" relation="AUX"/></mor-post></mor></w>
    <w>hold<mor type="mor"><mw><pos><c>v</c></pos><stem>hold</stem></mw><gra type="gra" index="3" head="0" relation="ROOT"/></mor></w>
    <w>her<mor type="mor"><mw><pos><c>pro</c><s>obj</s></pos><stem>her</stem></mw><gra type="gra" index="4" head="3" relation="OBJ"/></mor></w>
    <t type="p"><mor type="mor"><mt type="p"/><gra type="gra" index="5" head="3" relation="PUNCT"/></mor></t>
    <media
      start="84.767"
      end="86.536"
      unit="s"
    />
  </u>
  <u who="MOT" uID="u25">
    <w>here<mor type="mor"><mw><pos><c>adv</c></pos><stem>here</stem></mw><gra type="gra" index="1" head="3" relation="JCT"/></mor></w>
    <w>you<mor type="mor"><mw><pos><c>pro</c><s>per</s></pos><stem>you</stem></mw><gra type="gra" index="2" head="3" relation="SUBJ"/></mor></w>
    <w>use<mor type="mor"><mw><pos><c>v</c></pos><stem>use</stem></mw><gra type="gra" index="3" head="7" relation="CJCT"/></mor></w>
    <w>this<mor type="mor"><mw><pos><c>det</c><s>dem</s></pos><stem>this</stem></mw><gra type="gra" index="4" head="5" relation="DET"/></mor></w>
    <w>spoon<mor type="mor"><mw><pos><c>n</c></pos><stem>spoon</stem></mw><gra type="gra" index="5" head="3" relation="OBJ"/></mor></w>
    <w>I<mor type="mor"><mw><pos><c>pro</c><s>sub</s></pos><stem>I</stem></mw><gra type="gra" index="6" head="7" relation="SUBJ"/></mor></w>
    <w>think<mor type="mor"><mw><pos><c>v</c></pos><stem>think</stem></mw><gra type="gra" index="7" head="0" relation="ROOT"/></mor></w>
    <w>this<mor type="mor"><mw><pos><c>det</c><s>dem</s></pos><stem>this</stem></mw><gra type="gra" index="8" head="9" relation="DET"/></mor></w>
    <w>spoon<mor type="mor"><mw><pos><c>n</c></pos><stem>spoon</stem></mw><gra type="gra" index="9" head="10" relation="SUBJ"/></mor></w>
    <w>is<mor type="mor"><mw><pos><c>cop</c></pos><stem>be</stem><mk type="sfxf">3S</mk></mw><gra type="gra" index="10" head="7" relation="COMP"/></mor></w>
    <w>a<mor type="mor"><mw><pos><c>det</c><s>art</s></pos><stem>a</stem></mw><gra type="gra" index="11" head="12" relation="DET"/></mor></w>
    <w>little<mor type="mor"><mw><pos><c>adj</c></pos><stem>little</stem></mw><gra type="gra" index="12" head="10" relation="PRED"/></mor></w>
    <w>more<mor type="mor"><mw><pos><c>adv</c></pos><stem>more</stem></mw><gra type="gra" index="13" head="12" relation="JCT"/></mor></w>
    <w>your<mor type="mor"><mw><pos><c>det</c><s>poss</s></pos><stem>your</stem></mw><gra type="gra" index="14" head="15" relation="DET"/></mor></w>
    <g><w>size<mor type="mor"><mw><pos><c>n</c></pos><stem>size</stem></mw><gra type="gra" index="15" head="13" relation="POBJ"/></mor></w><ga type="paralinguistics">eating noises</ga></g>
    <t type="p"><mor type="mor"><mt type="p"/><gra type="gra" index="16" head="7" relation="PUNCT"/></mor></t>
    <media
      start="86.536"
      end="91.898"
      unit="s"
    />
  </u>
  <u who="MOT" uID="u26">
    <e><action/><ga type="paralinguistics">background noise</ga></e>
    <t type="p"></t>
    <media
      start="91.898"
      end="96.678"
      unit="s"
    />
  </u>
  <u who="MOT" uID="u27">
    <g><w>mm<mor type="mor"><mw><pos><c>co</c></pos><stem>mm</stem></mw><gra type="gra" index="1" head="0" relation="INCROOT"/></mor></w><ga type="paralinguistics">background noise</ga></g>
    <t type="p"><mor type="mor"><mt type="p"/><gra type="gra" index="2" head="1" relation="PUNCT"/></mor></t>
    <media
      start="96.678"
      end="108.622"
      unit="s"
    />
  </u>
  <u who="MOT" uID="u28">
    <w>mm<mor type="mor"><mw><pos><c>co</c></pos><stem>mm</stem></mw><gra type="gra" index="1" head="0" relation="INCROOT"/></mor></w>
    <t type="p"><mor type="mor"><mt type="p"/><gra type="gra" index="2" head="1" relation="PUNCT"/></mor></t>
    <media
      start="108.622"
      end="112.839"
      unit="s"
    />
  </u>
  <u who="MOT" uID="u29">
    <w formType="interjection">numnumnum<mor type="mor"><mw><pos><c>co</c></pos><stem>numnumnum</stem></mw><gra type="gra" index="1" head="0" relation="INCROOT"/></mor></w>
    <t type="p"><mor type="mor"><mt type="p"/><gra type="gra" index="2" head="1" relation="PUNCT"/></mor></t>
    <media
      start="112.839"
      end="116.238"
      unit="s"
    />
  </u>
  <u who="MOT" uID="u30">
    <w>what<mor type="mor"><mw><pos><c>pro</c><s>int</s></pos><stem>what</stem></mw><gra type="gra" index="1" head="4" relation="SUBJ"/></mor></w>
    <w>do<mor type="mor"><mw><pos><c>mod</c></pos><stem>do</stem></mw><gra type="gra" index="2" head="4" relation="AUX"/></mor></w>
    <w>you<mor type="mor"><mw><pos><c>pro</c><s>per</s></pos><stem>you</stem></mw><gra type="gra" index="3" head="4" relation="SUBJ"/></mor></w>
    <w>wanna<mor type="mor"><mw><pos><c>v</c></pos><stem>want</stem></mw><gra type="gra" index="4" head="0" relation="ROOT"/><mor-post><mw><pos><c>inf</c></pos><stem>to</stem></mw><gra type="gra" index="5" head="6" relation="INF"/></mor-post></mor></w>
    <w>give<mor type="mor"><mw><pos><c>v</c></pos><stem>give</stem></mw><gra type="gra" index="6" head="4" relation="COMP"/></mor></w>
    <w>the<mor type="mor"><mw><pos><c>det</c><s>art</s></pos><stem>the</stem></mw><gra type="gra" index="7" head="8" relation="DET"/></mor></w>
    <w>baby<mor type="mor"><mw><pos><c>n</c></pos><stem>baby</stem></mw><gra type="gra" index="8" head="6" relation="OBJ"/></mor></w>
    <t type="q"><mor type="mor"><mt type="q"/><gra type="gra" index="9" head="4" relation="PUNCT"/></mor></t>
    <media
      start="116.238"
      end="130.040"
      unit="s"
    />
  </u>
  <u who="MOT" uID="u31">
    <e><action/><ga type="paralinguistics">background noise then silence</ga></e>
    <t type="p"></t>
    <media
      start="130.040"
      end="137.303"
      unit="s"
    />
  </u>
  <u who="MOT" uID="u32">
    <w>well<mor type="mor"><mw><pos><c>co</c></pos><stem>well</stem></mw><gra type="gra" index="1" head="0" relation="INCROOT"/></mor></w>
    <t type="q"><mor type="mor"><mt type="q"/><gra type="gra" index="2" head="1" relation="PUNCT"/></mor></t>
    <media
      start="137.303"
      end="140.254"
      unit="s"
    />
  </u>
  <u who="MOT" uID="u33">
    <w>can<mor type="mor"><mw><pos><c>mod</c></pos><stem>can</stem></mw><gra type="gra" index="1" head="4" relation="AUX"/></mor></w>
    <w>the<mor type="mor"><mw><pos><c>det</c><s>art</s></pos><stem>the</stem></mw><gra type="gra" index="2" head="3" relation="DET"/></mor></w>
    <w>baby<mor type="mor"><mw><pos><c>n</c></pos><stem>baby</stem></mw><gra type="gra" index="3" head="4" relation="SUBJ"/></mor></w>
    <w>have<mor type="mor"><mw><pos><c>v</c></pos><stem>have</stem></mw><gra type="gra" index="4" head="0" relation="ROOT"/></mor></w>
    <w>a<mor type="mor"><mw><pos><c>det</c><s>art</s></pos><stem>a</stem></mw><gra type="gra" index="5" head="6" relation="DET"/></mor></w>
    <w>book<mor type="mor"><mw><pos><c>n</c></pos><stem>book</stem></mw><gra type="gra" index="6" head="4" relation="OBJ"/></mor></w>
    <t type="q"><mor type="mor"><mt type="q"/><gra type="gra" index="7" head="4" relation="PUNCT"/></mor></t>
    <media
      start="140.254"
      end="148.010"
      unit="s"
    />
  </u>
  <u who="MOT" uID="u34">
    <w>oh<mor type="mor"><mw><pos><c>co</c></pos><stem>oh</stem></mw><gra type="gra" index="1" head="3" relation="COM"/></mor></w>
    <w>the<mor type="mor"><mw><pos><c>det</c><s>art</s></pos><stem>the</stem></mw><gra type="gra" index="2" head="3" relation="DET"/></mor></w>
    <w>cookie<mor type="mor"><mw><pos><c>n</c></pos><stem>cookie</stem></mw><gra type="gra" index="3" head="0" relation="INCROOT"/></mor></w>
    <t type="q"><mor type="mor"><mt type="q"/><gra type="gra" index="4" head="3" relation="PUNCT"/></mor></t>
    <media
      start="148.010"
      end="150.956"
      unit="s"
    />
  </u>
  <u who="MOT" uID="u35">
    <e><action/><ga type="paralinguistics">silence</ga></e>
    <t type="p"></t>
    <media
      start="150.956"
      end="166.687"
      unit="s"
    />
  </u>
  <u who="MOT" uID="u36">
    <w>mm<mor type="mor"><mw><pos><c>co</c></pos><stem>mm</stem></mw><gra type="gra" index="1" head="0" relation="INCROOT"/></mor></w>
    <t type="p"><mor type="mor"><mt type="p"/><gra type="gra" index="2" head="1" relation="PUNCT"/></mor></t>
    <media
      start="166.687"
      end="169.732"
      unit="s"
    />
  </u>
  <u who="MOT" uID="u37">
    <w>uhoh<mor type="mor"><mw><pos><c>co</c></pos><stem>uhoh</stem></mw><gra type="gra" index="1" head="0" relation="INCROOT"/></mor></w>
    <t type="p"><mor type="mor"><mt type="p"/><gra type="gra" index="2" head="1" relation="PUNCT"/></mor></t>
    <media
      start="169.732"
      end="173.606"
      unit="s"
    />
  </u>
  <u who="MOT" uID="u38">
    <w>Amira<mor type="mor"><mw><pos><c>n</c><s>prop</s></pos><stem>Amira</stem></mw><gra type="gra" index="1" head="0" relation="INCROOT"/></mor></w>
    <t type="p"><mor type="mor"><mt type="p"/><gra type="gra" index="2" head="1" relation="PUNCT"/></mor></t>
    <media
      start="173.606"
      end="187.499"
      unit="s"
    />
  </u>
  <u who="MOT" uID="u39">
    <w>do<mor type="mor"><mw><pos><c>mod</c></pos><stem>do</stem></mw><gra type="gra" index="1" head="3" relation="AUX"/></mor></w>
    <w>you<mor type="mor"><mw><pos><c>pro</c><s>per</s></pos><stem>you</stem></mw><gra type="gra" index="2" head="3" relation="SUBJ"/></mor></w>
    <w>wanna<mor type="mor"><mw><pos><c>v</c></pos><stem>want</stem></mw><gra type="gra" index="3" head="0" relation="ROOT"/><mor-post><mw><pos><c>inf</c></pos><stem>to</stem></mw><gra type="gra" index="4" head="5" relation="INF"/></mor-post></mor></w>
    <w>read<mor type="mor"><mw><pos><c>v</c></pos><stem>read</stem><mk type="sfxf">ZERO</mk></mw><gra type="gra" index="5" head="3" relation="COMP"/></mor></w>
    <w>a<mor type="mor"><mw><pos><c>det</c><s>art</s></pos><stem>a</stem></mw><gra type="gra" index="6" head="7" relation="DET"/></mor></w>
    <w>book<mor type="mor"><mw><pos><c>n</c></pos><stem>book</stem></mw><gra type="gra" index="7" head="5" relation="OBJ"/></mor></w>
    <t type="q"><mor type="mor"><mt type="q"/><gra type="gra" index="8" head="3" relation="PUNCT"/></mor></t>
    <media
      start="187.499"
      end="191.657"
      unit="s"
    />
  </u>
  <u who="MOT" uID="u40">
    <w>no<mor type="mor"><mw><pos><c>co</c></pos><stem>no</stem></mw><gra type="gra" index="1" head="3" relation="COM"/></mor></w>
    <w>you<mor type="mor"><mw><pos><c>pro</c><s>per</s></pos><stem>you</stem></mw><gra type="gra" index="2" head="3" relation="SUBJ"/></mor></w>
    <w>like<mor type="mor"><mw><pos><c>v</c></pos><stem>like</stem></mw><gra type="gra" index="3" head="0" relation="ROOT"/></mor></w>
    <w>the<mor type="mor"><mw><pos><c>det</c><s>art</s></pos><stem>the</stem></mw><gra type="gra" index="4" head="5" relation="DET"/></mor></w>
    <w>food<mor type="mor"><mw><pos><c>n</c></pos><stem>food</stem></mw><gra type="gra" index="5" head="3" relation="OBJ"/></mor></w>
    <w>huh<mor type="mor"><mw><pos><c>co</c></pos><stem>huh</stem></mw><gra type="gra" index="6" head="3" relation="COM"/></mor></w>
    <t type="q"><mor type="mor"><mt type="q"/><gra type="gra" index="7" head="3" relation="PUNCT"/></mor></t>
    <media
      start="191.657"
      end="198.756"
      unit="s"
    />
  </u>
  <u who="MOT" uID="u41">
    <e><action/><ga type="paralinguistics">silence</ga></e>
    <t type="p"></t>
    <media
      start="198.756"
      end="206.940"
      unit="s"
    />
  </u>
  <u who="MOT" uID="u42">
    <e><action/><ga type="paralinguistics">eating noises</ga></e>
    <t type="p"></t>
    <media
      start="206.940"
      end="209.639"
      unit="s"
    />
  </u>
  <u who="MOT" uID="u43">
    <w>can<mor type="mor"><mw><pos><c>mod</c></pos><stem>can</stem></mw><gra type="gra" index="1" head="3" relation="AUX"/></mor></w>
    <w>you<mor type="mor"><mw><pos><c>pro</c><s>per</s></pos><stem>you</stem></mw><gra type="gra" index="2" head="3" relation="SUBJ"/></mor></w>
    <w>read<mor type="mor"><mw><pos><c>v</c></pos><stem>read</stem><mk type="sfxf">ZERO</mk></mw><gra type="gra" index="3" head="0" relation="ROOT"/></mor></w>
    <w>a<mor type="mor"><mw><pos><c>det</c><s>art</s></pos><stem>a</stem></mw><gra type="gra" index="4" head="5" relation="DET"/></mor></w>
    <g><w>book<mor type="mor"><mw><pos><c>n</c></pos><stem>book</stem></mw><gra type="gra" index="5" head="3" relation="OBJ"/></mor></w><ga type="paralinguistics">silence</ga></g>
    <t type="q"><mor type="mor"><mt type="q"/><gra type="gra" index="6" head="3" relation="PUNCT"/></mor></t>
    <media
      start="209.639"
      end="224.011"
      unit="s"
    />
  </u>
  <u who="MOT" uID="u44">
    <w>oh<mor type="mor"><mw><pos><c>co</c></pos><stem>oh</stem></mw><gra type="gra" index="1" head="3" relation="COM"/></mor></w>
    <w>you<mor type="mor"><mw><pos><c>pro</c><s>per</s></pos><stem>you</stem></mw><gra type="gra" index="2" head="3" relation="SUBJ"/></mor></w>
    <w>have<mor type="mor"><mw><pos><c>v</c></pos><stem>have</stem></mw><gra type="gra" index="3" head="0" relation="ROOT"/></mor></w>
    <w>this<mor type="mor"><mw><pos><c>pro</c><s>dem</s></pos><stem>this</stem></mw><gra type="gra" index="4" head="5" relation="DET"/></mor></w>
    <w>one<mor type="mor"><mw><pos><c>pro</c><s>indef</s></pos><stem>one</stem></mw><gra type="gra" index="5" head="3" relation="OBJ"/></mor></w>
    <t type="e"><mor type="mor"><mt type="e"/><gra type="gra" index="6" head="3" relation="PUNCT"/></mor></t>
    <media
      start="224.011"
      end="225.598"
      unit="s"
    />
  </u>
  <u who="MOT" uID="u45">
    <w>you<mor type="mor"><mw><pos><c>pro</c><s>per</s></pos><stem>you</stem></mw><gra type="gra" index="1" head="2" relation="SUBJ"/></mor></w>
    <w>have<mor type="mor"><mw><pos><c>v</c></pos><stem>have</stem></mw><gra type="gra" index="2" head="0" relation="ROOT"/></mor></w>
    <w>this<mor type="mor"><mw><pos><c>det</c><s>dem</s></pos><stem>this</stem></mw><gra type="gra" index="3" head="4" relation="DET"/></mor></w>
    <w>book<mor type="mor"><mw><pos><c>n</c></pos><stem>book</stem></mw><gra type="gra" index="4" head="2" relation="OBJ"/></mor></w>
    <t type="p"><mor type="mor"><mt type="p"/><gra type="gra" index="5" head="2" relation="PUNCT"/></mor></t>
    <media
      start="225.598"
      end="231.490"
      unit="s"
    />
  </u>
  <u who="MOT" uID="u46">
    <g><w>mm<mor type="mor"><mw><pos><c>co</c></pos><stem>mm</stem></mw><gra type="gra" index="1" head="0" relation="INCROOT"/></mor></w><ga type="paralinguistics">eating noises</ga></g>
    <t type="p"><mor type="mor"><mt type="p"/><gra type="gra" index="2" head="1" relation="PUNCT"/></mor></t>
    <media
      start="231.490"
      end="237.490"
      unit="s"
    />
  </u>
  <u who="MOT" uID="u47">
    <w>mm<mor type="mor"><mw><pos><c>co</c></pos><stem>mm</stem></mw><gra type="gra" index="1" head="0" relation="INCROOT"/></mor></w>
    <t type="p"><mor type="mor"><mt type="p"/><gra type="gra" index="2" head="1" relation="PUNCT"/></mor></t>
    <media
      start="237.490"
      end="240.175"
      unit="s"
    />
  </u>
  <u who="MOT" uID="u48">
    <w>oh<mor type="mor"><mw><pos><c>co</c></pos><stem>oh</stem></mw><gra type="gra" index="1" head="2" relation="COM"/></mor></w>
    <w>thank<mor type="mor"><mw><pos><c>v</c></pos><stem>thank</stem></mw><gra type="gra" index="2" head="0" relation="ROOT"/></mor></w>
    <w>you<mor type="mor"><mw><pos><c>pro</c><s>per</s></pos><stem>you</stem></mw><gra type="gra" index="3" head="2" relation="OBJ"/></mor></w>
    <t type="p"><mor type="mor"><mt type="p"/><gra type="gra" index="4" head="2" relation="PUNCT"/></mor></t>
    <media
      start="240.175"
      end="246.904"
      unit="s"
    />
  </u>
  <u who="MOT" uID="u49">
    <w>the<mor type="mor"><mw><pos><c>det</c><s>art</s></pos><stem>the</stem></mw><gra type="gra" index="1" head="3" relation="DET"/></mor></w>
    <w>baby<mor type="mor"><mw><pos><c>n</c></pos><stem>baby</stem></mw><gra type="gra" index="2" head="3" relation="MOD"/></mor></w>
    <w>shoes<mor type="mor"><mw><pos><c>n</c></pos><stem>shoe</stem><mk type="sfx">PL</mk></mw><gra type="gra" index="3" head="0" relation="INCROOT"/></mor></w>
    <t type="p"><mor type="mor"><mt type="p"/><gra type="gra" index="4" head="3" relation="PUNCT"/></mor></t>
    <media
      start="246.904"
      end="252.690"
      unit="s"
    />
  </u>
  <u who="MOT" uID="u50">
    <w>her<mor type="mor"><mw><pos><c>det</c><s>poss</s></pos><stem>her</stem></mw><gra type="gra" index="1" head="2" relation="DET"/></mor></w>
    <w>shoes<mor type="mor"><mw><pos><c>n</c></pos><stem>shoe</stem><mk type="sfx">PL</mk></mw><gra type="gra" index="2" head="0" relation="INCROOT"/></mor></w>
    <t type="p"><mor type="mor"><mt type="p"/><gra type="gra" index="3" head="2" relation="PUNCT"/></mor></t>
    <media
      start="252.690"
      end="258.162"
      unit="s"
    />
  </u>
  <u who="MOT" uID="u51">
    <g><w>Amira<mor type="mor"><mw><pos><c>n</c><s>prop</s></pos><stem>Amira</stem></mw><gra type="gra" index="1" head="0" relation="INCROOT"/></mor></w><ga type="paralinguistics">background noise</ga></g>
    <t type="p"><mor type="mor"><mt type="p"/><gra type="gra" index="2" head="1" relation="PUNCT"/></mor></t>
    <media
      start="258.162"
      end="275.112"
      unit="s"
    />
  </u>
  <u who="MOT" uID="u52">
    <g><w>mm<mor type="mor"><mw><pos><c>co</c></pos><stem>mm</stem></mw><gra type="gra" index="1" head="0" relation="INCROOT"/></mor></w><ga type="paralinguistics">eating noises</ga></g>
    <t type="p"><mor type="mor"><mt type="p"/><gra type="gra" index="2" head="1" relation="PUNCT"/></mor></t>
    <media
      start="275.112"
      end="281.618"
      unit="s"
    />
  </u>
  <u who="MOT" uID="u53">
    <w>Amira<mor type="mor"><mw><pos><c>n</c><s>prop</s></pos><stem>Amira</stem></mw><gra type="gra" index="1" head="4" relation="SUBJ"/></mor></w>
    <w>can<mor type="mor"><mw><pos><c>mod</c></pos><stem>can</stem></mw><gra type="gra" index="2" head="4" relation="AUX"/></mor></w>
    <w>I<mor type="mor"><mw><pos><c>pro</c><s>sub</s></pos><stem>I</stem></mw><gra type="gra" index="3" head="4" relation="SUBJ"/></mor></w>
    <w>have<mor type="mor"><mw><pos><c>v</c></pos><stem>have</stem></mw><gra type="gra" index="4" head="0" relation="ROOT"/></mor></w>
    <w>something<mor type="mor"><mw><pos><c>pro</c><s>indef</s></pos><stem>something</stem></mw><gra type="gra" index="5" head="7" relation="SUBJ"/></mor></w>
    <w>to<mor type="mor"><mw><pos><c>inf</c></pos><stem>to</stem></mw><gra type="gra" index="6" head="7" relation="INF"/></mor></w>
    <w>eat<mor type="mor"><mw><pos><c>v</c></pos><stem>eat</stem></mw><gra type="gra" index="7" head="4" relation="COMP"/></mor></w>
    <t type="q"><mor type="mor"><mt type="q"/><gra type="gra" index="8" head="4" relation="PUNCT"/></mor></t>
    <media
      start="281.618"
      end="286.536"
      unit="s"
    />
  </u>
  <u who="MOT" uID="u54">
    <w>Amira<mor type="mor"><mw><pos><c>n</c><s>prop</s></pos><stem>Amira</stem></mw><gra type="gra" index="1" head="0" relation="INCROOT"/></mor></w>
    <t type="p"><mor type="mor"><mt type="p"/><gra type="gra" index="2" head="1" relation="PUNCT"/></mor></t>
    <media
      start="286.536"
      end="293.864"
      unit="s"
    />
  </u>
  <u who="MOT" uID="u55">
    <w>come<mor type="mor"><mw><pos><c>v</c></pos><stem>come</stem></mw><gra type="gra" index="1" head="0" relation="ROOT"/></mor></w>
    <w>here<mor type="mor"><mw><pos><c>adv</c></pos><stem>here</stem></mw><gra type="gra" index="2" head="1" relation="JCT"/></mor></w>
    <t type="e"><mor type="mor"><mt type="e"/><gra type="gra" index="3" head="1" relation="PUNCT"/></mor></t>
    <media
      start="293.864"
      end="295.187"
      unit="s"
    />
  </u>
  <u who="MOT" uID="u56">
    <w>yeah<mor type="mor"><mw><pos><c>co</c></pos><stem>yeah</stem></mw><gra type="gra" index="1" head="5" relation="COM"/></mor></w>
    <w>daddy<mor type="mor"><mw><pos><c>n</c></pos><stem>daddy</stem></mw><gra type="gra" index="2" head="5" relation="SUBJ"/></mor></w>
    <w>doesn't<mor type="mor"><mw><pos><c>mod</c></pos><stem>do</stem><mk type="sfxf">3S</mk></mw><gra type="gra" index="3" head="5" relation="AUX"/><mor-post><mw><pos><c>neg</c></pos><stem>not</stem></mw><gra type="gra" index="4" head="3" relation="NEG"/></mor-post></mor></w>
    <w>want<mor type="mor"><mw><pos><c>v</c></pos><stem>want</stem></mw><gra type="gra" index="5" head="0" relation="ROOT"/></mor></w>
    <w>all<mor type="mor"><mw><pos><c>pro</c><s>indef</s></pos><stem>all</stem></mw><gra type="gra" index="6" head="5" relation="OBJ"/></mor></w>
    <w>of<mor type="mor"><mw><pos><c>prep</c></pos><stem>of</stem></mw><gra type="gra" index="7" head="6" relation="NJCT"/></mor></w>
    <w>this<mor type="mor"><mw><pos><c>pro</c><s>dem</s></pos><stem>this</stem></mw><gra type="gra" index="8" head="7" relation="POBJ"/></mor></w>
    <t type="p"><mor type="mor"><mt type="p"/><gra type="gra" index="9" head="5" relation="PUNCT"/></mor></t>
    <media
      start="295.187"
      end="301.445"
      unit="s"
    />
  </u>
  <u who="MOT" uID="u57">
    <w>here<mor type="mor"><mw><pos><c>adv</c></pos><stem>here</stem></mw><gra type="gra" index="1" head="0" relation="INCROOT"/></mor></w>
    <t type="p"><mor type="mor"><mt type="p"/><gra type="gra" index="2" head="1" relation="PUNCT"/></mor></t>
    <media
      start="301.445"
      end="303.386"
      unit="s"
    />
  </u>
  <u who="MOT" uID="u58">
    <w>thank<mor type="mor"><mw><pos><c>v</c></pos><stem>thank</stem></mw><gra type="gra" index="1" head="0" relation="ROOT"/></mor></w>
    <w>you<mor type="mor"><mw><pos><c>pro</c><s>per</s></pos><stem>you</stem></mw><gra type="gra" index="2" head="1" relation="OBJ"/></mor></w>
    <t type="p"><mor type="mor"><mt type="p"/><gra type="gra" index="3" head="1" relation="PUNCT"/></mor></t>
    <media
      start="303.386"
      end="307.203"
      unit="s"
    />
  </u>
  <u who="MOT" uID="u59">
    <w>the<mor type="mor"><mw><pos><c>det</c><s>art</s></pos><stem>the</stem></mw><gra type="gra" index="1" head="2" relation="DET"/></mor></w>
    <w>clo<p type="drawl"/>ck<mor type="mor"><mw><pos><c>n</c></pos><stem>clock</stem></mw><gra type="gra" index="2" head="0" relation="INCROOT"/></mor></w>
    <t type="p"><mor type="mor"><mt type="p"/><gra type="gra" index="3" head="2" relation="PUNCT"/></mor></t>
    <media
      start="307.203"
      end="310.293"
      unit="s"
    />
  </u>
  <u who="MOT" uID="u60">
    <w>what's<mor type="mor"><mw><pos><c>pro</c><s>int</s></pos><stem>what</stem></mw><gra type="gra" index="1" head="2" relation="SUBJ"/><mor-post><mw><pos><c>cop</c></pos><stem>be</stem><mk type="sfxf">3S</mk></mw><gra type="gra" index="2" head="0" relation="ROOT"/></mor-post></mor></w>
    <w>that<mor type="mor"><mw><pos><c>pro</c><s>dem</s></pos><stem>that</stem></mw><gra type="gra" index="3" head="2" relation="PRED"/></mor></w>
    <t type="q"><mor type="mor"><mt type="q"/><gra type="gra" index="4" head="2" relation="PUNCT"/></mor></t>
    <media
      start="310.293"
      end="311.588"
      unit="s"
    />
  </u>
  <u who="MOT" uID="u61">
    <w>the<mor type="mor"><mw><pos><c>det</c><s>art</s></pos><stem>the</stem></mw><gra type="gra" index="1" head="2" relation="DET"/></mor></w>
    <w>clo<p type="drawl"/>ck<mor type="mor"><mw><pos><c>n</c></pos><stem>clock</stem></mw><gra type="gra" index="2" head="0" relation="INCROOT"/></mor></w>
    <t type="p"><mor type="mor"><mt type="p"/><gra type="gra" index="3" head="2" relation="PUNCT"/></mor></t>
    <media
      start="311.588"
      end="314.153"
      unit="s"
    />
  </u>
  <u who="MOT" uID="u62">
    <w>thank<mor type="mor"><mw><pos><c>v</c></pos><stem>thank</stem></mw><gra type="gra" index="1" head="0" relation="ROOT"/></mor></w>
    <w>you<mor type="mor"><mw><pos><c>pro</c><s>per</s></pos><stem>you</stem></mw><gra type="gra" index="2" head="1" relation="OBJ"/></mor></w>
    <t type="p"><mor type="mor"><mt type="p"/><gra type="gra" index="3" head="1" relation="PUNCT"/></mor></t>
    <media
      start="314.153"
      end="317.253"
      unit="s"
    />
  </u>
  <u who="MOT" uID="u63">
    <g><w>ooh<mor type="mor"><mw><pos><c>v</c></pos><stem>ooh</stem></mw><gra type="gra" index="1" head="0" relation="ROOT"/></mor></w><ga type="paralinguistics">background noise and silence</ga></g>
    <t type="p"><mor type="mor"><mt type="p"/><gra type="gra" index="2" head="1" relation="PUNCT"/></mor></t>
    <media
      start="317.253"
      end="328.145"
      unit="s"
    />
  </u>
  <u who="MOT" uID="u64">
    <w>ooh<mor type="mor"><mw><pos><c>v</c></pos><stem>ooh</stem></mw><gra type="gra" index="1" head="0" relation="ROOT"/></mor></w>
    <t type="p"><mor type="mor"><mt type="p"/><gra type="gra" index="2" head="1" relation="PUNCT"/></mor></t>
    <media
      start="328.145"
      end="331.746"
      unit="s"
    />
  </u>
  <u who="MOT" uID="u65">
    <w>where's<mor type="mor"><mw><pos><c>pro</c><s>int</s></pos><stem>where</stem></mw><gra type="gra" index="1" head="2" relation="LINK"/><mor-post><mw><pos><c>cop</c></pos><stem>be</stem><mk type="sfxf">3S</mk></mw><gra type="gra" index="2" head="0" relation="ROOT"/></mor-post></mor></w>
    <w>the<mor type="mor"><mw><pos><c>det</c><s>art</s></pos><stem>the</stem></mw><gra type="gra" index="3" head="4" relation="DET"/></mor></w>
    <w>dog<mor type="mor"><mw><pos><c>n</c></pos><stem>dog</stem></mw><gra type="gra" index="4" head="2" relation="PRED"/></mor></w>
    <t type="q"><mor type="mor"><mt type="q"/><gra type="gra" index="5" head="2" relation="PUNCT"/></mor></t>
    <media
      start="331.746"
      end="337.152"
      unit="s"
    />
  </u>
  <u who="MOT" uID="u66">
    <w>Amira<mor type="mor"><mw><pos><c>n</c><s>prop</s></pos><stem>Amira</stem></mw><gra type="gra" index="1" head="3" relation="SUBJ"/></mor></w>
    <w>where's<mor type="mor"><mw><pos><c>pro</c><s>int</s></pos><stem>where</stem></mw><gra type="gra" index="2" head="3" relation="JCT"/><mor-post><mw><pos><c>cop</c></pos><stem>be</stem><mk type="sfxf">3S</mk></mw><gra type="gra" index="3" head="0" relation="ROOT"/></mor-post></mor></w>
    <w>the<mor type="mor"><mw><pos><c>det</c><s>art</s></pos><stem>the</stem></mw><gra type="gra" index="4" head="5" relation="DET"/></mor></w>
    <w>dog<mor type="mor"><mw><pos><c>n</c></pos><stem>dog</stem></mw><gra type="gra" index="5" head="3" relation="PRED"/></mor></w>
    <t type="q"><mor type="mor"><mt type="q"/><gra type="gra" index="6" head="3" relation="PUNCT"/></mor></t>
    <media
      start="337.152"
      end="339.628"
      unit="s"
    />
  </u>
  <u who="MOT" uID="u67">
    <w>oh<mor type="mor"><mw><pos><c>co</c></pos><stem>oh</stem></mw><gra type="gra" index="1" head="3" relation="COM"/></mor></w>
    <w>that's<mor type="mor"><mw><pos><c>pro</c><s>dem</s></pos><stem>that</stem></mw><gra type="gra" index="2" head="3" relation="SUBJ"/><mor-post><mw><pos><c>cop</c></pos><stem>be</stem><mk type="sfxf">3S</mk></mw><gra type="gra" index="3" head="0" relation="ROOT"/></mor-post></mor></w>
    <g><w>a</w>
    <w>horse</w><k type="retracing with correction"/></g>
    <w>a<mor type="mor"><mw><pos><c>det</c><s>art</s></pos><stem>a</stem></mw><gra type="gra" index="4" head="5" relation="DET"/></mor></w>
    <w>zebra<mor type="mor"><mw><pos><c>n</c></pos><stem>zebra</stem></mw><gra type="gra" index="5" head="3" relation="PRED"/></mor></w>
    <t type="p"><mor type="mor"><mt type="p"/><gra type="gra" index="6" head="3" relation="PUNCT"/></mor></t>
    <media
      start="339.628"
      end="345.440"
      unit="s"
    />
  </u>
  <u who="MOT" uID="u68">
    <e><action/><ga type="paralinguistics">noise of horse trotting</ga></e>
    <t type="p"></t>
    <media
      start="345.440"
      end="349.944"
      unit="s"
    />
  </u>
  <u who="MOT" uID="u69">
    <w>thank<mor type="mor"><mw><pos><c>v</c></pos><stem>thank</stem></mw><gra type="gra" index="1" head="0" relation="ROOT"/></mor></w>
    <g><w>you<mor type="mor"><mw><pos><c>pro</c><s>per</s></pos><stem>you</stem></mw><gra type="gra" index="2" head="1" relation="OBJ"/></mor></w><ga type="paralinguistics">kissing noises</ga></g>
    <t type="p"><mor type="mor"><mt type="p"/><gra type="gra" index="3" head="1" relation="PUNCT"/></mor></t>
    <media
      start="349.944"
      end="357.357"
      unit="s"
    />
  </u>
  <u who="MOT" uID="u70">
    <e><action/><ga type="paralinguistics">noise</ga></e>
    <t type="p"></t>
    <media
      start="357.357"
      end="363.724"
      unit="s"
    />
  </u>
  <u who="MOT" uID="u71">
    <w>what's<mor type="mor"><mw><pos><c>pro</c><s>int</s></pos><stem>what</stem></mw><gra type="gra" index="1" head="2" relation="SUBJ"/><mor-post><mw><pos><c>cop</c></pos><stem>be</stem><mk type="sfxf">3S</mk></mw><gra type="gra" index="2" head="0" relation="ROOT"/></mor-post></mor></w>
    <g><w>that<mor type="mor"><mw><pos><c>pro</c><s>dem</s></pos><stem>that</stem></mw><gra type="gra" index="3" head="2" relation="PRED"/></mor></w><ga type="paralinguistics">silence</ga></g>
    <t type="q"><mor type="mor"><mt type="q"/><gra type="gra" index="4" head="2" relation="PUNCT"/></mor></t>
    <media
      start="363.724"
      end="384.940"
      unit="s"
    />
  </u>
  <u who="MOT" uID="u72">
    <w>mm<mor type="mor"><mw><pos><c>co</c></pos><stem>mm</stem></mw><gra type="gra" index="1" head="3" relation="COM"/></mor></w>
    <w>the<mor type="mor"><mw><pos><c>det</c><s>art</s></pos><stem>the</stem></mw><gra type="gra" index="2" head="3" relation="DET"/></mor></w>
    <w>bee<mor type="mor"><mw><pos><c>n</c></pos><stem>bee</stem></mw><gra type="gra" index="3" head="0" relation="INCROOT"/></mor></w>
    <t type="q"><mor type="mor"><mt type="q"/><gra type="gra" index="4" head="3" relation="PUNCT"/></mor></t>

  </u>
  <u who="MOT" uID="u73">
    <w formType="onomatopoeia">bzzz<mor type="mor"><mw><pos><c>on</c></pos><stem>bzzz</stem></mw><gra type="gra" index="1" head="0" relation="INCROOT"/></mor></w>
    <t type="p"><mor type="mor"><mt type="p"/><gra type="gra" index="2" head="1" relation="PUNCT"/></mor></t>
    <media
      start="384.940"
      end="394.082"
      unit="s"
    />
  </u>
  <u who="MOT" uID="u74">
    <w>oh<mor type="mor"><mw><pos><c>co</c></pos><stem>oh</stem></mw><gra type="gra" index="1" head="3" relation="COM"/></mor></w>
    <w>the<mor type="mor"><mw><pos><c>det</c><s>art</s></pos><stem>the</stem></mw><gra type="gra" index="2" head="3" relation="DET"/></mor></w>
    <w>rooster<mor type="mor"><mw><pos><c>n</c></pos><stem>rooster</stem></mw><gra type="gra" index="3" head="0" relation="INCROOT"/></mor></w>
    <t type="q"><mor type="mor"><mt type="q"/><gra type="gra" index="4" head="3" relation="PUNCT"/></mor></t>
    <media
      start="394.082"
      end="403.265"
      unit="s"
    />
  </u>
  <u who="MOT" uID="u75">
    <w>you<mor type="mor"><mw><pos><c>pro</c><s>per</s></pos><stem>you</stem></mw><gra type="gra" index="1" head="2" relation="SUBJ"/></mor></w>
    <w>giving<mor type="mor"><mw><pos><c>part</c></pos><stem>give</stem><mk type="sfx">PRESP</mk></mw><gra type="gra" index="2" head="0" relation="ROOT"/></mor></w>
    <w>the<mor type="mor"><mw><pos><c>det</c><s>art</s></pos><stem>the</stem></mw><gra type="gra" index="3" head="4" relation="DET"/></mor></w>
    <w>baby<mor type="mor"><mw><pos><c>n</c></pos><stem>baby</stem></mw><gra type="gra" index="4" head="2" relation="OBJ"/></mor></w>
    <w>a<mor type="mor"><mw><pos><c>det</c><s>art</s></pos><stem>a</stem></mw><gra type="gra" index="5" head="6" relation="DET"/></mor></w>
    <w>bottle<mor type="mor"><mw><pos><c>n</c></pos><stem>bottle</stem></mw><gra type="gra" index="6" head="4" relation="OBJ"/></mor></w>
    <t type="q"><mor type="mor"><mt type="q"/><gra type="gra" index="7" head="2" relation="PUNCT"/></mor></t>
    <media
      start="403.265"
      end="425.729"
      unit="s"
    />
  </u>
  <u who="MOT" uID="u76">
    <w>can<mor type="mor"><mw><pos><c>mod</c></pos><stem>can</stem></mw><gra type="gra" index="1" head="4" relation="AUX"/></mor></w>
    <w>the<mor type="mor"><mw><pos><c>det</c><s>art</s></pos><stem>the</stem></mw><gra type="gra" index="2" head="3" relation="DET"/></mor></w>
    <w>baby<mor type="mor"><mw><pos><c>n</c></pos><stem>baby</stem></mw><gra type="gra" index="3" head="4" relation="SUBJ"/></mor></w>
    <w>have<mor type="mor"><mw><pos><c>v</c></pos><stem>have</stem></mw><gra type="gra" index="4" head="0" relation="ROOT"/></mor></w>
    <w>a<mor type="mor"><mw><pos><c>det</c><s>art</s></pos><stem>a</stem></mw><gra type="gra" index="5" head="6" relation="DET"/></mor></w>
    <g><w>cookie<mor type="mor"><mw><pos><c>n</c></pos><stem>cookie</stem></mw><gra type="gra" index="6" head="4" relation="OBJ"/></mor></w><ga type="paralinguistics">background noise</ga></g>
    <t type="q"><mor type="mor"><mt type="q"/><gra type="gra" index="7" head="4" relation="PUNCT"/></mor></t>
    <media
      start="425.729"
      end="430.652"
      unit="s"
    />
  </u>
  <u who="MOT" uID="u77">
    <w>mm<mor type="mor"><mw><pos><c>co</c></pos><stem>mm</stem></mw><gra type="gra" index="1" head="2" relation="COM"/></mor></w>
    <w>num_num<mor type="mor"><mw><pos><c>on</c></pos><stem>num</stem><mk type="sfxf">DUP</mk></mw><gra type="gra" index="2" head="0" relation="INCROOT"/></mor></w>
    <t type="p"><mor type="mor"><mt type="p"/><gra type="gra" index="3" head="2" relation="PUNCT"/></mor></t>
    <media
      start="430.652"
      end="435.107"
      unit="s"
    />
  </u>
  <u who="MOT" uID="u78">
    <w>mm<mor type="mor"><mw><pos><c>co</c></pos><stem>mm</stem></mw><gra type="gra" index="1" head="2" relation="COM"/></mor></w>
    <w>num_num<mor type="mor"><mw><pos><c>on</c></pos><stem>num</stem><mk type="sfxf">DUP</mk></mw><gra type="gra" index="2" head="0" relation="INCROOT"/></mor></w>
    <t type="p"><mor type="mor"><mt type="p"/><gra type="gra" index="3" head="2" relation="PUNCT"/></mor></t>
    <media
      start="435.107"
      end="439.495"
      unit="s"
    />
  </u>
  <u who="MOT" uID="u79">
    <w>mm<mor type="mor"><mw><pos><c>co</c></pos><stem>mm</stem></mw><gra type="gra" index="1" head="0" relation="INCROOT"/></mor></w>
    <t type="p"><mor type="mor"><mt type="p"/><gra type="gra" index="2" head="1" relation="PUNCT"/></mor></t>
    <media
      start="439.495"
      end="443.463"
      unit="s"
    />
  </u>
  <u who="MOT" uID="u80">
    <g><w>mm<mor type="mor"><mw><pos><c>co</c></pos><stem>mm</stem></mw><gra type="gra" index="1" head="0" relation="INCROOT"/></mor></w><ga type="paralinguistics">eating noises</ga></g>
    <t type="p"><mor type="mor"><mt type="p"/><gra type="gra" index="2" head="1" relation="PUNCT"/></mor></t>
    <media
      start="443.463"
      end="452.344"
      unit="s"
    />
  </u>
  <u who="MOT" uID="u81">
    <w>can<mor type="mor"><mw><pos><c>mod</c></pos><stem>can</stem></mw><gra type="gra" index="1" head="3" relation="AUX"/></mor></w>
    <w>she<mor type="mor"><mw><pos><c>pro</c><s>sub</s></pos><stem>she</stem></mw><gra type="gra" index="2" head="3" relation="SUBJ"/></mor></w>
    <w>have<mor type="mor"><mw><pos><c>v</c></pos><stem>have</stem></mw><gra type="gra" index="3" head="0" relation="ROOT"/></mor></w>
    <w>a<mor type="mor"><mw><pos><c>det</c><s>art</s></pos><stem>a</stem></mw><gra type="gra" index="4" head="5" relation="DET"/></mor></w>
    <w>cookie<mor type="mor"><mw><pos><c>n</c></pos><stem>cookie</stem></mw><gra type="gra" index="5" head="3" relation="OBJ"/></mor></w>
    <t type="q"><mor type="mor"><mt type="q"/><gra type="gra" index="6" head="3" relation="PUNCT"/></mor></t>
    <media
      start="452.344"
      end="454.679"
      unit="s"
    />
  </u>
  <u who="MOT" uID="u82">
    <w>the<mor type="mor"><mw><pos><c>det</c><s>art</s></pos><stem>the</stem></mw><gra type="gra" index="1" head="2" relation="DET"/></mor></w>
    <w>baby<mor type="mor"><mw><pos><c>n</c></pos><stem>baby</stem></mw><gra type="gra" index="2" head="3" relation="SUBJ"/></mor></w>
    <w>wants<mor type="mor"><mw><pos><c>v</c></pos><stem>want</stem><mk type="sfx">3S</mk></mw><gra type="gra" index="3" head="0" relation="ROOT"/></mor></w>
    <w>a<mor type="mor"><mw><pos><c>det</c><s>art</s></pos><stem>a</stem></mw><gra type="gra" index="4" head="5" relation="DET"/></mor></w>
    <w>cookie<mor type="mor"><mw><pos><c>n</c></pos><stem>cookie</stem></mw><gra type="gra" index="5" head="3" relation="OBJ"/></mor></w>
    <t type="p"><mor type="mor"><mt type="p"/><gra type="gra" index="6" head="3" relation="PUNCT"/></mor></t>
    <media
      start="454.679"
      end="459.334"
      unit="s"
    />
  </u>
  <u who="MOT" uID="u83">
    <e><action/><ga type="paralinguistics">silence</ga></e>
    <t type="p"></t>
    <media
      start="459.334"
      end="475.238"
      unit="s"
    />
  </u>
  <u who="MOT" uID="u84">
    <w>mm<mor type="mor"><mw><pos><c>co</c></pos><stem>mm</stem></mw><gra type="gra" index="1" head="0" relation="INCROOT"/></mor></w>
    <t type="p"><mor type="mor"><mt type="p"/><gra type="gra" index="2" head="1" relation="PUNCT"/></mor></t>
    <media
      start="475.238"
      end="478.536"
      unit="s"
    />
  </u>
  <u who="MOT" uID="u85">
    <w>spaghetti<mor type="mor"><mw><pos><c>n</c></pos><stem>spaghetti</stem></mw><gra type="gra" index="1" head="0" relation="INCROOT"/></mor></w>
    <t type="p"><mor type="mor"><mt type="p"/><gra type="gra" index="2" head="1" relation="PUNCT"/></mor></t>
    <media
      start="478.536"
      end="489.986"
      unit="s"
    />
  </u>
  <u who="MOT" uID="u86">
    <w>oh<mor type="mor"><mw><pos><c>co</c></pos><stem>oh</stem></mw><gra type="gra" index="1" head="3" relation="COM"/></mor></w>
    <w>some<mor type="mor"><mw><pos><c>qn</c></pos><stem>some</stem></mw><gra type="gra" index="2" head="3" relation="QUANT"/></mor></w>
    <w>cheese<mor type="mor"><mw><pos><c>n</c></pos><stem>cheese</stem></mw><gra type="gra" index="3" head="0" relation="INCROOT"/></mor></w>
    <t type="p"><mor type="mor"><mt type="p"/><gra type="gra" index="4" head="3" relation="PUNCT"/></mor></t>
    <media
      start="489.986"
      end="497.832"
      unit="s"
    />
  </u>
  <u who="MOT" uID="u87">
    <g><w>mm<mor type="mor"><mw><pos><c>co</c></pos><stem>mm</stem></mw><gra type="gra" index="1" head="0" relation="INCROOT"/></mor></w><ga type="paralinguistics">eating noises</ga></g>
    <t type="p"><mor type="mor"><mt type="p"/><gra type="gra" index="2" head="1" relation="PUNCT"/></mor></t>
    <media
      start="497.832"
      end="517.100"
      unit="s"
    />
  </u>
  <u who="MOT" uID="u88">
    <w>thank<mor type="mor"><mw><pos><c>v</c></pos><stem>thank</stem></mw><gra type="gra" index="1" head="0" relation="ROOT"/></mor></w>
    <w>you<mor type="mor"><mw><pos><c>pro</c><s>per</s></pos><stem>you</stem></mw><gra type="gra" index="2" head="1" relation="OBJ"/></mor></w>
    <t type="p"><mor type="mor"><mt type="p"/><gra type="gra" index="3" head="1" relation="PUNCT"/></mor></t>

  </u>
  <u who="MOT" uID="u89">
    <w>here<mor type="mor"><mw><pos><c>adv</c></pos><stem>here</stem></mw><gra type="gra" index="1" head="2" relation="JCT"/></mor></w>
    <w>let's<mor type="mor"><mw><pos><c>v</c></pos><stem>let</stem></mw><gra type="gra" index="2" head="0" relation="ROOT"/><mor-post><mw><pos><c>pro</c><s>obj</s></pos><stem>us</stem></mw><gra type="gra" index="3" head="4" relation="SUBJ"/></mor-post></mor></w>
    <w>fix<mor type="mor"><mw><pos><c>v</c></pos><stem>fix</stem></mw><gra type="gra" index="4" head="2" relation="COMP"/></mor></w>
    <w>this<mor type="mor"><mw><pos><c>det</c><s>dem</s></pos><stem>this</stem></mw><gra type="gra" index="5" head="6" relation="DET"/></mor></w>
    <w>baby<mor type="mor"><mw><pos><c>n</c></pos><stem>baby</stem></mw><gra type="gra" index="6" head="2" relation="OBJ"/></mor></w>
    <w>of<mor type="mor"><mw><pos><c>prep</c></pos><stem>of</stem></mw><gra type="gra" index="7" head="6" relation="NJCT"/></mor></w>
    <w>yours<mor type="mor"><mw><pos><c>pro</c><s>poss</s></pos><stem>yours</stem></mw><gra type="gra" index="8" head="7" relation="POBJ"/></mor></w>
    <t type="p"><mor type="mor"><mt type="p"/><gra type="gra" index="9" head="2" relation="PUNCT"/></mor></t>
    <media
      start="517.100"
      end="526.703"
      unit="s"
    />
  </u>
  <u who="MOT" uID="u90">
    <w>mm<mor type="mor"><mw><pos><c>co</c></pos><stem>mm</stem></mw><gra type="gra" index="1" head="2" relation="COM"/></mor></w>
    <g><w>mm<mor type="mor"><mw><pos><c>co</c></pos><stem>mm</stem></mw><gra type="gra" index="2" head="0" relation="INCROOT"/></mor></w><ga type="paralinguistics">background noise</ga></g>
    <t type="p"><mor type="mor"><mt type="p"/><gra type="gra" index="3" head="2" relation="PUNCT"/></mor></t>
    <media
      start="526.703"
      end="536.557"
      unit="s"
    />
  </u>
  <u who="MOT" uID="u91">
    <w>where's<mor type="mor"><mw><pos><c>pro</c><s>int</s></pos><stem>where</stem></mw><gra type="gra" index="1" head="2" relation="SUBJ"/><mor-post><mw><pos><c>cop</c></pos><stem>be</stem><mk type="sfxf">3S</mk></mw><gra type="gra" index="2" head="0" relation="ROOT"/></mor-post></mor></w>
    <w>the<mor type="mor"><mw><pos><c>det</c><s>art</s></pos><stem>the</stem></mw><gra type="gra" index="3" head="5" relation="DET"/></mor></w>
    <w>baby's<mor type="mor"><mw><pos><c>adj</c></pos><stem>baby</stem><mk type="sfxf">dn</mk><mk type="sfx">POSS</mk></mw><gra type="gra" index="4" head="5" relation="MOD"/></mor></w>
    <w>nose<mor type="mor"><mw><pos><c>n</c></pos><stem>nose</stem></mw><gra type="gra" index="5" head="2" relation="PRED"/></mor></w>
    <t type="q"><mor type="mor"><mt type="q"/><gra type="gra" index="6" head="2" relation="PUNCT"/></mor></t>
    <media
      start="536.557"
      end="538.109"
      unit="s"
    />
  </u>
  <u who="MOT" uID="u92">
    <w>where's<mor type="mor"><mw><pos><c>pro</c><s>int</s></pos><stem>where</stem></mw><gra type="gra" index="1" head="2" relation="LINK"/><mor-post><mw><pos><c>cop</c></pos><stem>be</stem><mk type="sfxf">3S</mk></mw><gra type="gra" index="2" head="0" relation="ROOT"/></mor-post></mor></w>
    <w>her<mor type="mor"><mw><pos><c>det</c><s>poss</s></pos><stem>her</stem></mw><gra type="gra" index="3" head="4" relation="DET"/></mor></w>
    <w>nose<mor type="mor"><mw><pos><c>n</c></pos><stem>nose</stem></mw><gra type="gra" index="4" head="2" relation="PRED"/></mor></w>
    <w>Amira<mor type="mor"><mw><pos><c>n</c><s>prop</s></pos><stem>Amira</stem></mw><gra type="gra" index="5" head="4" relation="APP"/></mor></w>
    <t type="q"><mor type="mor"><mt type="q"/><gra type="gra" index="6" head="2" relation="PUNCT"/></mor></t>
    <media
      start="538.109"
      end="540.930"
      unit="s"
    />
  </u>
  <u who="MOT" uID="u93">
    <w>where's<mor type="mor"><mw><pos><c>pro</c><s>int</s></pos><stem>where</stem></mw><gra type="gra" index="1" head="2" relation="SUBJ"/><mor-post><mw><pos><c>cop</c></pos><stem>be</stem><mk type="sfxf">3S</mk></mw><gra type="gra" index="2" head="0" relation="ROOT"/></mor-post></mor></w>
    <w>her<mor type="mor"><mw><pos><c>det</c><s>poss</s></pos><stem>her</stem></mw><gra type="gra" index="3" head="4" relation="DET"/></mor></w>
    <w>nose<mor type="mor"><mw><pos><c>n</c></pos><stem>nose</stem></mw><gra type="gra" index="4" head="2" relation="PRED"/></mor></w>
    <t type="q"><mor type="mor"><mt type="q"/><gra type="gra" index="5" head="2" relation="PUNCT"/></mor></t>
    <media
      start="540.930"
      end="543.127"
      unit="s"
    />
  </u>
  <u who="MOT" uID="u94">
    <w>look<mor type="mor"><mw><pos><c>co</c></pos><stem>look</stem></mw><gra type="gra" index="1" head="0" relation="INCROOT"/></mor></w>
    <t type="p"><mor type="mor"><mt type="p"/><gra type="gra" index="2" head="1" relation="PUNCT"/></mor></t>
    <media
      start="543.127"
      end="545.304"
      unit="s"
    />
  </u>
  <u who="MOT" uID="u95">
    <w>where's<mor type="mor"><mw><pos><c>pro</c><s>int</s></pos><stem>where</stem></mw><gra type="gra" index="1" head="2" relation="SUBJ"/><mor-post><mw><pos><c>cop</c></pos><stem>be</stem><mk type="sfxf">3S</mk></mw><gra type="gra" index="2" head="0" relation="ROOT"/></mor-post></mor></w>
    <w>the<mor type="mor"><mw><pos><c>det</c><s>art</s></pos><stem>the</stem></mw><gra type="gra" index="3" head="5" relation="DET"/></mor></w>
    <w>baby's<mor type="mor"><mw><pos><c>adj</c></pos><stem>baby</stem><mk type="sfxf">dn</mk><mk type="sfx">POSS</mk></mw><gra type="gra" index="4" head="5" relation="MOD"/></mor></w>
    <w>nose<mor type="mor"><mw><pos><c>n</c></pos><stem>nose</stem></mw><gra type="gra" index="5" head="2" relation="PRED"/></mor></w>
    <t type="q"><mor type="mor"><mt type="q"/><gra type="gra" index="6" head="2" relation="PUNCT"/></mor></t>
    <media
      start="545.304"
      end="547.659"
      unit="s"
    />
  </u>
  <u who="MOT" uID="u96">
    <w>here<mor type="mor"><mw><pos><c>adv</c></pos><stem>here</stem></mw><gra type="gra" index="1" head="2" relation="JCT"/></mor></w>
    <w>wanna<mor type="mor"><mw><pos><c>v</c></pos><stem>want</stem></mw><gra type="gra" index="2" head="0" relation="ROOT"/><mor-post><mw><pos><c>inf</c></pos><stem>to</stem></mw><gra type="gra" index="3" head="4" relation="INF"/></mor-post></mor></w>
    <w>do<mor type="mor"><mw><pos><c>v</c></pos><stem>do</stem></mw><gra type="gra" index="4" head="2" relation="COMP"/></mor></w>
    <w>it<mor type="mor"><mw><pos><c>pro</c><s>per</s></pos><stem>it</stem></mw><gra type="gra" index="5" head="4" relation="OBJ"/></mor></w>
    <t type="q"><mor type="mor"><mt type="q"/><gra type="gra" index="6" head="2" relation="PUNCT"/></mor></t>
    <media
      start="547.659"
      end="549.065"
      unit="s"
    />
  </u>
  <u who="MOT" uID="u97">
    <w>mm<mor type="mor"><mw><pos><c>co</c></pos><stem>mm</stem></mw><gra type="gra" index="1" head="2" relation="COM"/></mor></w>
    <w>thank<mor type="mor"><mw><pos><c>v</c></pos><stem>thank</stem></mw><gra type="gra" index="2" head="0" relation="ROOT"/></mor></w>
    <g><w>you<mor type="mor"><mw><pos><c>pro</c><s>per</s></pos><stem>you</stem></mw><gra type="gra" index="3" head="2" relation="OBJ"/></mor></w><ga type="paralinguistics">background noise</ga></g>
    <t type="p"><mor type="mor"><mt type="p"/><gra type="gra" index="4" head="2" relation="PUNCT"/></mor></t>
    <media
      start="549.065"
      end="573.734"
      unit="s"
    />
  </u>
  <u who="MOT" uID="u98">
    <w>you<mor type="mor"><mw><pos><c>pro</c><s>per</s></pos><stem>you</stem></mw><gra type="gra" index="1" head="2" relation="SUBJ"/></mor></w>
    <w>gonna<mor type="mor"><mw><pos><c>part</c></pos><stem>go</stem><mk type="sfx">PRESP</mk></mw><gra type="gra" index="2" head="0" relation="ROOT"/><mor-post><mw><pos><c>inf</c></pos><stem>to</stem></mw><gra type="gra" index="3" head="4" relation="INF"/></mor-post></mor></w>
    <w>feed<mor type="mor"><mw><pos><c>v</c></pos><stem>feed</stem></mw><gra type="gra" index="4" head="2" relation="COMP"/></mor></w>
    <w>the<mor type="mor"><mw><pos><c>det</c><s>art</s></pos><stem>the</stem></mw><gra type="gra" index="5" head="6" relation="DET"/></mor></w>
    <w>baby<mor type="mor"><mw><pos><c>n</c></pos><stem>baby</stem></mw><gra type="gra" index="6" head="4" relation="OBJ"/></mor></w>
    <w>or<mor type="mor"><mw><pos><c>coord</c></pos><stem>or</stem></mw><gra type="gra" index="7" head="2" relation="CONJ"/></mor></w>
    <w>is<mor type="mor"><mw><pos><c>cop</c></pos><stem>be</stem><mk type="sfxf">3S</mk></mw><gra type="gra" index="8" head="7" relation="COORD"/></mor></w>
    <w>that<mor type="mor"><mw><pos><c>pro</c><s>dem</s></pos><stem>that</stem></mw><gra type="gra" index="9" head="8" relation="PRED"/></mor></w>
    <w>for<mor type="mor"><mw><pos><c>prep</c></pos><stem>for</stem></mw><gra type="gra" index="10" head="9" relation="JCT"/></mor></w>
    <g><w>you<mor type="mor"><mw><pos><c>pro</c><s>per</s></pos><stem>you</stem></mw><gra type="gra" index="11" head="10" relation="POBJ"/></mor></w><ga type="paralinguistics">sighs</ga></g>
    <t type="q"><mor type="mor"><mt type="q"/><gra type="gra" index="12" head="2" relation="PUNCT"/></mor></t>
    <media
      start="573.734"
      end="588.225"
      unit="s"
    />
  </u>
  <u who="MOT" uID="u99">
    <g><w>mm<mor type="mor"><mw><pos><c>co</c></pos><stem>mm</stem></mw><gra type="gra" index="1" head="0" relation="INCROOT"/></mor></w><ga type="paralinguistics">eating noises</ga></g>
    <t type="p"><mor type="mor"><mt type="p"/><gra type="gra" index="2" head="1" relation="PUNCT"/></mor></t>
    <media
      start="588.225"
      end="593.027"
      unit="s"
    />
  </u>
  <u who="MOT" uID="u100">
    <w>thank<mor type="mor"><mw><pos><c>v</c></pos><stem>thank</stem></mw><gra type="gra" index="1" head="0" relation="ROOT"/></mor></w>
    <g><w>you<mor type="mor"><mw><pos><c>pro</c><s>per</s></pos><stem>you</stem></mw><gra type="gra" index="2" head="1" relation="OBJ"/></mor></w><ga type="paralinguistics">eating noises</ga></g>
    <t type="p"><mor type="mor"><mt type="p"/><gra type="gra" index="3" head="1" relation="PUNCT"/></mor></t>
    <media
      start="593.027"
      end="597.234"
      unit="s"
    />
  </u>
  <u who="MOT" uID="u101">
    <w>thank<mor type="mor"><mw><pos><c>v</c></pos><stem>thank</stem></mw><gra type="gra" index="1" head="0" relation="ROOT"/></mor></w>
    <w>you<mor type="mor"><mw><pos><c>pro</c><s>per</s></pos><stem>you</stem></mw><gra type="gra" index="2" head="1" relation="OBJ"/></mor></w>
    <t type="p"><mor type="mor"><mt type="p"/><gra type="gra" index="3" head="1" relation="PUNCT"/></mor></t>
    <media
      start="597.234"
      end="600.035"
      unit="s"
    />
  </u>
  <u who="MOT" uID="u102">
    <w>thank<mor type="mor"><mw><pos><c>v</c></pos><stem>thank</stem></mw><gra type="gra" index="1" head="0" relation="ROOT"/></mor></w>
    <w>you<mor type="mor"><mw><pos><c>pro</c><s>per</s></pos><stem>you</stem></mw><gra type="gra" index="2" head="1" relation="OBJ"/></mor></w>
    <t type="p"><mor type="mor"><mt type="p"/><gra type="gra" index="3" head="1" relation="PUNCT"/></mor></t>
    <media
      start="600.035"
      end="603.449"
      unit="s"
    />
  </u>
  <u who="MOT" uID="u103">
    <g><w>mm<mor type="mor"><mw><pos><c>co</c></pos><stem>mm</stem></mw><gra type="gra" index="1" head="0" relation="INCROOT"/></mor></w><ga type="paralinguistics">eating noises</ga></g>
    <t type="p"><mor type="mor"><mt type="p"/><gra type="gra" index="2" head="1" relation="PUNCT"/></mor></t>
    <media
      start="603.449"
      end="606.432"
      unit="s"
    />
  </u>
  <u who="MOT" uID="u104">
    <e><action/><ga type="paralinguistics">eating noises</ga></e>
    <t type="p"></t>
    <media
      start="606.432"
      end="610.432"
      unit="s"
    />
  </u>
  <u who="MOT" uID="u105">
    <w>mm<mor type="mor"><mw><pos><c>co</c></pos><stem>mm</stem></mw><gra type="gra" index="1" head="0" relation="INCROOT"/></mor></w>
    <t type="p"><mor type="mor"><mt type="p"/><gra type="gra" index="2" head="1" relation="PUNCT"/></mor></t>

  </u>
  <u who="MOT" uID="u106">
    <w>you<mor type="mor"><mw><pos><c>pro</c><s>per</s></pos><stem>you</stem></mw><gra type="gra" index="1" head="4" relation="SUBJ"/></mor></w>
    <w>don't<mor type="mor"><mw><pos><c>mod</c></pos><stem>do</stem></mw><gra type="gra" index="2" head="4" relation="AUX"/><mor-post><mw><pos><c>neg</c></pos><stem>not</stem></mw><gra type="gra" index="3" head="2" relation="NEG"/></mor-post></mor></w>
    <w>drink<mor type="mor"><mw><pos><c>v</c></pos><stem>drink</stem></mw><gra type="gra" index="4" head="0" relation="ROOT"/></mor></w>
    <w>out<mor type="mor"><mw><pos><c>adv</c></pos><stem>out</stem></mw><gra type="gra" index="5" head="4" relation="JCT"/></mor></w>
    <w>of<mor type="mor"><mw><pos><c>prep</c></pos><stem>of</stem></mw><gra type="gra" index="6" head="4" relation="JCT"/></mor></w>
    <w>a<mor type="mor"><mw><pos><c>det</c><s>art</s></pos><stem>a</stem></mw><gra type="gra" index="7" head="8" relation="DET"/></mor></w>
    <g><w>bottle<mor type="mor"><mw><pos><c>n</c></pos><stem>bottle</stem></mw><gra type="gra" index="8" head="6" relation="POBJ"/></mor></w><ga type="paralinguistics">child moving toys</ga></g>
    <t type="p"><mor type="mor"><mt type="p"/><gra type="gra" index="9" head="4" relation="PUNCT"/></mor></t>
    <media
      start="610.432"
      end="623.033"
      unit="s"
    />
  </u>
  <u who="MOT" uID="u107">
    <e><action/><ga type="paralinguistics">eating noises</ga></e>
    <t type="p"></t>
    <media
      start="623.033"
      end="632.436"
      unit="s"
    />
  </u>
  <u who="MOT" uID="u108">
    <w>this<mor type="mor"><mw><pos><c>pro</c><s>dem</s></pos><stem>this</stem></mw><gra type="gra" index="1" head="2" relation="SUBJ"/></mor></w>
    <w>is<mor type="mor"><mw><pos><c>cop</c></pos><stem>be</stem><mk type="sfxf">3S</mk></mw><gra type="gra" index="2" head="0" relation="ROOT"/></mor></w>
    <w>for<mor type="mor"><mw><pos><c>prep</c></pos><stem>for</stem></mw><gra type="gra" index="3" head="2" relation="JCT"/></mor></w>
    <w>the<mor type="mor"><mw><pos><c>det</c><s>art</s></pos><stem>the</stem></mw><gra type="gra" index="4" head="5" relation="DET"/></mor></w>
    <w>baby<mor type="mor"><mw><pos><c>n</c></pos><stem>baby</stem></mw><gra type="gra" index="5" head="3" relation="POBJ"/></mor></w>
    <t type="p"><mor type="mor"><mt type="p"/><gra type="gra" index="6" head="2" relation="PUNCT"/></mor></t>

  </u>
  <u who="MOT" uID="u109">
    <w>you<mor type="mor"><mw><pos><c>pro</c><s>per</s></pos><stem>you</stem></mw><gra type="gra" index="1" head="4" relation="SUBJ"/></mor></w>
    <w>don't<mor type="mor"><mw><pos><c>mod</c></pos><stem>do</stem></mw><gra type="gra" index="2" head="4" relation="AUX"/><mor-post><mw><pos><c>neg</c></pos><stem>not</stem></mw><gra type="gra" index="3" head="2" relation="NEG"/></mor-post></mor></w>
    <w>drink<mor type="mor"><mw><pos><c>v</c></pos><stem>drink</stem></mw><gra type="gra" index="4" head="0" relation="ROOT"/></mor></w>
    <w>out<mor type="mor"><mw><pos><c>adv</c></pos><stem>out</stem></mw><gra type="gra" index="5" head="4" relation="JCT"/></mor></w>
    <w>of<mor type="mor"><mw><pos><c>prep</c></pos><stem>of</stem></mw><gra type="gra" index="6" head="4" relation="JCT"/></mor></w>
    <w>a<mor type="mor"><mw><pos><c>det</c><s>art</s></pos><stem>a</stem></mw><gra type="gra" index="7" head="8" relation="DET"/></mor></w>
    <w>bottle<mor type="mor"><mw><pos><c>n</c></pos><stem>bottle</stem></mw><gra type="gra" index="8" head="6" relation="POBJ"/></mor></w>
    <t type="p"><mor type="mor"><mt type="p"/><gra type="gra" index="9" head="4" relation="PUNCT"/></mor></t>
    <media
      start="632.436"
      end="636.541"
      unit="s"
    />
  </u>
  <u who="MOT" uID="u110">
    <w>that's<mor type="mor"><mw><pos><c>pro</c><s>dem</s></pos><stem>that</stem></mw><gra type="gra" index="1" head="2" relation="SUBJ"/><mor-post><mw><pos><c>cop</c></pos><stem>be</stem><mk type="sfxf">3S</mk></mw><gra type="gra" index="2" head="0" relation="ROOT"/></mor-post></mor></w>
    <w>for<mor type="mor"><mw><pos><c>prep</c></pos><stem>for</stem></mw><gra type="gra" index="3" head="2" relation="JCT"/></mor></w>
    <w>the<mor type="mor"><mw><pos><c>det</c><s>art</s></pos><stem>the</stem></mw><gra type="gra" index="4" head="5" relation="DET"/></mor></w>
    <w>baby<mor type="mor"><mw><pos><c>n</c></pos><stem>baby</stem></mw><gra type="gra" index="5" head="3" relation="POBJ"/></mor></w>
    <t type="p"><mor type="mor"><mt type="p"/><gra type="gra" index="6" head="2" relation="PUNCT"/></mor></t>
    <media
      start="636.541"
      end="640.364"
      unit="s"
    />
  </u>
  <u who="MOT" uID="u111">
    <w>mm<mor type="mor"><mw><pos><c>co</c></pos><stem>mm</stem></mw><gra type="gra" index="1" head="0" relation="INCROOT"/></mor></w>
    <t type="p"><mor type="mor"><mt type="p"/><gra type="gra" index="2" head="1" relation="PUNCT"/></mor></t>
    <media
      start="640.364"
      end="650.659"
      unit="s"
    />
  </u>
  <u who="MOT" uID="u112">
    <w>Amira<mor type="mor"><mw><pos><c>n</c><s>prop</s></pos><stem>Amira</stem></mw><gra type="gra" index="1" head="2" relation="SUBJ"/></mor></w>
    <w>look<mor type="mor"><mw><pos><c>v</c></pos><stem>look</stem></mw><gra type="gra" index="2" head="0" relation="ROOT"/></mor></w>
    <w>at<mor type="mor"><mw><pos><c>prep</c></pos><stem>at</stem></mw><gra type="gra" index="3" head="2" relation="JCT"/></mor></w>
    <w>the<mor type="mor"><mw><pos><c>det</c><s>art</s></pos><stem>the</stem></mw><gra type="gra" index="4" head="5" relation="DET"/></mor></w>
    <g><w>book<mor type="mor"><mw><pos><c>n</c></pos><stem>book</stem></mw><gra type="gra" index="5" head="3" relation="POBJ"/></mor></w><ga type="paralinguistics">grunts</ga></g>
    <t type="p"><mor type="mor"><mt type="p"/><gra type="gra" index="6" head="2" relation="PUNCT"/></mor></t>
    <media
      start="650.659"
      end="662.883"
      unit="s"
    />
  </u>
  <u who="MOT" uID="u113">
    <g><w>look<mor type="mor"><mw><pos><c>co</c></pos><stem>look</stem></mw><gra type="gra" index="1" head="0" relation="INCROOT"/></mor></w><ga type="paralinguistics">tapping noise</ga></g>
    <t type="p"><mor type="mor"><mt type="p"/><gra type="gra" index="2" head="1" relation="PUNCT"/></mor></t>
    <media
      start="662.883"
      end="667.010"
      unit="s"
    />
  </u>
  <u who="MOT" uID="u114">
    <g><w untranscribed="unintelligible">xxx</w><ga type="paralinguistics">silence</ga></g>
    <t type="p"></t>
    <media
      start="667.010"
      end="674.993"
      unit="s"
    />
  </u>
  <u who="MOT" uID="u115">
    <w>the<mor type="mor"><mw><pos><c>det</c><s>art</s></pos><stem>the</stem></mw><gra type="gra" index="1" head="2" relation="DET"/></mor></w>
    <w>doggies<mor type="mor"><mw><pos><c>n</c></pos><stem>dog</stem><mk type="sfx">DIM</mk><mk type="sfx">PL</mk></mw><gra type="gra" index="2" head="0" relation="INCROOT"/></mor></w>
    <t type="p"><mor type="mor"><mt type="p"/><gra type="gra" index="3" head="2" relation="PUNCT"/></mor></t>

  </u>
  <u who="MOT" uID="u116">
    <w>look<mor type="mor"><mw><pos><c>co</c></pos><stem>look</stem></mw><gra type="gra" index="1" head="0" relation="INCROOT"/></mor></w>
    <t type="p"><mor type="mor"><mt type="p"/><gra type="gra" index="2" head="1" relation="PUNCT"/></mor></t>
    <media
      start="674.993"
      end="679.169"
      unit="s"
    />
  </u>
  <u who="MOT" uID="u117">
    <w>the<mor type="mor"><mw><pos><c>det</c><s>art</s></pos><stem>the</stem></mw><gra type="gra" index="1" head="2" relation="DET"/></mor></w>
    <w>sheep<mor type="mor"><mw><pos><c>n</c></pos><stem>sheep</stem></mw><gra type="gra" index="2" head="0" relation="INCROOT"/></mor></w>
    <t type="p"><mor type="mor"><mt type="p"/><gra type="gra" index="3" head="2" relation="PUNCT"/></mor></t>
    <media
      start="679.169"
      end="683.390"
      unit="s"
    />
  </u>
  <u who="MOT" uID="u118">
    <w>ooh<mor type="mor"><mw><pos><c>v</c></pos><stem>ooh</stem></mw><gra type="gra" index="1" head="0" relation="ROOT"/></mor></w>
    <w>so<mor type="mor"><mw><pos><c>adv</c></pos><stem>so</stem></mw><gra type="gra" index="2" head="3" relation="JCT"/></mor></w>
    <w>soft<mor type="mor"><mw><pos><c>adj</c></pos><stem>soft</stem></mw><gra type="gra" index="3" head="1" relation="JCT"/></mor></w>
    <t type="p"><mor type="mor"><mt type="p"/><gra type="gra" index="4" head="1" relation="PUNCT"/></mor></t>
    <media
      start="683.390"
      end="686.230"
      unit="s"
    />
  </u>
  <u who="MOT" uID="u119">
    <w>mm<mor type="mor"><mw><pos><c>co</c></pos><stem>mm</stem></mw><gra type="gra" index="1" head="0" relation="INCROOT"/></mor></w>
    <t type="p"><mor type="mor"><mt type="p"/><gra type="gra" index="2" head="1" relation="PUNCT"/></mor></t>
    <media
      start="686.230"
      end="703.185"
      unit="s"
    />
  </u>
  <u who="MOT" uID="u120">
    <w>mm<mor type="mor"><mw><pos><c>co</c></pos><stem>mm</stem></mw><gra type="gra" index="1" head="2" relation="COM"/></mor></w>
    <w>is<mor type="mor"><mw><pos><c>cop</c></pos><stem>be</stem><mk type="sfxf">3S</mk></mw><gra type="gra" index="2" head="0" relation="ROOT"/></mor></w>
    <w>that<mor type="mor"><mw><pos><c>pro</c><s>dem</s></pos><stem>that</stem></mw><gra type="gra" index="3" head="2" relation="PRED"/></mor></w>
    <w>for<mor type="mor"><mw><pos><c>prep</c></pos><stem>for</stem></mw><gra type="gra" index="4" head="3" relation="JCT"/></mor></w>
    <w>the<mor type="mor"><mw><pos><c>det</c><s>art</s></pos><stem>the</stem></mw><gra type="gra" index="5" head="6" relation="DET"/></mor></w>
    <g><w>baby<mor type="mor"><mw><pos><c>n</c></pos><stem>baby</stem></mw><gra type="gra" index="6" head="4" relation="POBJ"/></mor></w><ga type="paralinguistics">background noise</ga></g>
    <t type="q"><mor type="mor"><mt type="q"/><gra type="gra" index="7" head="2" relation="PUNCT"/></mor></t>
    <media
      start="703.185"
      end="720.440"
      unit="s"
    />
  </u>
  <u who="MOT" uID="u121">
    <e><action/><ga type="paralinguistics">background noise</ga></e>
    <t type="p"></t>
    <media
      start="720.440"
      end="735.548"
      unit="s"
    />
  </u>
  <u who="MOT" uID="u122">
    <g><w>mm<mor type="mor"><mw><pos><c>co</c></pos><stem>mm</stem></mw><gra type="gra" index="1" head="0" relation="INCROOT"/></mor></w><ga type="paralinguistics">background noise and eating noises</ga></g>
    <t type="p"><mor type="mor"><mt type="p"/><gra type="gra" index="2" head="1" relation="PUNCT"/></mor></t>
    <media
      start="735.548"
      end="757.389"
      unit="s"
    />
  </u>
  <u who="MOT" uID="u123">
    <w>mm<mor type="mor"><mw><pos><c>co</c></pos><stem>mm</stem></mw><gra type="gra" index="1" head="0" relation="INCROOT"/></mor></w>
    <t type="p"><mor type="mor"><mt type="p"/><gra type="gra" index="2" head="1" relation="PUNCT"/></mor></t>
    <media
      start="757.389"
      end="761.741"
      unit="s"
    />
  </u>
  <u who="MOT" uID="u124">
    <w>the<mor type="mor"><mw><pos><c>det</c><s>art</s></pos><stem>the</stem></mw><gra type="gra" index="1" head="0" relation="INCROOT"/></mor></w>
    <g><w untranscribed="unintelligible">xxx</w><ga type="paralinguistics">eating noises</ga></g>
    <t type="p"><mor type="mor"><mt type="p"/><gra type="gra" index="2" head="1" relation="PUNCT"/></mor></t>
    <media
      start="761.741"
      end="767.428"
      unit="s"
    />
  </u>
  <u who="MOT" uID="u125">
    <w>mm<mor type="mor"><mw><pos><c>co</c></pos><stem>mm</stem></mw><gra type="gra" index="1" head="0" relation="INCROOT"/></mor></w>
    <t type="p"><mor type="mor"><mt type="p"/><gra type="gra" index="2" head="1" relation="PUNCT"/></mor></t>
    <media
      start="767.428"
      end="771.832"
      unit="s"
    />
  </u>
  <u who="MOT" uID="u126">
    <w>can<mor type="mor"><mw><pos><c>mod</c></pos><stem>can</stem></mw><gra type="gra" index="1" head="4" relation="AUX"/></mor></w>
    <w>the<mor type="mor"><mw><pos><c>det</c><s>art</s></pos><stem>the</stem></mw><gra type="gra" index="2" head="3" relation="DET"/></mor></w>
    <w>baby<mor type="mor"><mw><pos><c>n</c></pos><stem>baby</stem></mw><gra type="gra" index="3" head="4" relation="SUBJ"/></mor></w>
    <w>have<mor type="mor"><mw><pos><c>v</c></pos><stem>have</stem></mw><gra type="gra" index="4" head="0" relation="ROOT"/></mor></w>
    <w>some<mor type="mor"><mw><pos><c>qn</c></pos><stem>some</stem></mw><gra type="gra" index="5" head="4" relation="OBJ"/></mor></w>
    <t type="q"><mor type="mor"><mt type="q"/><gra type="gra" index="6" head="4" relation="PUNCT"/></mor></t>
    <media
      start="771.832"
      end="778.165"
      unit="s"
    />
  </u>
  <u who="MOT" uID="u127">
    <w>Amira<mor type="mor"><mw><pos><c>n</c><s>prop</s></pos><stem>Amira</stem></mw><gra type="gra" index="1" head="2" relation="MOD"/></mor></w>
    <w>can<mor type="mor"><mw><pos><c>n</c></pos><stem>can</stem></mw><gra type="gra" index="2" head="0" relation="INCROOT"/></mor></w>
    <w>the<mor type="mor"><mw><pos><c>det</c><s>art</s></pos><stem>the</stem></mw><gra type="gra" index="3" head="4" relation="DET"/></mor></w>
    <w>baby<mor type="mor"><mw><pos><c>n</c></pos><stem>baby</stem></mw><gra type="gra" index="4" head="5" relation="SUBJ"/></mor></w>
    <w>have<mor type="mor"><mw><pos><c>v</c></pos><stem>have</stem></mw><gra type="gra" index="5" head="2" relation="CMOD"/></mor></w>
    <w>a<mor type="mor"><mw><pos><c>det</c><s>art</s></pos><stem>a</stem></mw><gra type="gra" index="6" head="7" relation="DET"/></mor></w>
    <w>bite<mor type="mor"><mw><pos><c>n</c></pos><stem>bite</stem></mw><gra type="gra" index="7" head="5" relation="OBJ"/></mor></w>
    <t type="q"><mor type="mor"><mt type="q"/><gra type="gra" index="8" head="2" relation="PUNCT"/></mor></t>
    <media
      start="778.165"
      end="782.468"
      unit="s"
    />
  </u>
  <u who="MOT" uID="u128">
    <w>mm<mor type="mor"><mw><pos><c>co</c></pos><stem>mm</stem></mw><gra type="gra" index="1" head="0" relation="INCROOT"/></mor></w>
    <t type="p"><mor type="mor"><mt type="p"/><gra type="gra" index="2" head="1" relation="PUNCT"/></mor></t>
    <media
      start="782.468"
      end="783.784"
      unit="s"
    />
  </u>
  <u who="MOT" uID="u129">
    <w>can<mor type="mor"><mw><pos><c>mod</c></pos><stem>can</stem></mw><gra type="gra" index="1" head="3" relation="AUX"/></mor></w>
    <w>I<mor type="mor"><mw><pos><c>pro</c><s>sub</s></pos><stem>I</stem></mw><gra type="gra" index="2" head="3" relation="SUBJ"/></mor></w>
    <w>have<mor type="mor"><mw><pos><c>v</c></pos><stem>have</stem></mw><gra type="gra" index="3" head="0" relation="ROOT"/></mor></w>
    <w>some<mor type="mor"><mw><pos><c>qn</c></pos><stem>some</stem></mw><gra type="gra" index="4" head="3" relation="OBJ"/></mor></w>
    <t type="q"><mor type="mor"><mt type="q"/><gra type="gra" index="5" head="3" relation="PUNCT"/></mor></t>
    <media
      start="783.784"
      end="785.591"
      unit="s"
    />
  </u>
  <u who="MOT" uID="u130">
    <w>can<mor type="mor"><mw><pos><c>mod</c></pos><stem>can</stem></mw><gra type="gra" index="1" head="3" relation="AUX"/></mor></w>
    <w>I<mor type="mor"><mw><pos><c>pro</c><s>sub</s></pos><stem>I</stem></mw><gra type="gra" index="2" head="3" relation="SUBJ"/></mor></w>
    <w>have<mor type="mor"><mw><pos><c>v</c></pos><stem>have</stem></mw><gra type="gra" index="3" head="0" relation="ROOT"/></mor></w>
    <w>a<mor type="mor"><mw><pos><c>det</c><s>art</s></pos><stem>a</stem></mw><gra type="gra" index="4" head="5" relation="DET"/></mor></w>
    <w>bite<mor type="mor"><mw><pos><c>n</c></pos><stem>bite</stem></mw><gra type="gra" index="5" head="3" relation="OBJ"/></mor></w>
    <t type="q"><mor type="mor"><mt type="q"/><gra type="gra" index="6" head="3" relation="PUNCT"/></mor></t>
    <media
      start="785.591"
      end="788.528"
      unit="s"
    />
  </u>
  <u who="MOT" uID="u131">
    <g><w>Amira<mor type="mor"><mw><pos><c>n</c><s>prop</s></pos><stem>Amira</stem></mw><gra type="gra" index="1" head="0" relation="INCROOT"/></mor></w><ga type="paralinguistics">background noise</ga></g>
    <t type="p"><mor type="mor"><mt type="p"/><gra type="gra" index="2" head="1" relation="PUNCT"/></mor></t>
    <media
      start="788.528"
      end="796.649"
      unit="s"
    />
  </u>
  <u who="MOT" uID="u132">
    <g><w>Amira<mor type="mor"><mw><pos><c>n</c><s>prop</s></pos><stem>Amira</stem></mw><gra type="gra" index="1" head="0" relation="INCROOT"/></mor></w><ga type="paralinguistics">child playing with toys</ga></g>
    <t type="p"><mor type="mor"><mt type="p"/><gra type="gra" index="2" head="1" relation="PUNCT"/></mor></t>
    <media
      start="796.649"
      end="806.930"
      unit="s"
    />
  </u>
  <u who="MOT" uID="u133">
    <w>come<mor type="mor"><mw><pos><c>v</c></pos><stem>come</stem></mw><gra type="gra" index="1" head="0" relation="ROOT"/></mor></w>
    <w>on<mor type="mor"><mw><pos><c>adv</c></pos><stem>on</stem></mw><gra type="gra" index="2" head="1" relation="JCT"/></mor></w>
    <t type="p"><mor type="mor"><mt type="p"/><gra type="gra" index="3" head="1" relation="PUNCT"/></mor></t>
    <media
      start="806.930"
      end="814.866"
      unit="s"
    />
  </u>
</CHAT>