<?xml version="1.0" encoding="UTF-8"?>

<CHAT xmlns:xsi="http://www.w3.org/2001/XMLSchema-instance"
      xmlns="http://www.talkbank.org/ns/talkbank"
      xsi:schemaLocation="http://www.talkbank.org/ns/talkbank https://talkbank.org/software/talkbank.xsd"
      Media="5224EZS" Mediatypes="audio"
            DesignType="long"
            ActivityType="preverbal"
            GroupType="TD"
      PID="11312/c-00043336-1"
      Window="276_604_444_707_0_0_354_1_354_1"
      Version="2.16.0"
      Lang="eng"
      Options="bullets"
      Corpus="NewmanRatner"
      >
  <Participants>
    <participant
      id="CHI"
    name="5224EZS11"
      role="Target_Child"
      language="eng"
      age="P0Y11M"
      sex="female"
      group="TD"
      education="UG"

    />
    <participant
      id="MOT"
    name="5224EZS11"
      role="Mother"
      language="eng"
      sex="female"
      education="College_Doctoral"

    />
    <participant
      id="EXP"
    name="Clinician"
      role="Investigator"
      language="eng"

    />
  </Participants>
  <comment type="Transcriber">Catherine_Bender</comment>
  <comment type="Types">long, preverbal, TD</comment>
  <u who="MOT" uID="u0">
    <e><action/><ga type="paralinguistics">setting up noises</ga></e>
    <t type="p"></t>
    <media
      start="0.000"
      end="10.076"
      unit="s"
    />
  </u>
  <u who="EXP" uID="u1">
    <w>this<mor type="mor"><mw><pos><c>pro</c><s>dem</s></pos><stem>this</stem></mw><gra type="gra" index="1" head="2" relation="SUBJ"/></mor></w>
    <w>is<mor type="mor"><mw><pos><c>cop</c></pos><stem>be</stem><mk type="sfxf">3S</mk></mw><gra type="gra" index="2" head="0" relation="ROOT"/></mor></w>
    <w>participant<mor type="mor"><mw><pos><c>n</c></pos><stem>participant</stem></mw><gra type="gra" index="3" head="4" relation="MOD"/></mor></w>
    <w>number<mor type="mor"><mw><pos><c>n</c></pos><stem>number</stem></mw><gra type="gra" index="4" head="2" relation="PRED"/></mor></w>
    <w>five<mor type="mor"><mw><pos><c>det</c><s>num</s></pos><stem>five</stem></mw><gra type="gra" index="5" head="8" relation="DATE"/></mor></w>
    <w>two<mor type="mor"><mw><pos><c>det</c><s>num</s></pos><stem>two</stem></mw><gra type="gra" index="6" head="8" relation="DATE"/></mor></w>
    <w>four<mor type="mor"><mw><pos><c>det</c><s>num</s></pos><stem>four</stem></mw><gra type="gra" index="7" head="8" relation="DATE"/></mor></w>
    <w>four<mor type="mor"><mw><pos><c>det</c><s>num</s></pos><stem>four</stem></mw><gra type="gra" index="8" head="9" relation="QUANT"/></mor></w>
    <w formType="letter">e<mor type="mor"><mw><pos><c>n</c><s>let</s></pos><stem>e</stem></mw><gra type="gra" index="9" head="2" relation="CJCT"/></mor></w>
    <w formType="letter">z<mor type="mor"><mw><pos><c>n</c><s>let</s></pos><stem>z</stem></mw><gra type="gra" index="10" head="11" relation="MOD"/></mor></w>
    <w formType="letter">s<mor type="mor"><mw><pos><c>n</c><s>let</s></pos><stem>s</stem></mw><gra type="gra" index="11" head="9" relation="ENUM"/></mor></w>
    <t type="p"><mor type="mor"><mt type="p"/><gra type="gra" index="12" head="2" relation="PUNCT"/></mor></t>
    <media
      start="10.076"
      end="23.307"
      unit="s"
    />
  </u>
  <u who="EXP" uID="u2">
    <w>today<mor type="mor"><mw><pos><c>adv</c><s>tem</s></pos><stem>today</stem></mw><gra type="gra" index="1" head="2" relation="SUBJ"/></mor></w>
    <w>is<mor type="mor"><mw><pos><c>cop</c></pos><stem>be</stem><mk type="sfxf">3S</mk></mw><gra type="gra" index="2" head="0" relation="ROOT"/></mor></w>
    <w>September<mor type="mor"><mw><pos><c>n</c><s>prop</s></pos><stem>September</stem></mw><gra type="gra" index="3" head="4" relation="MOD"/></mor></w>
    <w>eleventh<mor type="mor"><mw><pos><c>adj</c></pos><stem>eleventh</stem></mw><gra type="gra" index="4" head="2" relation="PRED"/></mor></w>
    <w>two<mor type="mor"><mw><pos><c>det</c><s>num</s></pos><stem>two</stem></mw><gra type="gra" index="5" head="6" relation="QUANT"/></mor></w>
    <w>thousand<mor type="mor"><mw><pos><c>det</c><s>num</s></pos><stem>thousand</stem></mw><gra type="gra" index="6" head="7" relation="QUANT"/></mor></w>
    <w>nine<mor type="mor"><mw><pos><c>det</c><s>num</s></pos><stem>nine</stem></mw><gra type="gra" index="7" head="10" relation="SUBJ"/></mor></w>
    <w>and<mor type="mor"><mw><pos><c>coord</c></pos><stem>and</stem></mw><gra type="gra" index="8" head="7" relation="CONJ"/></mor></w>
    <w>this<mor type="mor"><mw><pos><c>pro</c><s>dem</s></pos><stem>this</stem></mw><gra type="gra" index="9" head="8" relation="COORD"/></mor></w>
    <w>is<mor type="mor"><mw><pos><c>cop</c></pos><stem>be</stem><mk type="sfxf">3S</mk></mw><gra type="gra" index="10" head="4" relation="CMOD"/></mor></w>
    <w>their<mor type="mor"><mw><pos><c>det</c><s>poss</s></pos><stem>their</stem></mw><gra type="gra" index="11" head="13" relation="DET"/></mor></w>
    <w>third<mor type="mor"><mw><pos><c>adj</c></pos><stem>third</stem></mw><gra type="gra" index="12" head="13" relation="MOD"/></mor></w>
    <w>visit<mor type="mor"><mw><pos><c>n</c></pos><stem>visit</stem></mw><gra type="gra" index="13" head="10" relation="PRED"/></mor></w>
    <t type="p"><mor type="mor"><mt type="p"/><gra type="gra" index="14" head="2" relation="PUNCT"/></mor></t>
    <media
      start="23.307"
      end="28.094"
      unit="s"
    />
  </u>
  <u who="MOT" uID="u3">
    <e><action/><ga type="paralinguistics">setting up noises and door latch</ga></e>
    <t type="p"></t>
    <media
      start="28.468"
      end="44.509"
      unit="s"
    />
  </u>
  <u who="MOT" uID="u4">
    <w>what<mor type="mor"><mw><pos><c>pro</c><s>int</s></pos><stem>what</stem></mw><gra type="gra" index="1" head="4" relation="SUBJ"/></mor></w>
    <w>do<mor type="mor"><mw><pos><c>mod</c></pos><stem>do</stem></mw><gra type="gra" index="2" head="4" relation="AUX"/></mor></w>
    <w>ya<mor type="mor"><mw><pos><c>pro</c><s>per</s></pos><stem>you</stem></mw><gra type="gra" index="3" head="4" relation="SUBJ"/></mor></w>
    <w>have<mor type="mor"><mw><pos><c>v</c></pos><stem>have</stem></mw><gra type="gra" index="4" head="0" relation="ROOT"/></mor></w>
    <w>Elanore<mor type="mor"><mw><pos><c>n</c><s>prop</s></pos><stem>Elanore</stem></mw><gra type="gra" index="5" head="4" relation="OBJ"/></mor></w>
    <t type="q"><mor type="mor"><mt type="q"/><gra type="gra" index="6" head="4" relation="PUNCT"/></mor></t>
    <media
      start="44.509"
      end="46.969"
      unit="s"
    />
  </u>
  <u who="MOT" uID="u5">
    <e><action/><ga type="paralinguistics">tapping noises</ga></e>
    <t type="p"></t>

  </u>
  <u who="MOT" uID="u6">
    <w>whats<mor type="mor"><mw><pos><c>n</c><s>pt</s></pos><stem>whats</stem></mw><gra type="gra" index="1" head="3" relation="LINK"/></mor></w>
    <w>mommy<mor type="mor"><mw><pos><c>n</c></pos><stem>mommy</stem></mw><gra type="gra" index="2" head="3" relation="SUBJ"/></mor></w>
    <w>have<mor type="mor"><mw><pos><c>v</c></pos><stem>have</stem></mw><gra type="gra" index="3" head="0" relation="ROOT"/></mor></w>
    <t type="q"><mor type="mor"><mt type="q"/><gra type="gra" index="4" head="3" relation="PUNCT"/></mor></t>
    <media
      start="46.969"
      end="53.938"
      unit="s"
    />
  </u>
  <u who="MOT" uID="u7">
    <e><action/><ga type="paralinguistics">tapping and jostling of toys</ga></e>
    <t type="p"></t>

  </u>
  <u who="MOT" uID="u8">
    <w>you<mor type="mor"><mw><pos><c>pro</c><s>per</s></pos><stem>you</stem></mw><gra type="gra" index="1" head="2" relation="SUBJ"/></mor></w>
    <w>done<mor type="mor"><mw><pos><c>part</c></pos><stem>do</stem><mk type="sfxf">PASTP</mk></mw><gra type="gra" index="2" head="0" relation="ROOT"/></mor></w>
    <w>with<mor type="mor"><mw><pos><c>prep</c></pos><stem>with</stem></mw><gra type="gra" index="3" head="2" relation="JCT"/></mor></w>
    <w>that<mor type="mor"><mw><pos><c>pro</c><s>dem</s></pos><stem>that</stem></mw><gra type="gra" index="4" head="3" relation="POBJ"/></mor></w>
    <t type="q"><mor type="mor"><mt type="q"/><gra type="gra" index="5" head="2" relation="PUNCT"/></mor></t>
    <media
      start="53.938"
      end="64.271"
      unit="s"
    />
  </u>
  <u who="MOT" uID="u9">
    <e><action/><ga type="paralinguistics">toys banging</ga></e>
    <t type="p"></t>

  </u>
  <u who="MOT" uID="u10">
    <e><action/><ga type="paralinguistics">whispered</ga></e>
    <w>oh<mor type="mor"><mw><pos><c>co</c></pos><stem>oh</stem></mw><gra type="gra" index="1" head="0" relation="INCROOT"/></mor></w>
    <t type="p"><mor type="mor"><mt type="p"/><gra type="gra" index="2" head="1" relation="PUNCT"/></mor></t>

  </u>
  <u who="MOT" uID="u11">
    <e><action/><ga type="paralinguistics">tapping noise</ga></e>
    <t type="p"></t>
    <media
      start="64.271"
      end="70.374"
      unit="s"
    />
  </u>
  <u who="MOT" uID="u12">
    <e><action/><ga type="paralinguistics">rustling sounds</ga></e>
    <t type="p"></t>

  </u>
  <u who="MOT" uID="u13">
    <e><action/><ga type="paralinguistics">whispered</ga></e>
    <w>oh<mor type="mor"><mw><pos><c>co</c></pos><stem>oh</stem></mw><gra type="gra" index="1" head="0" relation="INCROOT"/></mor></w>
    <t type="p"><mor type="mor"><mt type="p"/><gra type="gra" index="2" head="1" relation="PUNCT"/></mor></t>

  </u>
  <u who="MOT" uID="u14">
    <w>see<mor type="mor"><mw><pos><c>v</c></pos><stem>see</stem></mw><gra type="gra" index="1" head="0" relation="ROOT"/></mor></w>
    <w>the<mor type="mor"><mw><pos><c>det</c><s>art</s></pos><stem>the</stem></mw><gra type="gra" index="2" head="3" relation="DET"/></mor></w>
    <w>toy<mor type="mor"><mw><pos><c>n</c></pos><stem>toy</stem></mw><gra type="gra" index="3" head="1" relation="OBJ"/></mor></w>
    <t type="q"><mor type="mor"><mt type="q"/><gra type="gra" index="4" head="1" relation="PUNCT"/></mor></t>

  </u>
  <u who="MOT" uID="u15">
    <w>mwah<mor type="mor"><mw><pos><c>on</c></pos><stem>mwah</stem></mw><gra type="gra" index="1" head="0" relation="INCROOT"/></mor></w>
    <t type="e"><mor type="mor"><mt type="e"/><gra type="gra" index="2" head="1" relation="PUNCT"/></mor></t>

  </u>
  <u who="MOT" uID="u16">
    <w>give<mor type="mor"><mw><pos><c>v</c></pos><stem>give</stem></mw><gra type="gra" index="1" head="0" relation="ROOT"/></mor></w>
    <w>you<mor type="mor"><mw><pos><c>pro</c><s>per</s></pos><stem>you</stem></mw><gra type="gra" index="2" head="3" relation="SUBJ"/></mor></w>
    <w>kisses<mor type="mor"><mw><pos><c>v</c></pos><stem>kiss</stem><mk type="sfx">3S</mk></mw><gra type="gra" index="3" head="1" relation="COMP"/></mor></w>
    <t type="e"><mor type="mor"><mt type="e"/><gra type="gra" index="4" head="1" relation="PUNCT"/></mor></t>

  </u>
  <u who="CHI" uID="u17">
    <e><action/><ga type="paralinguistics">whining sound</ga></e>
    <t type="p"></t>
    <media
      start="70.374"
      end="85.244"
      unit="s"
    />
  </u>
  <u who="MOT" uID="u18">
    <w>does<mor type="mor"><mw><pos><c>mod</c></pos><stem>do</stem><mk type="sfxf">3S</mk></mw><gra type="gra" index="1" head="3" relation="AUX"/></mor></w>
    <w>he<mor type="mor"><mw><pos><c>pro</c><s>sub</s></pos><stem>he</stem></mw><gra type="gra" index="2" head="3" relation="SUBJ"/></mor></w>
    <w>taste<mor type="mor"><mw><pos><c>v</c></pos><stem>taste</stem></mw><gra type="gra" index="3" head="0" relation="ROOT"/></mor></w>
    <w>good<mor type="mor"><mw><pos><c>adj</c></pos><stem>good</stem></mw><gra type="gra" index="4" head="3" relation="JCT"/></mor></w>
    <t type="q"><mor type="mor"><mt type="q"/><gra type="gra" index="5" head="3" relation="PUNCT"/></mor></t>
    <media
      start="85.530"
      end="90.210"
      unit="s"
    />
  </u>
  <u who="MOT" uID="u19">
    <w>no<mor type="mor"><mw><pos><c>co</c></pos><stem>no</stem></mw><gra type="gra" index="1" head="0" relation="INCROOT"/></mor></w>
    <t type="q"><mor type="mor"><mt type="q"/><gra type="gra" index="2" head="1" relation="PUNCT"/></mor></t>
    <media
      start="90.210"
      end="92.745"
      unit="s"
    />
  </u>
  <u who="MOT" uID="u20">
    <w>looks<mor type="mor"><mw><pos><c>v</c></pos><stem>look</stem><mk type="sfx">3S</mk></mw><gra type="gra" index="1" head="0" relation="ROOT"/></mor></w>
    <w>like<mor type="mor"><mw><pos><c>conj</c></pos><stem>like</stem></mw><gra type="gra" index="2" head="1" relation="JCT"/></mor></w>
    <w>an<mor type="mor"><mw><pos><c>det</c><s>art</s></pos><stem>a</stem></mw><gra type="gra" index="3" head="4" relation="DET"/></mor></w>
    <w>otter<mor type="mor"><mw><pos><c>n</c></pos><stem>otter</stem></mw><gra type="gra" index="4" head="2" relation="POBJ"/></mor></w>
    <t type="p"><mor type="mor"><mt type="p"/><gra type="gra" index="5" head="1" relation="PUNCT"/></mor></t>

  </u>
  <u who="CHI" uID="u21">
    <e><action/><ga type="paralinguistics">whines</ga></e>
    <t type="p"></t>
    <media
      start="92.745"
      end="95.487"
      unit="s"
    />
  </u>
  <u who="CHI" uID="u22">
    <e><action/><ga type="paralinguistics">whines</ga></e>
    <t type="p"></t>
    <media
      start="95.487"
      end="99.811"
      unit="s"
    />
  </u>
  <u who="CHI" uID="u23">
    <e><action/><ga type="paralinguistics">cooing then rustling noise</ga></e>
    <t type="p"></t>
    <media
      start="99.811"
      end="106.529"
      unit="s"
    />
  </u>
  <u who="MOT" uID="u24">
    <e><action/><ga type="paralinguistics">gasp</ga></e>
    <t type="p"></t>

  </u>
  <u who="MOT" uID="u25">
    <e><action/><ga type="paralinguistics">singsong voice</ga></e>
    <w>hi<mor type="mor"><mw><pos><c>co</c></pos><stem>hi</stem></mw><gra type="gra" index="1" head="2" relation="COM"/></mor></w>
    <w>Elanore<mor type="mor"><mw><pos><c>n</c><s>prop</s></pos><stem>Elanore</stem></mw><gra type="gra" index="2" head="0" relation="INCROOT"/></mor></w>
    <t type="p"><mor type="mor"><mt type="p"/><gra type="gra" index="3" head="2" relation="PUNCT"/></mor></t>
    <media
      start="106.529"
      end="115.780"
      unit="s"
    />
  </u>
  <u who="MOT" uID="u26">
    <w>boop<mor type="mor"><mw><pos><c>co</c></pos><stem>boop</stem></mw><gra type="gra" index="1" head="3" relation="COM"/></mor></w>
    <w>boop<mor type="mor"><mw><pos><c>co</c></pos><stem>boop</stem></mw><gra type="gra" index="2" head="3" relation="COM"/></mor></w>
    <w>boop<mor type="mor"><mw><pos><c>co</c></pos><stem>boop</stem></mw><gra type="gra" index="3" head="0" relation="INCROOT"/></mor></w>
    <g><w>boop<mor type="mor"><mw><pos><c>co</c></pos><stem>boop</stem></mw><gra type="gra" index="4" head="3" relation="COM"/></mor></w><ga type="paralinguistics">singsong voise</ga></g>
    <t type="p"><mor type="mor"><mt type="p"/><gra type="gra" index="5" head="3" relation="PUNCT"/></mor></t>
    <media
      start="115.780"
      end="118.203"
      unit="s"
    />
  </u>
  <u who="MOT" uID="u27">
    <w>do<mor type="mor"><mw><pos><c>mod</c></pos><stem>do</stem></mw><gra type="gra" index="1" head="2" relation="AUX"/></mor></w>
    <w>do<mor type="mor"><mw><pos><c>v</c></pos><stem>do</stem></mw><gra type="gra" index="2" head="0" relation="ROOT"/></mor></w>
    <t type="p"><mor type="mor"><mt type="p"/><gra type="gra" index="3" head="2" relation="PUNCT"/></mor></t>

  </u>
  <u who="MOT" uID="u28">
    <e><action/><ga type="paralinguistics">gasp</ga></e>
    <t type="p"></t>

  </u>
  <u who="MOT" uID="u29">
    <w>what<mor type="mor"><mw><pos><c>pro</c><s>int</s></pos><stem>what</stem></mw><gra type="gra" index="1" head="4" relation="LINK"/></mor></w>
    <w>are<mor type="mor"><mw><pos><c>aux</c></pos><stem>be</stem><mk type="sfxf">PRES</mk></mw><gra type="gra" index="2" head="4" relation="AUX"/></mor></w>
    <w>you<mor type="mor"><mw><pos><c>pro</c><s>per</s></pos><stem>you</stem></mw><gra type="gra" index="3" head="4" relation="SUBJ"/></mor></w>
    <w>doing<mor type="mor"><mw><pos><c>part</c></pos><stem>do</stem><mk type="sfx">PRESP</mk></mw><gra type="gra" index="4" head="0" relation="ROOT"/></mor></w>
    <w>to<mor type="mor"><mw><pos><c>prep</c></pos><stem>to</stem></mw><gra type="gra" index="5" head="4" relation="JCT"/></mor></w>
    <w>me<mor type="mor"><mw><pos><c>pro</c><s>obj</s></pos><stem>me</stem></mw><gra type="gra" index="6" head="5" relation="POBJ"/></mor></w>
    <t type="q"><mor type="mor"><mt type="q"/><gra type="gra" index="7" head="4" relation="PUNCT"/></mor></t>
    <media
      start="118.203"
      end="125.581"
      unit="s"
    />
  </u>
  <u who="MOT" uID="u30">
    <w>why<mor type="mor"><mw><pos><c>pro</c><s>int</s></pos><stem>why</stem></mw><gra type="gra" index="1" head="4" relation="LINK"/></mor></w>
    <w>are<mor type="mor"><mw><pos><c>aux</c></pos><stem>be</stem><mk type="sfxf">PRES</mk></mw><gra type="gra" index="2" head="4" relation="AUX"/></mor></w>
    <w>you<mor type="mor"><mw><pos><c>pro</c><s>per</s></pos><stem>you</stem></mw><gra type="gra" index="3" head="4" relation="SUBJ"/></mor></w>
    <w>grabbing<mor type="mor"><mw><pos><c>part</c></pos><stem>grab</stem><mk type="sfx">PRESP</mk></mw><gra type="gra" index="4" head="0" relation="ROOT"/></mor></w>
    <w>me<mor type="mor"><mw><pos><c>pro</c><s>obj</s></pos><stem>me</stem></mw><gra type="gra" index="5" head="4" relation="OBJ"/></mor></w>
    <t type="q"><mor type="mor"><mt type="q"/><gra type="gra" index="6" head="4" relation="PUNCT"/></mor></t>
    <media
      start="125.581"
      end="128.092"
      unit="s"
    />
  </u>
  <u who="MOT" uID="u31">
    <w>why<mor type="mor"><mw><pos><c>pro</c><s>rel</s></pos><stem>why</stem></mw><gra type="gra" index="1" head="0" relation="INCROOT"/></mor></w>
    <t type="q"><mor type="mor"><mt type="q"/><gra type="gra" index="2" head="1" relation="PUNCT"/></mor></t>

  </u>
  <u who="MOT" uID="u32">
    <e><action/><ga type="paralinguistics">gasp</ga></e>
    <w>oh<mor type="mor"><mw><pos><c>co</c></pos><stem>oh</stem></mw><gra type="gra" index="1" head="0" relation="INCROOT"/></mor></w>
    <t type="p"><mor type="mor"><mt type="p"/><gra type="gra" index="2" head="1" relation="PUNCT"/></mor></t>

  </u>
  <u who="MOT" uID="u33">
    <w>boop<mor type="mor"><mw><pos><c>co</c></pos><stem>boop</stem></mw><gra type="gra" index="1" head="3" relation="COM"/></mor></w>
    <w>boop<mor type="mor"><mw><pos><c>co</c></pos><stem>boop</stem></mw><gra type="gra" index="2" head="3" relation="COM"/></mor></w>
    <w>boop<mor type="mor"><mw><pos><c>co</c></pos><stem>boop</stem></mw><gra type="gra" index="3" head="0" relation="INCROOT"/></mor></w>
    <t type="p"><mor type="mor"><mt type="p"/><gra type="gra" index="4" head="3" relation="PUNCT"/></mor></t>
    <media
      start="128.092"
      end="132.701"
      unit="s"
    />
  </u>
  <u who="MOT" uID="u34">
    <e><action/><ga type="paralinguistics">rustling</ga></e>
    <t type="p"></t>

  </u>
  <u who="MOT" uID="u35">
    <w>do<mor type="mor"><mw><pos><c>mod</c></pos><stem>do</stem></mw><gra type="gra" index="1" head="2" relation="AUX"/></mor></w>
    <w>do<mor type="mor"><mw><pos><c>v</c></pos><stem>do</stem></mw><gra type="gra" index="2" head="0" relation="ROOT"/></mor></w>
    <t type="p"><mor type="mor"><mt type="p"/><gra type="gra" index="3" head="2" relation="PUNCT"/></mor></t>
    <media
      start="132.701"
      end="138.965"
      unit="s"
    />
  </u>
  <u who="MOT" uID="u36">
    <e><action/><ga type="paralinguistics">toys clanking together</ga></e>
    <t type="p"></t>
    <media
      start="138.965"
      end="148.478"
      unit="s"
    />
  </u>
  <u who="MOT" uID="u37">
    <e><action/><ga type="paralinguistics">rustling and toys clanking together</ga></e>
    <t type="p"></t>

  </u>
  <u who="MOT" uID="u38">
    <w>hm<mor type="mor"><mw><pos><c>co</c></pos><stem>hm</stem></mw><gra type="gra" index="1" head="0" relation="INCROOT"/></mor></w>
    <t type="p"><mor type="mor"><mt type="p"/><gra type="gra" index="2" head="1" relation="PUNCT"/></mor></t>
    <media
      start="148.478"
      end="156.613"
      unit="s"
    />
  </u>
  <u who="MOT" uID="u39">
    <w>you<mor type="mor"><mw><pos><c>pro</c><s>per</s></pos><stem>you</stem></mw><gra type="gra" index="1" head="2" relation="SUBJ"/></mor></w>
    <w>like<mor type="mor"><mw><pos><c>v</c></pos><stem>like</stem></mw><gra type="gra" index="2" head="0" relation="ROOT"/></mor></w>
    <w>that<mor type="mor"><mw><pos><c>det</c><s>dem</s></pos><stem>that</stem></mw><gra type="gra" index="3" head="4" relation="DET"/></mor></w>
    <w>bumblebee<mor type="mor"><mwc><pos><c>n</c></pos><mw><pos><c>n</c></pos><stem>bumble</stem></mw><mw><pos><c>n</c></pos><stem>bee</stem></mw></mwc><gra type="gra" index="4" head="2" relation="OBJ"/></mor></w>
    <t type="p"><mor type="mor"><mt type="p"/><gra type="gra" index="5" head="2" relation="PUNCT"/></mor></t>
    <media
      start="156.613"
      end="164.886"
      unit="s"
    />
  </u>
  <u who="CHI" uID="u40">
    <e><action/><ga type="paralinguistics">baby noise like a coo</ga></e>
    <t type="p"></t>
    <media
      start="164.886"
      end="168.855"
      unit="s"
    />
  </u>
  <u who="CHI" uID="u41">
    <e><action/><ga type="paralinguistics">toys ruslting</ga></e>
    <t type="p"></t>

  </u>
  <u who="CHI" uID="u42">
    <w untranscribed="unintelligible-with-pho">yyy</w>
    <t type="p"></t>
    <media
      start="168.855"
      end="177.459"
      unit="s"
    />
    <a type="extension" flavor="pho">adu .</a>
  </u>
  <u who="MOT" uID="u43">
    <e><action/><ga type="paralinguistics">whispered</ga></e>
    <g><w>oh<mor type="mor"><mw><pos><c>co</c></pos><stem>oh</stem></mw><gra type="gra" index="1" head="0" relation="INCROOT"/></mor></w><error>d</error></g>
    <t type="p"><mor type="mor"><mt type="p"/><gra type="gra" index="2" head="1" relation="PUNCT"/></mor></t>

  </u>
  <u who="MOT" uID="u44">
    <w>look<mor type="mor"><mw><pos><c>v</c></pos><stem>look</stem></mw><gra type="gra" index="1" head="0" relation="ROOT"/></mor></w>
    <w>at<mor type="mor"><mw><pos><c>prep</c></pos><stem>at</stem></mw><gra type="gra" index="2" head="1" relation="JCT"/></mor></w>
    <w>this<mor type="mor"><mw><pos><c>pro</c><s>dem</s></pos><stem>this</stem></mw><gra type="gra" index="3" head="2" relation="POBJ"/></mor></w>
    <t type="p"><mor type="mor"><mt type="p"/><gra type="gra" index="4" head="1" relation="PUNCT"/></mor></t>
    <media
      start="177.459"
      end="184.297"
      unit="s"
    />
  </u>
  <u who="MOT" uID="u45">
    <w>it<mor type="mor"><mw><pos><c>pro</c><s>per</s></pos><stem>it</stem></mw><gra type="gra" index="1" head="2" relation="SUBJ"/></mor></w>
    <w>bounces<mor type="mor"><mw><pos><c>v</c></pos><stem>bounce</stem><mk type="sfx">3S</mk></mw><gra type="gra" index="2" head="0" relation="ROOT"/></mor></w>
    <t type="e"><mor type="mor"><mt type="e"/><gra type="gra" index="3" head="2" relation="PUNCT"/></mor></t>
    <media
      start="184.297"
      end="187.249"
      unit="s"
    />
  </u>
  <u who="MOT" uID="u46">
    <e><action/><ga type="paralinguistics">undecipherable</ga></e>
    <t type="p"></t>

  </u>
  <u who="MOT" uID="u47">
    <w>can<mor type="mor"><mw><pos><c>mod</c></pos><stem>can</stem></mw><gra type="gra" index="1" head="3" relation="AUX"/></mor></w>
    <w>you<mor type="mor"><mw><pos><c>pro</c><s>per</s></pos><stem>you</stem></mw><gra type="gra" index="2" head="3" relation="SUBJ"/></mor></w>
    <w>grab<mor type="mor"><mw><pos><c>v</c></pos><stem>grab</stem></mw><gra type="gra" index="3" head="0" relation="ROOT"/></mor></w>
    <w>it<mor type="mor"><mw><pos><c>pro</c><s>per</s></pos><stem>it</stem></mw><gra type="gra" index="4" head="3" relation="OBJ"/></mor></w>
    <t type="q"><mor type="mor"><mt type="q"/><gra type="gra" index="5" head="3" relation="PUNCT"/></mor></t>
    <media
      start="187.249"
      end="189.777"
      unit="s"
    />
  </u>
  <u who="CHI" uID="u48">
    <e><action/><ga type="paralinguistics">baby coo</ga></e>
    <t type="p"></t>
    <media
      start="189.777"
      end="193.898"
      unit="s"
    />
  </u>
  <u who="CHI" uID="u49">
    <w>ooh<mor type="mor"><mw><pos><c>v</c></pos><stem>ooh</stem></mw><gra type="gra" index="1" head="0" relation="ROOT"/></mor></w>
    <t type="p"><mor type="mor"><mt type="p"/><gra type="gra" index="2" head="1" relation="PUNCT"/></mor></t>

  </u>
  <u who="MOT" uID="u50">
    <w>do<mor type="mor"><mw><pos><c>mod</c></pos><stem>do</stem></mw><gra type="gra" index="1" head="2" relation="AUX"/></mor></w>
    <w>do<mor type="mor"><mw><pos><c>v</c></pos><stem>do</stem></mw><gra type="gra" index="2" head="0" relation="ROOT"/></mor></w>
    <w>do<mor type="mor"><mw><pos><c>v</c></pos><stem>do</stem></mw><gra type="gra" index="3" head="2" relation="OBJ"/></mor></w>
    <t type="p"><mor type="mor"><mt type="p"/><gra type="gra" index="4" head="2" relation="PUNCT"/></mor></t>

  </u>
  <u who="CHI" uID="u51">
    <e><action/><ga type="paralinguistics">cooing and high pitched noise</ga></e>
    <t type="p"></t>
    <media
      start="193.898"
      end="209.426"
      unit="s"
    />
  </u>
  <u who="CHI" uID="u52">
    <g><w formType="babbling">adoa<mor type="mor"><mw><pos><c>bab</c></pos><stem>adoa</stem></mw><gra type="gra" index="1" head="0" relation="INCROOT"/></mor></w><ga type="paralinguistics">babbling sounds</ga></g>
    <t type="p"><mor type="mor"><mt type="p"/><gra type="gra" index="2" head="1" relation="PUNCT"/></mor></t>

  </u>
  <u who="MOT" uID="u53">
    <e><action/><ga type="paralinguistics">rustling of toys</ga></e>
    <t type="p"></t>
    <media
      start="209.426"
      end="218.982"
      unit="s"
    />
  </u>
  <u who="MOT" uID="u54">
    <e><action/><ga type="paralinguistics">gasp</ga></e>
    <t type="p"></t>

  </u>
  <u who="MOT" uID="u55">
    <w>do<mor type="mor"><mw><pos><c>mod</c></pos><stem>do</stem></mw><gra type="gra" index="1" head="3" relation="AUX"/></mor></w>
    <w>you<mor type="mor"><mw><pos><c>pro</c><s>per</s></pos><stem>you</stem></mw><gra type="gra" index="2" head="3" relation="SUBJ"/></mor></w>
    <w>see<mor type="mor"><mw><pos><c>v</c></pos><stem>see</stem></mw><gra type="gra" index="3" head="0" relation="ROOT"/></mor></w>
    <w>the<mor type="mor"><mw><pos><c>det</c><s>art</s></pos><stem>the</stem></mw><gra type="gra" index="4" head="5" relation="DET"/></mor></w>
    <w>look<mor type="mor"><mw><pos><c>v</c></pos><stem>look</stem></mw><gra type="gra" index="5" head="3" relation="OBJ"/></mor></w>
    <w>at<mor type="mor"><mw><pos><c>prep</c></pos><stem>at</stem></mw><gra type="gra" index="6" head="5" relation="JCT"/></mor></w>
    <w>this<mor type="mor"><mw><pos><c>det</c><s>dem</s></pos><stem>this</stem></mw><gra type="gra" index="7" head="8" relation="DET"/></mor></w>
    <w>book<mor type="mor"><mw><pos><c>n</c></pos><stem>book</stem></mw><gra type="gra" index="8" head="6" relation="POBJ"/></mor></w>
    <t type="e"><mor type="mor"><mt type="e"/><gra type="gra" index="9" head="3" relation="PUNCT"/></mor></t>
    <media
      start="218.982"
      end="223.948"
      unit="s"
    />
  </u>
  <u who="MOT" uID="u56">
    <w>look<mor type="mor"><mw><pos><c>v</c></pos><stem>look</stem></mw><gra type="gra" index="1" head="0" relation="ROOT"/></mor></w>
    <w>at<mor type="mor"><mw><pos><c>prep</c></pos><stem>at</stem></mw><gra type="gra" index="2" head="1" relation="JCT"/></mor></w>
    <w>all<mor type="mor"><mw><pos><c>qn</c></pos><stem>all</stem></mw><gra type="gra" index="3" head="5" relation="QUANT"/></mor></w>
    <w>the<mor type="mor"><mw><pos><c>det</c><s>art</s></pos><stem>the</stem></mw><gra type="gra" index="4" head="5" relation="DET"/></mor></w>
    <w>yellow<mor type="mor"><mw><pos><c>n</c></pos><stem>yellow</stem></mw><gra type="gra" index="5" head="2" relation="POBJ"/></mor></w>
    <t type="e"><mor type="mor"><mt type="e"/><gra type="gra" index="6" head="1" relation="PUNCT"/></mor></t>
    <media
      start="223.948"
      end="228.535"
      unit="s"
    />
  </u>
  <u who="MOT" uID="u57">
    <w>do<mor type="mor"><mw><pos><c>mod</c></pos><stem>do</stem></mw><gra type="gra" index="1" head="3" relation="AUX"/></mor></w>
    <w>you<mor type="mor"><mw><pos><c>pro</c><s>per</s></pos><stem>you</stem></mw><gra type="gra" index="2" head="3" relation="SUBJ"/></mor></w>
    <w>wanna<mor type="mor"><mw><pos><c>v</c></pos><stem>want</stem></mw><gra type="gra" index="3" head="0" relation="ROOT"/><mor-post><mw><pos><c>inf</c></pos><stem>to</stem></mw><gra type="gra" index="4" head="5" relation="INF"/></mor-post></mor></w>
    <w>feel<mor type="mor"><mw><pos><c>v</c></pos><stem>feel</stem></mw><gra type="gra" index="5" head="3" relation="COMP"/></mor></w>
    <t type="q"><mor type="mor"><mt type="q"/><gra type="gra" index="6" head="3" relation="PUNCT"/></mor></t>
    <media
      start="228.535"
      end="230.470"
      unit="s"
    />
  </u>
  <u who="CHI" uID="u58">
    <g><w type="filler">uh</w><ga type="paralinguistics">baby noise</ga></g>
    <t type="p"></t>

  </u>
  <u who="MOT" uID="u59">
    <w>the<mor type="mor"><mw><pos><c>det</c><s>art</s></pos><stem>the</stem></mw><gra type="gra" index="1" head="2" relation="DET"/></mor></w>
    <w>chicks<mor type="mor"><mw><pos><c>n</c></pos><stem>chick</stem><mk type="sfx">PL</mk></mw><gra type="gra" index="2" head="0" relation="INCROOT"/></mor></w>
    <t type="e"><mor type="mor"><mt type="e"/><gra type="gra" index="3" head="2" relation="PUNCT"/></mor></t>
    <media
      start="230.470"
      end="232.324"
      unit="s"
    />
  </u>
  <u who="MOT" uID="u60">
    <e><action/><ga type="paralinguistics">rustling</ga></e>
    <t type="p"></t>

  </u>
  <u who="MOT" uID="u61">
    <e><action/><ga type="paralinguistics">gasp</ga></e>
    <t type="p"></t>

  </u>
  <u who="CHI" uID="u62">
    <w>goo<mor type="mor"><mw><pos><c>n</c></pos><stem>goo</stem></mw><gra type="gra" index="1" head="2" relation="MOD"/></mor></w>
    <w formType="babbling">ga<mor type="mor"><mw><pos><c>bab</c></pos><stem>ga</stem></mw><gra type="gra" index="2" head="0" relation="ROOT"/></mor></w>
    <t type="p"><mor type="mor"><mt type="p"/><gra type="gra" index="3" head="2" relation="PUNCT"/></mor></t>

  </u>
  <u who="MOT" uID="u63">
    <w>feel<mor type="mor"><mw><pos><c>v</c></pos><stem>feel</stem></mw><gra type="gra" index="1" head="0" relation="ROOT"/></mor></w>
    <t type="q"><mor type="mor"><mt type="q"/><gra type="gra" index="2" head="1" relation="PUNCT"/></mor></t>

  </u>
  <u who="CHI" uID="u64">
    <w>goo<mor type="mor"><mw><pos><c>n</c></pos><stem>goo</stem></mw><gra type="gra" index="1" head="2" relation="MOD"/></mor></w>
    <w formType="babbling">ga<mor type="mor"><mw><pos><c>bab</c></pos><stem>ga</stem></mw><gra type="gra" index="2" head="0" relation="ROOT"/></mor></w>
    <t type="p"><mor type="mor"><mt type="p"/><gra type="gra" index="3" head="2" relation="PUNCT"/></mor></t>
    <media
      start="232.324"
      end="246.297"
      unit="s"
    />
  </u>
  <u who="MOT" uID="u65">
    <e><action/><ga type="paralinguistics">gasp</ga></e>
    <w>ready<mor type="mor"><mw><pos><c>adj</c></pos><stem>ready</stem></mw><gra type="gra" index="1" head="0" relation="INCROOT"/></mor></w>
    <t type="q"><mor type="mor"><mt type="q"/><gra type="gra" index="2" head="1" relation="PUNCT"/></mor></t>

  </u>
  <u who="MOT" uID="u66">
    <w formType="babbling">puh<mor type="mor"><mw><pos><c>bab</c></pos><stem>puh</stem></mw><gra type="gra" index="1" head="0" relation="INCROOT"/></mor></w>
    <t type="p"><mor type="mor"><mt type="p"/><gra type="gra" index="2" head="1" relation="PUNCT"/></mor></t>
    <media
      start="246.297"
      end="250.744"
      unit="s"
    />
  </u>
  <u who="MOT" uID="u67">
    <w>furry<mor type="mor"><mw><pos><c>adj</c></pos><stem>furry</stem></mw><gra type="gra" index="1" head="0" relation="INCROOT"/></mor></w>
    <t type="p"><mor type="mor"><mt type="p"/><gra type="gra" index="2" head="1" relation="PUNCT"/></mor></t>
    <media
      start="250.744"
      end="252.833"
      unit="s"
    />
  </u>
  <u who="MOT" uID="u68">
    <w>next<mor type="mor"><mw><pos><c>adj</c></pos><stem>next</stem></mw><gra type="gra" index="1" head="2" relation="MOD"/></mor></w>
    <w>page<mor type="mor"><mw><pos><c>n</c></pos><stem>page</stem></mw><gra type="gra" index="2" head="0" relation="INCROOT"/></mor></w>
    <t type="q"><mor type="mor"><mt type="q"/><gra type="gra" index="3" head="2" relation="PUNCT"/></mor></t>
    <media
      start="252.833"
      end="259.332"
      unit="s"
    />
  </u>
  <u who="MOT" uID="u69">
    <w>it's<mor type="mor"><mw><pos><c>pro</c><s>per</s></pos><stem>it</stem></mw><gra type="gra" index="1" head="2" relation="SUBJ"/><mor-post><mw><pos><c>cop</c></pos><stem>be</stem><mk type="sfxf">3S</mk></mw><gra type="gra" index="2" head="0" relation="ROOT"/></mor-post></mor></w>
    <w>the<mor type="mor"><mw><pos><c>det</c><s>art</s></pos><stem>the</stem></mw><gra type="gra" index="3" head="5" relation="DET"/></mor></w>
    <w>brown<mor type="mor"><mw><pos><c>adj</c></pos><stem>brown</stem></mw><gra type="gra" index="4" head="5" relation="MOD"/></mor></w>
    <w>horse<mor type="mor"><mw><pos><c>n</c></pos><stem>horse</stem></mw><gra type="gra" index="5" head="2" relation="PRED"/></mor></w>
    <t type="p"><mor type="mor"><mt type="p"/><gra type="gra" index="6" head="2" relation="PUNCT"/></mor></t>
    <media
      start="259.332"
      end="262.135"
      unit="s"
    />
  </u>
  <u who="MOT" uID="u70">
    <e><action/><ga type="paralinguistics">rustling</ga></e>
    <t type="p"></t>

  </u>
  <u who="MOT" uID="u71">
    <w>cow<mor type="mor"><mw><pos><c>n</c></pos><stem>cow</stem></mw><gra type="gra" index="1" head="0" relation="INCROOT"/></mor></w>
    <t type="p"><mor type="mor"><mt type="p"/><gra type="gra" index="2" head="1" relation="PUNCT"/></mor></t>

  </u>
  <u who="CHI" uID="u72">
    <g><w>ado<mor type="mor"><mw><pos><c>n</c></pos><stem>ado</stem></mw><gra type="gra" index="1" head="0" relation="INCROOT"/></mor></w><ga type="paralinguistics">excited baby coo</ga></g>
    <t type="p"><mor type="mor"><mt type="p"/><gra type="gra" index="2" head="1" relation="PUNCT"/></mor></t>
    <media
      start="262.135"
      end="275.589"
      unit="s"
    />
  </u>
  <u who="MOT" uID="u73">
    <w>I<mor type="mor"><mw><pos><c>pro</c><s>sub</s></pos><stem>I</stem></mw><gra type="gra" index="1" head="2" relation="SUBJ"/></mor></w>
    <w>know<mor type="mor"><mw><pos><c>v</c></pos><stem>know</stem></mw><gra type="gra" index="2" head="0" relation="ROOT"/></mor></w>
    <w>it's<mor type="mor"><mw><pos><c>pro</c><s>per</s></pos><stem>it</stem></mw><gra type="gra" index="3" head="4" relation="SUBJ"/><mor-post><mw><pos><c>cop</c></pos><stem>be</stem><mk type="sfxf">3S</mk></mw><gra type="gra" index="4" head="2" relation="COMP"/></mor-post></mor></w>
    <w>a<mor type="mor"><mw><pos><c>det</c><s>art</s></pos><stem>a</stem></mw><gra type="gra" index="5" head="6" relation="DET"/></mor></w>
    <w>cow<mor type="mor"><mw><pos><c>n</c></pos><stem>cow</stem></mw><gra type="gra" index="6" head="4" relation="PRED"/></mor></w>
    <t type="e"><mor type="mor"><mt type="e"/><gra type="gra" index="7" head="2" relation="PUNCT"/></mor></t>
    <media
      start="275.589"
      end="278.001"
      unit="s"
    />
  </u>
  <u who="CHI" uID="u74">
    <w>do<mor type="mor"><mw><pos><c>v</c></pos><stem>do</stem></mw><gra type="gra" index="1" head="0" relation="ROOT"/></mor></w>
    <t type="p"><mor type="mor"><mt type="p"/><gra type="gra" index="2" head="1" relation="PUNCT"/></mor></t>
    <media
      start="278.001"
      end="282.670"
      unit="s"
    />
  </u>
  <u who="MOT" uID="u75">
    <e><action/><ga type="paralinguistics">rustling of toys</ga></e>
    <t type="p"></t>

  </u>
  <u who="MOT" uID="u76">
    <e><action/><ga type="paralinguistics">gasp</ga></e>
    <t type="p"></t>

  </u>
  <u who="MOT" uID="u77">
    <w>it's<mor type="mor"><mw><pos><c>pro</c><s>per</s></pos><stem>it</stem></mw><gra type="gra" index="1" head="2" relation="SUBJ"/><mor-post><mw><pos><c>cop</c></pos><stem>be</stem><mk type="sfxf">3S</mk></mw><gra type="gra" index="2" head="0" relation="ROOT"/></mor-post></mor></w>
    <w>a<mor type="mor"><mw><pos><c>det</c><s>art</s></pos><stem>a</stem></mw><gra type="gra" index="3" head="4" relation="DET"/></mor></w>
    <w>pig<mor type="mor"><mw><pos><c>n</c></pos><stem>pig</stem></mw><gra type="gra" index="4" head="2" relation="PRED"/></mor></w>
    <t type="e"><mor type="mor"><mt type="e"/><gra type="gra" index="5" head="2" relation="PUNCT"/></mor></t>
    <media
      start="282.670"
      end="296.435"
      unit="s"
    />
  </u>
  <u who="CHI" uID="u78">
    <w>ado<mor type="mor"><mw><pos><c>n</c></pos><stem>ado</stem></mw><gra type="gra" index="1" head="0" relation="INCROOT"/></mor></w>
    <t type="p"><mor type="mor"><mt type="p"/><gra type="gra" index="2" head="1" relation="PUNCT"/></mor></t>
    <media
      start="296.435"
      end="298.479"
      unit="s"
    />
  </u>
  <u who="MOT" uID="u79">
    <w>ado<mor type="mor"><mw><pos><c>n</c></pos><stem>ado</stem></mw><gra type="gra" index="1" head="0" relation="INCROOT"/></mor></w>
    <t type="p"><mor type="mor"><mt type="p"/><gra type="gra" index="2" head="1" relation="PUNCT"/></mor></t>
    <media
      start="298.479"
      end="300.685"
      unit="s"
    />
  </u>
  <u who="CHI" uID="u80">
    <w>ado<mor type="mor"><mw><pos><c>n</c></pos><stem>ado</stem></mw><gra type="gra" index="1" head="0" relation="INCROOT"/></mor></w>
    <t type="p"><mor type="mor"><mt type="p"/><gra type="gra" index="2" head="1" relation="PUNCT"/></mor></t>
    <media
      start="300.685"
      end="302.088"
      unit="s"
    />
  </u>
  <u who="MOT" uID="u81">
    <w>and<mor type="mor"><mw><pos><c>coord</c></pos><stem>and</stem></mw><gra type="gra" index="1" head="3" relation="LINK"/></mor></w>
    <w>a<mor type="mor"><mw><pos><c>det</c><s>art</s></pos><stem>a</stem></mw><gra type="gra" index="2" head="3" relation="DET"/></mor></w>
    <w>cow<mor type="mor"><mw><pos><c>n</c></pos><stem>cow</stem></mw><gra type="gra" index="3" head="0" relation="INCROOT"/></mor></w>
    <t type="p"><mor type="mor"><mt type="p"/><gra type="gra" index="4" head="3" relation="PUNCT"/></mor></t>

  </u>
  <u who="CHI" uID="u82">
    <w>ado<mor type="mor"><mw><pos><c>n</c></pos><stem>ado</stem></mw><gra type="gra" index="1" head="0" relation="INCROOT"/></mor></w>
    <t type="p"><mor type="mor"><mt type="p"/><gra type="gra" index="2" head="1" relation="PUNCT"/></mor></t>
    <media
      start="302.088"
      end="304.513"
      unit="s"
    />
  </u>
  <u who="CHI" uID="u83">
    <g><w>ado<mor type="mor"><mw><pos><c>n</c></pos><stem>ado</stem></mw><gra type="gra" index="1" head="0" relation="INCROOT"/></mor></w><ga type="paralinguistics">high pitched excited</ga></g>
    <t type="p"><mor type="mor"><mt type="p"/><gra type="gra" index="2" head="1" relation="PUNCT"/></mor></t>
    <media
      start="304.513"
      end="306.725"
      unit="s"
    />
  </u>
  <u who="MOT" uID="u84">
    <w>it's<mor type="mor"><mw><pos><c>pro</c><s>per</s></pos><stem>it</stem></mw><gra type="gra" index="1" head="2" relation="SUBJ"/><mor-post><mw><pos><c>cop</c></pos><stem>be</stem><mk type="sfxf">3S</mk></mw><gra type="gra" index="2" head="0" relation="ROOT"/></mor-post></mor></w>
    <w>a<mor type="mor"><mw><pos><c>det</c><s>art</s></pos><stem>a</stem></mw><gra type="gra" index="3" head="4" relation="DET"/></mor></w>
    <w>cow<mor type="mor"><mw><pos><c>n</c></pos><stem>cow</stem></mw><gra type="gra" index="4" head="2" relation="PRED"/></mor></w>
    <t type="e"><mor type="mor"><mt type="e"/><gra type="gra" index="5" head="2" relation="PUNCT"/></mor></t>

  </u>
  <u who="CHI" uID="u85">
    <w>ado<mor type="mor"><mw><pos><c>n</c></pos><stem>ado</stem></mw><gra type="gra" index="1" head="0" relation="INCROOT"/></mor></w>
    <t type="p"><mor type="mor"><mt type="p"/><gra type="gra" index="2" head="1" relation="PUNCT"/></mor></t>
    <media
      start="306.725"
      end="309.578"
      unit="s"
    />
  </u>
  <u who="MOT" uID="u86">
    <w>ado<mor type="mor"><mw><pos><c>n</c></pos><stem>ado</stem></mw><gra type="gra" index="1" head="0" relation="INCROOT"/></mor></w>
    <t type="q"><mor type="mor"><mt type="q"/><gra type="gra" index="2" head="1" relation="PUNCT"/></mor></t>
    <media
      start="309.578"
      end="312.416"
      unit="s"
    />
  </u>
  <u who="CHI" uID="u87">
    <w>do<mor type="mor"><mw><pos><c>v</c></pos><stem>do</stem></mw><gra type="gra" index="1" head="0" relation="ROOT"/></mor></w>
    <t type="p"><mor type="mor"><mt type="p"/><gra type="gra" index="2" head="1" relation="PUNCT"/></mor></t>

  </u>
  <u who="MOT" uID="u88">
    <e><action/><ga type="paralinguistics">rustling toys</ga></e>
    <t type="p"></t>

  </u>
  <u who="MOT" uID="u89">
    <w>hey<mor type="mor"><mw><pos><c>co</c></pos><stem>hey</stem></mw><gra type="gra" index="1" head="5" relation="COM"/></mor></w>
    <w>we<mor type="mor"><mw><pos><c>pro</c><s>sub</s></pos><stem>we</stem></mw><gra type="gra" index="2" head="5" relation="SUBJ"/></mor></w>
    <w>don't<mor type="mor"><mw><pos><c>mod</c></pos><stem>do</stem></mw><gra type="gra" index="3" head="5" relation="AUX"/><mor-post><mw><pos><c>neg</c></pos><stem>not</stem></mw><gra type="gra" index="4" head="3" relation="NEG"/></mor-post></mor></w>
    <w>wanna<mor type="mor"><mw><pos><c>v</c></pos><stem>want</stem></mw><gra type="gra" index="5" head="0" relation="ROOT"/><mor-post><mw><pos><c>inf</c></pos><stem>to</stem></mw><gra type="gra" index="6" head="7" relation="INF"/></mor-post></mor></w>
    <w>kick<mor type="mor"><mw><pos><c>v</c></pos><stem>kick</stem></mw><gra type="gra" index="7" head="5" relation="COMP"/></mor></w>
    <w>the<mor type="mor"><mw><pos><c>det</c><s>art</s></pos><stem>the</stem></mw><gra type="gra" index="8" head="9" relation="DET"/></mor></w>
    <w>toys<mor type="mor"><mw><pos><c>n</c></pos><stem>toy</stem><mk type="sfx">PL</mk></mw><gra type="gra" index="9" head="7" relation="OBJ"/></mor></w>
    <t type="p"><mor type="mor"><mt type="p"/><gra type="gra" index="10" head="5" relation="PUNCT"/></mor></t>
    <media
      start="312.416"
      end="323.382"
      unit="s"
    />
  </u>
  <u who="MOT" uID="u90">
    <e><action/><ga type="paralinguistics">rustling toys</ga></e>
    <t type="p"></t>

  </u>
  <u who="MOT" uID="u91">
    <w>see<mor type="mor"><mw><pos><c>v</c></pos><stem>see</stem></mw><gra type="gra" index="1" head="0" relation="ROOT"/></mor></w>
    <w>the<mor type="mor"><mw><pos><c>det</c><s>art</s></pos><stem>the</stem></mw><gra type="gra" index="2" head="4" relation="DET"/></mor></w>
    <w>measuring<mor type="mor"><mw><pos><c>part</c></pos><stem>measure</stem><mk type="sfx">PRESP</mk></mw><gra type="gra" index="3" head="4" relation="MOD"/></mor></w>
    <w>spoons<mor type="mor"><mw><pos><c>n</c></pos><stem>spoon</stem><mk type="sfx">PL</mk></mw><gra type="gra" index="4" head="1" relation="OBJ"/></mor></w>
    <t type="q"><mor type="mor"><mt type="q"/><gra type="gra" index="5" head="1" relation="PUNCT"/></mor></t>
    <media
      start="323.382"
      end="332.071"
      unit="s"
    />
  </u>
  <u who="MOT" uID="u92">
    <w>you<mor type="mor"><mw><pos><c>pro</c><s>per</s></pos><stem>you</stem></mw><gra type="gra" index="1" head="2" relation="SUBJ"/></mor></w>
    <w>have<mor type="mor"><mw><pos><c>v</c></pos><stem>have</stem></mw><gra type="gra" index="2" head="0" relation="ROOT"/></mor></w>
    <w>those<mor type="mor"><mw><pos><c>pro</c><s>dem</s></pos><stem>those</stem></mw><gra type="gra" index="3" head="2" relation="OBJ"/></mor></w>
    <w>at<mor type="mor"><mw><pos><c>prep</c></pos><stem>at</stem></mw><gra type="gra" index="4" head="3" relation="JCT"/></mor></w>
    <w>home<mor type="mor"><mw><pos><c>n</c></pos><stem>home</stem></mw><gra type="gra" index="5" head="4" relation="POBJ"/></mor></w>
    <t type="p"><mor type="mor"><mt type="p"/><gra type="gra" index="6" head="2" relation="PUNCT"/></mor></t>
    <media
      start="332.071"
      end="334.013"
      unit="s"
    />
  </u>
  <u who="MOT" uID="u93">
    <e><action/><ga type="paralinguistics">toys rustling and tapping</ga></e>
    <t type="p"></t>
    <media
      start="334.013"
      end="347.614"
      unit="s"
    />
  </u>
  <u who="MOT" uID="u94">
    <w>is<mor type="mor"><mw><pos><c>cop</c></pos><stem>be</stem><mk type="sfxf">3S</mk></mw><gra type="gra" index="1" head="0" relation="ROOT"/></mor></w>
    <w>that<mor type="mor"><mw><pos><c>det</c><s>dem</s></pos><stem>that</stem></mw><gra type="gra" index="2" head="3" relation="DET"/></mor></w>
    <w>good<mor type="mor"><mw><pos><c>adj</c></pos><stem>good</stem></mw><gra type="gra" index="3" head="1" relation="PRED"/></mor></w>
    <t type="q"><mor type="mor"><mt type="q"/><gra type="gra" index="4" head="1" relation="PUNCT"/></mor></t>

  </u>
  <u who="MOT" uID="u95">
    <w>taste<mor type="mor"><mw><pos><c>n</c></pos><stem>taste</stem></mw><gra type="gra" index="1" head="0" relation="INCROOT"/></mor></w>
    <w>like<mor type="mor"><mw><pos><c>prep</c></pos><stem>like</stem></mw><gra type="gra" index="2" head="1" relation="NJCT"/></mor></w>
    <w>real<mor type="mor"><mw><pos><c>adj</c></pos><stem>real</stem></mw><gra type="gra" index="3" head="4" relation="MOD"/></mor></w>
    <w>hamburger<mor type="mor"><mw><pos><c>n</c></pos><stem>hamburger</stem></mw><gra type="gra" index="4" head="2" relation="POBJ"/></mor></w>
    <t type="q"><mor type="mor"><mt type="q"/><gra type="gra" index="5" head="1" relation="PUNCT"/></mor></t>

  </u>
  <u who="MOT" uID="u96">
    <w>no<mor type="mor"><mw><pos><c>co</c></pos><stem>no</stem></mw><gra type="gra" index="1" head="0" relation="INCROOT"/></mor></w>
    <t type="q"><mor type="mor"><mt type="q"/><gra type="gra" index="2" head="1" relation="PUNCT"/></mor></t>

  </u>
  <u who="CHI" uID="u97">
    <w>ado<mor type="mor"><mw><pos><c>n</c></pos><stem>ado</stem></mw><gra type="gra" index="1" head="0" relation="INCROOT"/></mor></w>
    <t type="p"><mor type="mor"><mt type="p"/><gra type="gra" index="2" head="1" relation="PUNCT"/></mor></t>
    <media
      start="347.614"
      end="354.305"
      unit="s"
    />
  </u>
  <u who="CHI" uID="u98">
    <w>ooh<mor type="mor"><mw><pos><c>v</c></pos><stem>ooh</stem></mw><gra type="gra" index="1" head="0" relation="ROOT"/></mor></w>
    <t type="p"><mor type="mor"><mt type="p"/><gra type="gra" index="2" head="1" relation="PUNCT"/></mor></t>

  </u>
  <u who="MOT" uID="u99">
    <e><action/><ga type="paralinguistics">toys rustling</ga></e>
    <t type="p"></t>

  </u>
  <u who="CHI" uID="u100">
    <w>ooh<mor type="mor"><mw><pos><c>v</c></pos><stem>ooh</stem></mw><gra type="gra" index="1" head="0" relation="ROOT"/></mor></w>
    <t type="p"><mor type="mor"><mt type="p"/><gra type="gra" index="2" head="1" relation="PUNCT"/></mor></t>
    <media
      start="354.305"
      end="366.136"
      unit="s"
    />
  </u>
  <u who="MOT" uID="u101">
    <e><action/><ga type="paralinguistics">gasps</ga></e>
    <t type="p"></t>

  </u>
  <u who="MOT" uID="u102">
    <w>the<mor type="mor"><mw><pos><c>det</c><s>art</s></pos><stem>the</stem></mw><gra type="gra" index="1" head="3" relation="DET"/></mor></w>
    <w>foot<mor type="mor"><mw><pos><c>n</c></pos><stem>foot</stem></mw><gra type="gra" index="2" head="3" relation="MOD"/></mor></w>
    <w>book<mor type="mor"><mw><pos><c>n</c></pos><stem>book</stem></mw><gra type="gra" index="3" head="0" relation="INCROOT"/></mor></w>
    <t type="p"><mor type="mor"><mt type="p"/><gra type="gra" index="4" head="3" relation="PUNCT"/></mor></t>
    <media
      start="366.136"
      end="372.448"
      unit="s"
    />
  </u>
  <u who="MOT" uID="u103">
    <w>left<mor type="mor"><mw><pos><c>adj</c></pos><stem>left</stem></mw><gra type="gra" index="1" head="2" relation="MOD"/></mor></w>
    <w>foot<mor type="mor"><mw><pos><c>n</c></pos><stem>foot</stem></mw><gra type="gra" index="2" head="0" relation="INCROOT"/></mor></w>
    <g><w>ligh</w><k type="retracing with correction"/></g>
    <t type="self interruption"><mor type="mor"><mt type="self interruption"/><gra type="gra" index="3" head="2" relation="PUNCT"/></mor></t>

  </u>
  <u who="MOT" uID="u104">
    <w>left<mor type="mor"><mw><pos><c>adj</c></pos><stem>left</stem></mw><gra type="gra" index="1" head="2" relation="MOD"/></mor></w>
    <w>foot<mor type="mor"><mw><pos><c>n</c></pos><stem>foot</stem></mw><gra type="gra" index="2" head="3" relation="SUBJ"/></mor></w>
    <w>left<mor type="mor"><mw><pos><c>v</c></pos><stem>leave</stem><mk type="sfxf">PAST</mk></mw><gra type="gra" index="3" head="0" relation="ROOT"/></mor></w>
    <w>foot<mor type="mor"><mw><pos><c>n</c></pos><stem>foot</stem></mw><gra type="gra" index="4" head="6" relation="MOD"/></mor></w>
    <w>right<mor type="mor"><mw><pos><c>adj</c></pos><stem>right</stem></mw><gra type="gra" index="5" head="6" relation="MOD"/></mor></w>
    <w>foot<mor type="mor"><mw><pos><c>n</c></pos><stem>foot</stem></mw><gra type="gra" index="6" head="3" relation="OBJ"/></mor></w>
    <w>right<mor type="mor"><mw><pos><c>co</c></pos><stem>right</stem></mw><gra type="gra" index="7" head="6" relation="COM"/></mor></w>
    <t type="p"><mor type="mor"><mt type="p"/><gra type="gra" index="8" head="3" relation="PUNCT"/></mor></t>
    <media
      start="372.448"
      end="378.195"
      unit="s"
    />
  </u>
  <u who="MOT" uID="u105">
    <w>feet<mor type="mor"><mw><pos><c>n</c></pos><stem>foot</stem><mk type="sfxf">PL</mk></mw><gra type="gra" index="1" head="0" relation="INCROOT"/></mor></w>
    <w>in<mor type="mor"><mw><pos><c>prep</c></pos><stem>in</stem></mw><gra type="gra" index="2" head="1" relation="NJCT"/></mor></w>
    <w>the<mor type="mor"><mw><pos><c>det</c><s>art</s></pos><stem>the</stem></mw><gra type="gra" index="3" head="4" relation="DET"/></mor></w>
    <w>day<mor type="mor"><mw><pos><c>n</c></pos><stem>day</stem></mw><gra type="gra" index="4" head="2" relation="POBJ"/></mor></w>
    <tagMarker type="comma"><mor type="mor"><mw><pos><c>cm</c></pos><stem>cm</stem></mw><gra type="gra" index="5" head="1" relation="LP"/></mor></tagMarker>
    <w>feet<mor type="mor"><mw><pos><c>n</c></pos><stem>foot</stem><mk type="sfxf">PL</mk></mw><gra type="gra" index="6" head="1" relation="ENUM"/></mor></w>
    <w>in<mor type="mor"><mw><pos><c>prep</c></pos><stem>in</stem></mw><gra type="gra" index="7" head="6" relation="NJCT"/></mor></w>
    <w>the<mor type="mor"><mw><pos><c>det</c><s>art</s></pos><stem>the</stem></mw><gra type="gra" index="8" head="9" relation="DET"/></mor></w>
    <w>night<mor type="mor"><mw><pos><c>n</c></pos><stem>night</stem></mw><gra type="gra" index="9" head="7" relation="POBJ"/></mor></w>
    <t type="p"><mor type="mor"><mt type="p"/><gra type="gra" index="10" head="1" relation="PUNCT"/></mor></t>
    <media
      start="378.195"
      end="383.247"
      unit="s"
    />
  </u>
  <u who="CHI" uID="u106">
    <w>ooh<mor type="mor"><mw><pos><c>v</c></pos><stem>ooh</stem></mw><gra type="gra" index="1" head="0" relation="ROOT"/></mor></w>
    <t type="p"><mor type="mor"><mt type="p"/><gra type="gra" index="2" head="1" relation="PUNCT"/></mor></t>

  </u>
  <u who="MOT" uID="u107">
    <g><w>look<mor type="mor"><mw><pos><c>co</c></pos><stem>look</stem></mw><gra type="gra" index="1" head="0" relation="INCROOT"/></mor></w><ga type="paralinguistics">whispers and gasp</ga></g>
    <t type="p"><mor type="mor"><mt type="p"/><gra type="gra" index="2" head="1" relation="PUNCT"/></mor></t>
    <media
      start="383.247"
      end="391.810"
      unit="s"
    />
  </u>
  <u who="MOT" uID="u108">
    <w>no<mor type="mor"><mw><pos><c>qn</c></pos><stem>no</stem></mw><gra type="gra" index="1" head="2" relation="QUANT"/></mor></w>
    <w>book<mor type="mor"><mw><pos><c>n</c></pos><stem>book</stem></mw><gra type="gra" index="2" head="0" relation="INCROOT"/></mor></w>
    <w>today<mor type="mor"><mw><pos><c>adv</c><s>tem</s></pos><stem>today</stem></mw><gra type="gra" index="3" head="2" relation="JCT"/></mor></w>
    <t type="q"><mor type="mor"><mt type="q"/><gra type="gra" index="4" head="2" relation="PUNCT"/></mor></t>

  </u>
  <u who="MOT" uID="u109">
    <w>na<mor type="mor"><mw><pos><c>co</c></pos><stem>na</stem></mw><gra type="gra" index="1" head="0" relation="INCROOT"/></mor></w>
    <t type="q"><mor type="mor"><mt type="q"/><gra type="gra" index="2" head="1" relation="PUNCT"/></mor></t>
    <media
      start="391.810"
      end="395.569"
      unit="s"
    />
  </u>
  <u who="MOT" uID="u110">
    <e><action/><ga type="paralinguistics">clicking of toys</ga></e>
    <t type="p"></t>

  </u>
  <u who="MOT" uID="u111">
    <e><action/><ga type="paralinguistics">gasp</ga></e>
    <t type="p"></t>

  </u>
  <u who="MOT" uID="u112">
    <g><w>look<mor type="mor"><mw><pos><c>co</c></pos><stem>look</stem></mw><gra type="gra" index="1" head="0" relation="INCROOT"/></mor></w><ga type="paralinguistics">whispers</ga></g>
    <t type="p"><mor type="mor"><mt type="p"/><gra type="gra" index="2" head="1" relation="PUNCT"/></mor></t>
    <media
      start="395.569"
      end="409.446"
      unit="s"
    />
  </u>
  <u who="MOT" uID="u113">
    <w>that's<mor type="mor"><mw><pos><c>pro</c><s>dem</s></pos><stem>that</stem></mw><gra type="gra" index="1" head="2" relation="SUBJ"/><mor-post><mw><pos><c>cop</c></pos><stem>be</stem><mk type="sfxf">3S</mk></mw><gra type="gra" index="2" head="0" relation="ROOT"/></mor-post></mor></w>
    <w>not<mor type="mor"><mw><pos><c>neg</c></pos><stem>not</stem></mw><gra type="gra" index="3" head="2" relation="NEG"/></mor></w>
    <w>a<mor type="mor"><mw><pos><c>det</c><s>art</s></pos><stem>a</stem></mw><gra type="gra" index="4" head="7" relation="DET"/></mor></w>
    <w>real<mor type="mor"><mw><pos><c>adj</c></pos><stem>real</stem></mw><gra type="gra" index="5" head="6" relation="MOD"/></mor></w>
    <w>bottle<mor type="mor"><mw><pos><c>n</c></pos><stem>bottle</stem></mw><gra type="gra" index="6" head="7" relation="MOD"/></mor></w>
    <w>honey<mor type="mor"><mw><pos><c>n</c></pos><stem>honey</stem></mw><gra type="gra" index="7" head="2" relation="PRED"/></mor></w>
    <t type="p"><mor type="mor"><mt type="p"/><gra type="gra" index="8" head="2" relation="PUNCT"/></mor></t>
    <media
      start="409.446"
      end="416.910"
      unit="s"
    />
  </u>
  <u who="MOT" uID="u114">
    <w>you<mor type="mor"><mw><pos><c>pro</c><s>per</s></pos><stem>you</stem></mw><gra type="gra" index="1" head="2" relation="SUBJ"/></mor></w>
    <w>wanna<mor type="mor"><mw><pos><c>v</c></pos><stem>want</stem></mw><gra type="gra" index="2" head="0" relation="ROOT"/><mor-post><mw><pos><c>inf</c></pos><stem>to</stem></mw><gra type="gra" index="3" head="4" relation="INF"/></mor-post></mor></w>
    <w>try<mor type="mor"><mw><pos><c>v</c></pos><stem>try</stem></mw><gra type="gra" index="4" head="2" relation="COMP"/></mor></w>
    <w>it<mor type="mor"><mw><pos><c>pro</c><s>per</s></pos><stem>it</stem></mw><gra type="gra" index="5" head="4" relation="OBJ"/></mor></w>
    <w>anyway<mor type="mor"><mw><pos><c>adv</c></pos><stem>anyway</stem></mw><gra type="gra" index="6" head="2" relation="JCT"/></mor></w>
    <t type="p"><mor type="mor"><mt type="p"/><gra type="gra" index="7" head="2" relation="PUNCT"/></mor></t>
    <media
      start="416.910"
      end="421.324"
      unit="s"
    />
  </u>
  <u who="MOT" uID="u115">
    <e><action/><ga type="paralinguistics">clicking of toys and rustling</ga></e>
    <t type="p"></t>
    <media
      start="421.324"
      end="438.353"
      unit="s"
    />
  </u>
  <u who="CHI" uID="u116">
    <w>ah<p type="drawl"/><mor type="mor"><mw><pos><c>co</c></pos><stem>ah</stem></mw><gra type="gra" index="1" head="0" relation="INCROOT"/></mor></w>
    <t type="p"><mor type="mor"><mt type="p"/><gra type="gra" index="2" head="1" relation="PUNCT"/></mor></t>

  </u>
  <u who="MOT" uID="u117">
    <e><action/><ga type="paralinguistics">rustling of toys and clicking</ga></e>
    <t type="p"></t>

  </u>
  <u who="MOT" uID="u118">
    <w>mommy<mor type="mor"><mw><pos><c>n</c></pos><stem>mommy</stem></mw><gra type="gra" index="1" head="2" relation="SUBJ"/></mor></w>
    <w>make<mor type="mor"><mw><pos><c>v</c></pos><stem>make</stem></mw><gra type="gra" index="2" head="0" relation="ROOT"/></mor></w>
    <w>you<mor type="mor"><mw><pos><c>pro</c><s>per</s></pos><stem>you</stem></mw><gra type="gra" index="3" head="5" relation="MOD"/></mor></w>
    <w>nice<mor type="mor"><mw><pos><c>adj</c></pos><stem>nice</stem></mw><gra type="gra" index="4" head="5" relation="MOD"/></mor></w>
    <w>sandwich<mor type="mor"><mw><pos><c>n</c></pos><stem>sandwich</stem></mw><gra type="gra" index="5" head="2" relation="OBJ"/></mor></w>
    <t type="p"><mor type="mor"><mt type="p"/><gra type="gra" index="6" head="2" relation="PUNCT"/></mor></t>

  </u>
  <u who="MOT" uID="u119">
    <w>look<mor type="mor"><mw><pos><c>co</c></pos><stem>look</stem></mw><gra type="gra" index="1" head="0" relation="INCROOT"/></mor></w>
    <t type="e"><mor type="mor"><mt type="e"/><gra type="gra" index="2" head="1" relation="PUNCT"/></mor></t>
    <media
      start="438.353"
      end="446.638"
      unit="s"
    />
  </u>
  <u who="CHI" uID="u120">
    <w>ado<mor type="mor"><mw><pos><c>n</c></pos><stem>ado</stem></mw><gra type="gra" index="1" head="2" relation="MOD"/></mor></w>
    <w>ado<mor type="mor"><mw><pos><c>n</c></pos><stem>ado</stem></mw><gra type="gra" index="2" head="0" relation="INCROOT"/></mor></w>
    <t type="p"><mor type="mor"><mt type="p"/><gra type="gra" index="3" head="2" relation="PUNCT"/></mor></t>

  </u>
  <u who="MOT" uID="u121">
    <e><action/><ga type="paralinguistics">gasps</ga></e>
    <t type="p"></t>

  </u>
  <u who="CHI" uID="u122">
    <e><action/><ga type="paralinguistics">cooing</ga></e>
    <t type="p"></t>

  </u>
  <u who="MOT" uID="u123">
    <w>pa<mor type="mor"><mw><pos><c>n</c></pos><stem>pa</stem></mw><gra type="gra" index="1" head="4" relation="MOD"/></mor></w>
    <w>pa<mor type="mor"><mw><pos><c>n</c></pos><stem>pa</stem></mw><gra type="gra" index="2" head="4" relation="MOD"/></mor></w>
    <w>pa<mor type="mor"><mw><pos><c>n</c></pos><stem>pa</stem></mw><gra type="gra" index="3" head="4" relation="MOD"/></mor></w>
    <w>pa<mor type="mor"><mw><pos><c>n</c></pos><stem>pa</stem></mw><gra type="gra" index="4" head="0" relation="ROOT"/></mor></w>
    <t type="p"><mor type="mor"><mt type="p"/><gra type="gra" index="5" head="4" relation="PUNCT"/></mor></t>
    <media
      start="446.638"
      end="462.793"
      unit="s"
    />
  </u>
  <u who="MOT" uID="u124">
    <e><action/><ga type="paralinguistics">gasp</ga></e>
    <t type="p"></t>

  </u>
  <u who="MOT" uID="u125">
    <w>ah<mor type="mor"><mw><pos><c>co</c></pos><stem>ah</stem></mw><gra type="gra" index="1" head="0" relation="INCROOT"/></mor></w>
    <t type="p"><mor type="mor"><mt type="p"/><gra type="gra" index="2" head="1" relation="PUNCT"/></mor></t>

  </u>
  <u who="MOT" uID="u126">
    <w>do<mor type="mor"><mw><pos><c>mod</c></pos><stem>do</stem></mw><gra type="gra" index="1" head="2" relation="AUX"/></mor></w>
    <w>do<mor type="mor"><mw><pos><c>v</c></pos><stem>do</stem></mw><gra type="gra" index="2" head="0" relation="ROOT"/></mor></w>
    <w>do<mor type="mor"><mw><pos><c>v</c></pos><stem>do</stem></mw><gra type="gra" index="3" head="2" relation="COMP"/></mor></w>
    <w>do<mor type="mor"><mw><pos><c>v</c></pos><stem>do</stem></mw><gra type="gra" index="4" head="3" relation="COMP"/></mor></w>
    <w>do<mor type="mor"><mw><pos><c>v</c></pos><stem>do</stem></mw><gra type="gra" index="5" head="4" relation="OBJ"/></mor></w>
    <t type="p"><mor type="mor"><mt type="p"/><gra type="gra" index="6" head="2" relation="PUNCT"/></mor></t>
    <media
      start="462.793"
      end="474.196"
      unit="s"
    />
  </u>
  <u who="CHI" uID="u127">
    <w type="filler">uh</w>
    <t type="p"></t>
    <media
      start="474.196"
      end="482.961"
      unit="s"
    />
  </u>
  <u who="MOT" uID="u128">
    <e><action/><ga type="paralinguistics">rustling of toys</ga></e>
    <t type="p"></t>
    <media
      start="482.961"
      end="490.888"
      unit="s"
    />
  </u>
  <u who="MOT" uID="u129">
    <w>now<mor type="mor"><mw><pos><c>adv</c></pos><stem>now</stem></mw><gra type="gra" index="1" head="2" relation="JCT"/></mor></w>
    <w>stay<mor type="mor"><mw><pos><c>v</c></pos><stem>stay</stem></mw><gra type="gra" index="2" head="0" relation="ROOT"/></mor></w>
    <w>over<mor type="mor"><mw><pos><c>prep</c></pos><stem>over</stem></mw><gra type="gra" index="3" head="2" relation="JCT"/></mor></w>
    <w>here<mor type="mor"><mw><pos><c>n</c></pos><stem>here</stem></mw><gra type="gra" index="4" head="3" relation="POBJ"/></mor></w>
    <t type="p"><mor type="mor"><mt type="p"/><gra type="gra" index="5" head="2" relation="PUNCT"/></mor></t>
    <media
      start="490.888"
      end="496.018"
      unit="s"
    />
  </u>
  <u who="MOT" uID="u130">
    <w>stay<mor type="mor"><mw><pos><c>v</c></pos><stem>stay</stem></mw><gra type="gra" index="1" head="0" relation="ROOT"/></mor></w>
    <w>over<mor type="mor"><mw><pos><c>prep</c></pos><stem>over</stem></mw><gra type="gra" index="2" head="1" relation="JCT"/></mor></w>
    <w>here<mor type="mor"><mw><pos><c>n</c></pos><stem>here</stem></mw><gra type="gra" index="3" head="2" relation="POBJ"/></mor></w>
    <w>with<mor type="mor"><mw><pos><c>prep</c></pos><stem>with</stem></mw><gra type="gra" index="4" head="1" relation="JCT"/></mor></w>
    <w>mommy<mor type="mor"><mw><pos><c>n</c></pos><stem>mommy</stem></mw><gra type="gra" index="5" head="4" relation="POBJ"/></mor></w>
    <t type="p"><mor type="mor"><mt type="p"/><gra type="gra" index="6" head="1" relation="PUNCT"/></mor></t>
    <media
      start="496.018"
      end="497.600"
      unit="s"
    />
  </u>
  <u who="MOT" uID="u131">
    <w>you<mor type="mor"><mw><pos><c>pro</c><s>per</s></pos><stem>you</stem></mw><gra type="gra" index="1" head="4" relation="SUBJ"/></mor></w>
    <w>don't<mor type="mor"><mw><pos><c>mod</c></pos><stem>do</stem></mw><gra type="gra" index="2" head="4" relation="AUX"/><mor-post><mw><pos><c>neg</c></pos><stem>not</stem></mw><gra type="gra" index="3" head="2" relation="NEG"/></mor-post></mor></w>
    <w>wanna<mor type="mor"><mw><pos><c>v</c></pos><stem>want</stem></mw><gra type="gra" index="4" head="0" relation="ROOT"/><mor-post><mw><pos><c>inf</c></pos><stem>to</stem></mw><gra type="gra" index="5" head="6" relation="INF"/></mor-post></mor></w>
    <w>crawl<mor type="mor"><mw><pos><c>v</c></pos><stem>crawl</stem></mw><gra type="gra" index="6" head="4" relation="COMP"/></mor></w>
    <w>around<mor type="mor"><mw><pos><c>prep</c></pos><stem>around</stem></mw><gra type="gra" index="7" head="6" relation="JCT"/></mor></w>
    <w>the<mor type="mor"><mw><pos><c>det</c><s>art</s></pos><stem>the</stem></mw><gra type="gra" index="8" head="9" relation="DET"/></mor></w>
    <w>roo<p type="drawl"/>m<mor type="mor"><mw><pos><c>n</c></pos><stem>room</stem></mw><gra type="gra" index="9" head="7" relation="POBJ"/></mor></w>
    <t type="p"><mor type="mor"><mt type="p"/><gra type="gra" index="10" head="4" relation="PUNCT"/></mor></t>
    <media
      start="497.600"
      end="502.835"
      unit="s"
    />
  </u>
  <u who="CHI" uID="u132">
    <w>gah<mor type="mor"><mw><pos><c>co</c></pos><stem>gah</stem></mw><gra type="gra" index="1" head="0" relation="INCROOT"/></mor></w>
    <t type="p"><mor type="mor"><mt type="p"/><gra type="gra" index="2" head="1" relation="PUNCT"/></mor></t>

  </u>
  <u who="CHI" uID="u133">
    <w formType="child-invented">udo<mor type="mor"><mw><pos><c>chi</c></pos><stem>udo</stem></mw><gra type="gra" index="1" head="0" relation="INCROOT"/></mor></w>
    <t type="e"><mor type="mor"><mt type="e"/><gra type="gra" index="2" head="1" relation="PUNCT"/></mor></t>
    <media
      start="502.835"
      end="506.945"
      unit="s"
    />
  </u>
  <u who="MOT" uID="u134">
    <w>do<mor type="mor"><mw><pos><c>mod</c></pos><stem>do</stem></mw><gra type="gra" index="1" head="3" relation="AUX"/></mor></w>
    <w>you<mor type="mor"><mw><pos><c>pro</c><s>per</s></pos><stem>you</stem></mw><gra type="gra" index="2" head="3" relation="SUBJ"/></mor></w>
    <w>see<mor type="mor"><mw><pos><c>v</c></pos><stem>see</stem></mw><gra type="gra" index="3" head="0" relation="ROOT"/></mor></w>
    <w>the<mor type="mor"><mw><pos><c>det</c><s>art</s></pos><stem>the</stem></mw><gra type="gra" index="4" head="6" relation="DET"/></mor></w>
    <w>big<mor type="mor"><mw><pos><c>adj</c></pos><stem>big</stem></mw><gra type="gra" index="5" head="6" relation="MOD"/></mor></w>
    <w>spoon<mor type="mor"><mw><pos><c>n</c></pos><stem>spoon</stem></mw><gra type="gra" index="6" head="3" relation="OBJ"/></mor></w>
    <t type="q"><mor type="mor"><mt type="q"/><gra type="gra" index="7" head="3" relation="PUNCT"/></mor></t>

  </u>
  <u who="CHI" uID="u135">
    <linker type="lazy overlap mark"/>
    <e><action/><ga type="paralinguistics">baby coos</ga></e>
    <t type="p"></t>

  </u>
  <u who="CHI" uID="u136">
    <w formType="child-invented">adaa<mor type="mor"><mw><pos><c>chi</c></pos><stem>adaa</stem></mw><gra type="gra" index="1" head="0" relation="INCROOT"/></mor></w>
    <t type="p"><mor type="mor"><mt type="p"/><gra type="gra" index="2" head="1" relation="PUNCT"/></mor></t>
    <media
      start="506.945"
      end="509.914"
      unit="s"
    />
  </u>
  <u who="CHI" uID="u137">
    <e><action/><ga type="paralinguistics">grunts twice</ga></e>
    <t type="p"></t>

  </u>
  <u who="MOT" uID="u138">
    <e><action/><ga type="paralinguistics">toys rustle</ga></e>
    <t type="p"></t>

  </u>
  <u who="MOT" uID="u139">
    <e><action/><ga type="paralinguistics">gasps</ga></e>
    <t type="p"></t>

  </u>
  <u who="MOT" uID="u140">
    <w formType="neologism">popopopo<mor type="mor"><mw><pos><c>neo</c></pos><stem>popopopo</stem></mw><gra type="gra" index="1" head="0" relation="INCROOT"/></mor></w>
    <t type="p"><mor type="mor"><mt type="p"/><gra type="gra" index="2" head="1" relation="PUNCT"/></mor></t>

  </u>
  <u who="MOT" uID="u141">
    <w formType="neologism">poopo<mor type="mor"><mw><pos><c>neo</c></pos><stem>poopo</stem></mw><gra type="gra" index="1" head="3" relation="NAME"/></mor></w>
    <w>Bo<mor type="mor"><mw><pos><c>n</c><s>prop</s></pos><stem>Bo</stem></mw><gra type="gra" index="2" head="3" relation="NAME"/></mor></w>
    <w>Bo<mor type="mor"><mw><pos><c>n</c><s>prop</s></pos><stem>Bo</stem></mw><gra type="gra" index="3" head="0" relation="INCROOT"/></mor></w>
    <t type="p"><mor type="mor"><mt type="p"/><gra type="gra" index="4" head="3" relation="PUNCT"/></mor></t>
    <media
      start="508.694"
      end="525.526"
      unit="s"
    />
  </u>
  <u who="CHI" uID="u142">
    <e><action/><ga type="paralinguistics">hiccup sound</ga></e>
    <t type="p"></t>

  </u>
  <u who="CHI" uID="u143">
    <w>ado<mor type="mor"><mw><pos><c>n</c></pos><stem>ado</stem></mw><gra type="gra" index="1" head="0" relation="INCROOT"/></mor></w>
    <t type="e"><mor type="mor"><mt type="e"/><gra type="gra" index="2" head="1" relation="PUNCT"/></mor></t>

  </u>
  <u who="MOT" uID="u144">
    <e><action/><ga type="paralinguistics">toys rustle and tapping sound</ga></e>
    <t type="p"></t>

  </u>
  <u who="CHI" uID="u145">
    <e><action/><ga type="paralinguistics">grunts twice</ga></e>
    <t type="p"></t>

  </u>
  <u who="MOT" uID="u146">
    <w>hey<mor type="mor"><mw><pos><c>co</c></pos><stem>hey</stem></mw><gra type="gra" index="1" head="2" relation="COM"/></mor></w>
    <w>come<mor type="mor"><mw><pos><c>v</c></pos><stem>come</stem></mw><gra type="gra" index="2" head="0" relation="ROOT"/></mor></w>
    <w>over<mor type="mor"><mw><pos><c>prep</c></pos><stem>over</stem></mw><gra type="gra" index="3" head="2" relation="JCT"/></mor></w>
    <w>here<mor type="mor"><mw><pos><c>n</c></pos><stem>here</stem></mw><gra type="gra" index="4" head="5" relation="MOD"/></mor></w>
    <w type="fragment">s</w>
    <w>play<mor type="mor"><mw><pos><c>n</c></pos><stem>play</stem></mw><gra type="gra" index="5" head="3" relation="POBJ"/></mor></w>
    <w>with<mor type="mor"><mw><pos><c>prep</c></pos><stem>with</stem></mw><gra type="gra" index="6" head="2" relation="JCT"/></mor></w>
    <w>mama<mor type="mor"><mw><pos><c>n</c></pos><stem>mama</stem></mw><gra type="gra" index="7" head="6" relation="POBJ"/></mor></w>
    <t type="p"><mor type="mor"><mt type="p"/><gra type="gra" index="8" head="2" relation="PUNCT"/></mor></t>
    <media
      start="523.116"
      end="544.362"
      unit="s"
    />
  </u>
  <u who="MOT" uID="u147">
    <w>lets<mor type="mor"><mw><pos><c>v</c></pos><stem>let</stem><mk type="sfx">3S</mk></mw><gra type="gra" index="1" head="0" relation="ROOT"/></mor></w>
    <w>play<mor type="mor"><mw><pos><c>n</c></pos><stem>play</stem></mw><gra type="gra" index="2" head="1" relation="OBJ"/></mor></w>
    <w>over<mor type="mor"><mw><pos><c>prep</c></pos><stem>over</stem></mw><gra type="gra" index="3" head="1" relation="JCT"/></mor></w>
    <w>here<mor type="mor"><mw><pos><c>n</c></pos><stem>here</stem></mw><gra type="gra" index="4" head="3" relation="POBJ"/></mor></w>
    <t type="p"><mor type="mor"><mt type="p"/><gra type="gra" index="5" head="1" relation="PUNCT"/></mor></t>
    <media
      start="544.362"
      end="547.998"
      unit="s"
    />
  </u>
  <u who="MOT" uID="u148">
    <w>you<mor type="mor"><mw><pos><c>pro</c><s>per</s></pos><stem>you</stem></mw><gra type="gra" index="1" head="4" relation="SUBJ"/></mor></w>
    <w>don't<mor type="mor"><mw><pos><c>mod</c></pos><stem>do</stem></mw><gra type="gra" index="2" head="4" relation="AUX"/><mor-post><mw><pos><c>neg</c></pos><stem>not</stem></mw><gra type="gra" index="3" head="2" relation="NEG"/></mor-post></mor></w>
    <w>wanna<mor type="mor"><mw><pos><c>v</c></pos><stem>want</stem></mw><gra type="gra" index="4" head="0" relation="ROOT"/><mor-post><mw><pos><c>inf</c></pos><stem>to</stem></mw><gra type="gra" index="5" head="6" relation="INF"/></mor-post></mor></w>
    <w>sit<mor type="mor"><mw><pos><c>v</c></pos><stem>sit</stem></mw><gra type="gra" index="6" head="4" relation="COMP"/></mor></w>
    <t type="q"><mor type="mor"><mt type="q"/><gra type="gra" index="7" head="4" relation="PUNCT"/></mor></t>

  </u>
  <u who="MOT" uID="u149">
    <w>that's<mor type="mor"><mw><pos><c>pro</c><s>dem</s></pos><stem>that</stem></mw><gra type="gra" index="1" head="2" relation="SUBJ"/><mor-post><mw><pos><c>cop</c></pos><stem>be</stem><mk type="sfxf">3S</mk></mw><gra type="gra" index="2" head="0" relation="ROOT"/></mor-post></mor></w>
    <w>okay<mor type="mor"><mw><pos><c>adj</c></pos><stem>okay</stem></mw><gra type="gra" index="3" head="2" relation="PRED"/></mor></w>
    <t type="e"><mor type="mor"><mt type="e"/><gra type="gra" index="4" head="2" relation="PUNCT"/></mor></t>

  </u>
  <u who="MOT" uID="u150">
    <w>but<mor type="mor"><mw><pos><c>conj</c></pos><stem>but</stem></mw><gra type="gra" index="1" head="5" relation="LINK"/></mor></w>
    <w>you<mor type="mor"><mw><pos><c>pro</c><s>per</s></pos><stem>you</stem></mw><gra type="gra" index="2" head="5" relation="SUBJ"/></mor></w>
    <w>gotta<mor type="mor"><mw><pos><c>mod</c></pos><stem>got</stem></mw><gra type="gra" index="3" head="5" relation="AUX"/><mor-post><mw><pos><c>inf</c></pos><stem>to</stem></mw><gra type="gra" index="4" head="5" relation="INF"/></mor-post></mor></w>
    <w>sit<mor type="mor"><mw><pos><c>v</c></pos><stem>sit</stem></mw><gra type="gra" index="5" head="0" relation="ROOT"/></mor></w>
    <w>over<mor type="mor"><mw><pos><c>adv</c></pos><stem>over</stem></mw><gra type="gra" index="6" head="5" relation="JCT"/></mor></w>
    <w>with<mor type="mor"><mw><pos><c>prep</c></pos><stem>with</stem></mw><gra type="gra" index="7" head="5" relation="JCT"/></mor></w>
    <w>mommy<mor type="mor"><mw><pos><c>n</c></pos><stem>mommy</stem></mw><gra type="gra" index="8" head="7" relation="POBJ"/></mor></w>
    <t type="p"><mor type="mor"><mt type="p"/><gra type="gra" index="9" head="5" relation="PUNCT"/></mor></t>
    <media
      start="547.998"
      end="552.155"
      unit="s"
    />
  </u>
  <u who="MOT" uID="u151">
    <e><action/><ga type="paralinguistics">toys rustle</ga></e>
    <t type="p"></t>

  </u>
  <u who="MOT" uID="u152">
    <w>we<mor type="mor"><mw><pos><c>pro</c><s>sub</s></pos><stem>we</stem></mw><gra type="gra" index="1" head="4" relation="SUBJ"/></mor></w>
    <w>don't<mor type="mor"><mw><pos><c>mod</c></pos><stem>do</stem></mw><gra type="gra" index="2" head="4" relation="AUX"/><mor-post><mw><pos><c>neg</c></pos><stem>not</stem></mw><gra type="gra" index="3" head="2" relation="NEG"/></mor-post></mor></w>
    <w>wanna<mor type="mor"><mw><pos><c>v</c></pos><stem>want</stem></mw><gra type="gra" index="4" head="0" relation="ROOT"/><mor-post><mw><pos><c>inf</c></pos><stem>to</stem></mw><gra type="gra" index="5" head="6" relation="INF"/></mor-post></mor></w>
    <w>go<mor type="mor"><mw><pos><c>v</c></pos><stem>go</stem></mw><gra type="gra" index="6" head="4" relation="COMP"/></mor></w>
    <t type="p"><mor type="mor"><mt type="p"/><gra type="gra" index="7" head="4" relation="PUNCT"/></mor></t>
    <media
      start="552.155"
      end="558.438"
      unit="s"
    />
  </u>
  <u who="MOT" uID="u153">
    <w>over<mor type="mor"><mw><pos><c>adv</c></pos><stem>over</stem></mw><gra type="gra" index="1" head="0" relation="INCROOT"/></mor></w>
    <w>by<mor type="mor"><mw><pos><c>prep</c></pos><stem>by</stem></mw><gra type="gra" index="2" head="1" relation="JCT"/></mor></w>
    <w>the<mor type="mor"><mw><pos><c>det</c><s>art</s></pos><stem>the</stem></mw><gra type="gra" index="3" head="4" relation="DET"/></mor></w>
    <w>camera<mor type="mor"><mw><pos><c>n</c></pos><stem>camera</stem></mw><gra type="gra" index="4" head="2" relation="POBJ"/></mor></w>
    <t type="p"><mor type="mor"><mt type="p"/><gra type="gra" index="5" head="1" relation="PUNCT"/></mor></t>
    <media
      start="558.438"
      end="560.383"
      unit="s"
    />
  </u>
  <u who="CHI" uID="u154">
    <w>oo<p type="drawl"/><mor type="mor"><mw><pos><c>co</c></pos><stem>oo</stem></mw><gra type="gra" index="1" head="3" relation="COM"/></mor></w>
    <w>oo<p type="drawl"/><mor type="mor"><mw><pos><c>co</c></pos><stem>oo</stem></mw><gra type="gra" index="2" head="3" relation="COM"/></mor></w>
    <g><w>Ada<mor type="mor"><mw><pos><c>n</c><s>prop</s></pos><stem>Ada</stem></mw><gra type="gra" index="3" head="0" relation="ROOT"/></mor></w><ga type="paralinguistics">baby coo</ga></g>
    <t type="p"><mor type="mor"><mt type="p"/><gra type="gra" index="4" head="3" relation="PUNCT"/></mor></t>

  </u>
  <u who="MOT" uID="u155">
    <e><action/><ga type="paralinguistics">toys lightly rustle meanwhile</ga></e>
    <t type="p"></t>
    <media
      start="560.383"
      end="585.407"
      unit="s"
    />
  </u>
  <u who="MOT" uID="u156">
    <e><action/><ga type="paralinguistics">gasp heavy exhale out</ga></e>
    <t type="p"></t>

  </u>
  <u who="CHI" uID="u157">
    <w formType="child-invented">adaa<mor type="mor"><mw><pos><c>chi</c></pos><stem>adaa</stem></mw><gra type="gra" index="1" head="0" relation="INCROOT"/></mor></w>
    <t type="p"><mor type="mor"><mt type="p"/><gra type="gra" index="2" head="1" relation="PUNCT"/></mor></t>
    <media
      start="585.407"
      end="595.095"
      unit="s"
    />
  </u>
  <u who="MOT" uID="u158">
    <e><action/><ga type="paralinguistics">chuckles</ga></e>
    <t type="p"></t>
    <media
      start="595.095"
      end="602.173"
      unit="s"
    />
  </u>
  <u who="MOT" uID="u159">
    <w>that's<mor type="mor"><mw><pos><c>pro</c><s>dem</s></pos><stem>that</stem></mw><gra type="gra" index="1" head="2" relation="SUBJ"/><mor-post><mw><pos><c>cop</c></pos><stem>be</stem><mk type="sfxf">3S</mk></mw><gra type="gra" index="2" head="0" relation="ROOT"/></mor-post></mor></w>
    <w>a<mor type="mor"><mw><pos><c>det</c><s>art</s></pos><stem>a</stem></mw><gra type="gra" index="3" head="4" relation="DET"/></mor></w>
    <w>bottle<mor type="mor"><mw><pos><c>n</c></pos><stem>bottle</stem></mw><gra type="gra" index="4" head="2" relation="PRED"/></mor></w>
    <w>for<mor type="mor"><mw><pos><c>prep</c></pos><stem>for</stem></mw><gra type="gra" index="5" head="4" relation="NJCT"/></mor></w>
    <w>the<mor type="mor"><mw><pos><c>det</c><s>art</s></pos><stem>the</stem></mw><gra type="gra" index="6" head="7" relation="DET"/></mor></w>
    <w>baby<mor type="mor"><mw><pos><c>n</c></pos><stem>baby</stem></mw><gra type="gra" index="7" head="5" relation="POBJ"/></mor></w>
    <t type="p"><mor type="mor"><mt type="p"/><gra type="gra" index="8" head="2" relation="PUNCT"/></mor></t>
    <media
      start="602.173"
      end="604.150"
      unit="s"
    />
  </u>
  <u who="MOT" uID="u160">
    <w>the<mor type="mor"><mw><pos><c>det</c><s>art</s></pos><stem>the</stem></mw><gra type="gra" index="1" head="3" relation="DET"/></mor></w>
    <w>baby<mor type="mor"><mw><pos><c>n</c></pos><stem>baby</stem></mw><gra type="gra" index="2" head="3" relation="MOD"/></mor></w>
    <w>doll<mor type="mor"><mw><pos><c>n</c></pos><stem>doll</stem></mw><gra type="gra" index="3" head="0" relation="INCROOT"/></mor></w>
    <t type="p"><mor type="mor"><mt type="p"/><gra type="gra" index="4" head="3" relation="PUNCT"/></mor></t>

  </u>
  <u who="CHI" uID="u161">
    <w>doo<mor type="mor"><mw><pos><c>n</c></pos><stem>doo</stem></mw><gra type="gra" index="1" head="0" relation="INCROOT"/></mor></w>
    <t type="p"><mor type="mor"><mt type="p"/><gra type="gra" index="2" head="1" relation="PUNCT"/></mor></t>
    <media
      start="604.150"
      end="607.110"
      unit="s"
    />
  </u>
  <u who="MOT" uID="u162">
    <w>I<mor type="mor"><mw><pos><c>pro</c><s>sub</s></pos><stem>I</stem></mw><gra type="gra" index="1" head="2" relation="SUBJ"/></mor></w>
    <w>know<mor type="mor"><mw><pos><c>v</c></pos><stem>know</stem></mw><gra type="gra" index="2" head="0" relation="ROOT"/></mor></w>
    <t type="e"><mor type="mor"><mt type="e"/><gra type="gra" index="3" head="2" relation="PUNCT"/></mor></t>

  </u>
  <u who="MOT" uID="u163">
    <w>I<mor type="mor"><mw><pos><c>pro</c><s>sub</s></pos><stem>I</stem></mw><gra type="gra" index="1" head="2" relation="SUBJ"/></mor></w>
    <w>see<mor type="mor"><mw><pos><c>v</c></pos><stem>see</stem></mw><gra type="gra" index="2" head="0" relation="ROOT"/></mor></w>
    <w>it<mor type="mor"><mw><pos><c>pro</c><s>per</s></pos><stem>it</stem></mw><gra type="gra" index="3" head="2" relation="OBJ"/></mor></w>
    <t type="e"><mor type="mor"><mt type="e"/><gra type="gra" index="4" head="2" relation="PUNCT"/></mor></t>
    <media
      start="607.110"
      end="610.333"
      unit="s"
    />
  </u>
  <u who="CHI" uID="u164">
    <g><w formType="babbling">ajuadoo<mor type="mor"><mw><pos><c>bab</c></pos><stem>ajuadoo</stem></mw><gra type="gra" index="1" head="0" relation="INCROOT"/></mor></w><ga type="paralinguistics">baby cooing</ga></g>
    <t type="p"><mor type="mor"><mt type="p"/><gra type="gra" index="2" head="1" relation="PUNCT"/></mor></t>

  </u>
  <u who="MOT" uID="u165">
    <w>that's<mor type="mor"><mw><pos><c>pro</c><s>dem</s></pos><stem>that</stem></mw><gra type="gra" index="1" head="2" relation="SUBJ"/><mor-post><mw><pos><c>cop</c></pos><stem>be</stem><mk type="sfxf">3S</mk></mw><gra type="gra" index="2" head="0" relation="ROOT"/></mor-post></mor></w>
    <w>not<mor type="mor"><mw><pos><c>neg</c></pos><stem>not</stem></mw><gra type="gra" index="3" head="2" relation="NEG"/></mor></w>
    <w>your<mor type="mor"><mw><pos><c>det</c><s>poss</s></pos><stem>your</stem></mw><gra type="gra" index="4" head="5" relation="DET"/></mor></w>
    <w>bottle<mor type="mor"><mw><pos><c>n</c></pos><stem>bottle</stem></mw><gra type="gra" index="5" head="2" relation="PRED"/></mor></w>
    <t type="p"><mor type="mor"><mt type="p"/><gra type="gra" index="6" head="2" relation="PUNCT"/></mor></t>

  </u>
  <u who="MOT" uID="u166">
    <w>that's<mor type="mor"><mw><pos><c>pro</c><s>dem</s></pos><stem>that</stem></mw><gra type="gra" index="1" head="2" relation="SUBJ"/><mor-post><mw><pos><c>cop</c></pos><stem>be</stem><mk type="sfxf">3S</mk></mw><gra type="gra" index="2" head="0" relation="ROOT"/></mor-post></mor></w>
    <w>not<mor type="mor"><mw><pos><c>neg</c></pos><stem>not</stem></mw><gra type="gra" index="3" head="2" relation="NEG"/></mor></w>
    <w>a<mor type="mor"><mw><pos><c>det</c><s>art</s></pos><stem>a</stem></mw><gra type="gra" index="4" head="6" relation="DET"/></mor></w>
    <w>real<mor type="mor"><mw><pos><c>adj</c></pos><stem>real</stem></mw><gra type="gra" index="5" head="6" relation="MOD"/></mor></w>
    <w>bottle<mor type="mor"><mw><pos><c>n</c></pos><stem>bottle</stem></mw><gra type="gra" index="6" head="2" relation="PRED"/></mor></w>
    <t type="p"><mor type="mor"><mt type="p"/><gra type="gra" index="7" head="2" relation="PUNCT"/></mor></t>
    <media
      start="610.333"
      end="615.128"
      unit="s"
    />
  </u>
  <u who="MOT" uID="u167">
    <w>I<mor type="mor"><mw><pos><c>pro</c><s>sub</s></pos><stem>I</stem></mw><gra type="gra" index="1" head="2" relation="SUBJ"/></mor></w>
    <w>know<mor type="mor"><mw><pos><c>v</c></pos><stem>know</stem></mw><gra type="gra" index="2" head="0" relation="ROOT"/></mor></w>
    <w>you<mor type="mor"><mw><pos><c>pro</c><s>per</s></pos><stem>you</stem></mw><gra type="gra" index="3" head="4" relation="SUBJ"/></mor></w>
    <w>get<mor type="mor"><mw><pos><c>v</c></pos><stem>get</stem></mw><gra type="gra" index="4" head="2" relation="COMP"/></mor></w>
    <w>all<mor type="mor"><mw><pos><c>adv</c></pos><stem>all</stem></mw><gra type="gra" index="5" head="6" relation="JCT"/></mor></w>
    <w>excited<mor type="mor"><mw><pos><c>part</c></pos><stem>excite</stem><mk type="sfx">PASTP</mk></mw><gra type="gra" index="6" head="4" relation="COMP"/></mor></w>
    <t type="e"><mor type="mor"><mt type="e"/><gra type="gra" index="7" head="2" relation="PUNCT"/></mor></t>
    <media
      start="615.128"
      end="617.299"
      unit="s"
    />
  </u>
  <u who="CHI" uID="u168">
    <w>Ada<mor type="mor"><mw><pos><c>n</c><s>prop</s></pos><stem>Ada</stem></mw><gra type="gra" index="1" head="2" relation="NAME"/></mor></w>
    <w>Ada<mor type="mor"><mw><pos><c>n</c><s>prop</s></pos><stem>Ada</stem></mw><gra type="gra" index="2" head="3" relation="NAME"/></mor></w>
    <w>Ada<mor type="mor"><mw><pos><c>n</c><s>prop</s></pos><stem>Ada</stem></mw><gra type="gra" index="3" head="4" relation="NAME"/></mor></w>
    <w>Ada<mor type="mor"><mw><pos><c>n</c><s>prop</s></pos><stem>Ada</stem></mw><gra type="gra" index="4" head="6" relation="NAME"/></mor></w>
    <w>Ada<mor type="mor"><mw><pos><c>n</c><s>prop</s></pos><stem>Ada</stem></mw><gra type="gra" index="5" head="6" relation="NAME"/></mor></w>
    <w>Ada<mor type="mor"><mw><pos><c>n</c><s>prop</s></pos><stem>Ada</stem></mw><gra type="gra" index="6" head="0" relation="ROOT"/></mor></w>
    <t type="p"><mor type="mor"><mt type="p"/><gra type="gra" index="7" head="6" relation="PUNCT"/></mor></t>

  </u>
  <u who="CHI" uID="u169">
    <e><action/><ga type="paralinguistics">whispered and gets louder as she gets more excited</ga></e>
    <t type="p"></t>

  </u>
  <u who="MOT" uID="u170">
    <w>you<mor type="mor"><mw><pos><c>pro</c><s>per</s></pos><stem>you</stem></mw><gra type="gra" index="1" head="3" relation="SUBJ"/></mor></w>
    <w>can<mor type="mor"><mw><pos><c>mod</c></pos><stem>can</stem></mw><gra type="gra" index="2" head="3" relation="AUX"/></mor></w>
    <w>stand<mor type="mor"><mw><pos><c>v</c></pos><stem>stand</stem></mw><gra type="gra" index="3" head="0" relation="ROOT"/></mor></w>
    <w>up<mor type="mor"><mw><pos><c>adv</c></pos><stem>up</stem></mw><gra type="gra" index="4" head="3" relation="JCT"/></mor></w>
    <w>let<mor type="mor"><mw><pos><c>v</c></pos><stem>let</stem><mk type="sfxf">ZERO</mk></mw><gra type="gra" index="5" head="3" relation="ENUM"/></mor></w>
    <w>me<mor type="mor"><mw><pos><c>pro</c><s>obj</s></pos><stem>me</stem></mw><gra type="gra" index="6" head="7" relation="SUBJ"/></mor></w>
    <w>move<mor type="mor"><mw><pos><c>v</c></pos><stem>move</stem></mw><gra type="gra" index="7" head="5" relation="COMP"/></mor></w>
    <w>the<mor type="mor"><mw><pos><c>det</c><s>art</s></pos><stem>the</stem></mw><gra type="gra" index="8" head="9" relation="DET"/></mor></w>
    <w>toys<mor type="mor"><mw><pos><c>n</c></pos><stem>toy</stem><mk type="sfx">PL</mk></mw><gra type="gra" index="9" head="7" relation="OBJ"/></mor></w>
    <t type="p"><mor type="mor"><mt type="p"/><gra type="gra" index="10" head="3" relation="PUNCT"/></mor></t>
    <media
      start="617.299"
      end="640.430"
      unit="s"
    />
  </u>
  <u who="MOT" uID="u171">
    <w>do<mor type="mor"><mw><pos><c>mod</c></pos><stem>do</stem></mw><gra type="gra" index="1" head="3" relation="AUX"/></mor></w>
    <w>you<mor type="mor"><mw><pos><c>pro</c><s>per</s></pos><stem>you</stem></mw><gra type="gra" index="2" head="3" relation="SUBJ"/></mor></w>
    <w>wanna<mor type="mor"><mw><pos><c>v</c></pos><stem>want</stem></mw><gra type="gra" index="3" head="0" relation="ROOT"/><mor-post><mw><pos><c>inf</c></pos><stem>to</stem></mw><gra type="gra" index="4" head="5" relation="INF"/></mor-post></mor></w>
    <w>stand<mor type="mor"><mw><pos><c>v</c></pos><stem>stand</stem></mw><gra type="gra" index="5" head="3" relation="COMP"/></mor></w>
    <w>up<mor type="mor"><mw><pos><c>adv</c></pos><stem>up</stem></mw><gra type="gra" index="6" head="5" relation="JCT"/></mor></w>
    <t type="q"><mor type="mor"><mt type="q"/><gra type="gra" index="7" head="3" relation="PUNCT"/></mor></t>
    <media
      start="640.430"
      end="642.626"
      unit="s"
    />
  </u>
  <u who="MOT" uID="u172">
    <e><action/><ga type="paralinguistics">rustling and a bit of feedback</ga></e>
    <t type="p"></t>
    <media
      start="642.626"
      end="653.346"
      unit="s"
    />
  </u>
  <u who="MOT" uID="u173">
    <e><action/><ga type="paralinguistics">a lot of rustling and banging on microphone</ga></e>
    <t type="p"></t>
    <media
      start="653.346"
      end="663.052"
      unit="s"
    />
  </u>
  <u who="MOT" uID="u174">
    <e><action/><ga type="paralinguistics">microphone being masked with movement</ga></e>
    <t type="p"></t>

  </u>
  <u who="CHI" uID="u175">
    <w untranscribed="unintelligible-with-pho">yyy</w>
    <t type="p"></t>
    <media
      start="663.052"
      end="674.439"
      unit="s"
    />
    <a type="extension" flavor="pho">adu .</a>
  </u>
  <u who="MOT" uID="u176">
    <e><action/><ga type="paralinguistics">microphone being masked with movement</ga></e>
    <t type="p"></t>

  </u>
  <u who="MOT" uID="u177">
    <w>thank<mor type="mor"><mw><pos><c>v</c></pos><stem>thank</stem></mw><gra type="gra" index="1" head="0" relation="ROOT"/></mor></w>
    <w>you<mor type="mor"><mw><pos><c>pro</c><s>per</s></pos><stem>you</stem></mw><gra type="gra" index="2" head="1" relation="OBJ"/></mor></w>
    <t type="p"><mor type="mor"><mt type="p"/><gra type="gra" index="3" head="1" relation="PUNCT"/></mor></t>
    <media
      start="674.439"
      end="681.437"
      unit="s"
    />
  </u>
  <u who="EXP" uID="u178">
    <e><action/><ga type="paralinguistics">laughs</ga></e>
    <t type="p"></t>

  </u>
  <u who="EXP" uID="u179">
    <w>okay<mor type="mor"><mw><pos><c>co</c></pos><stem>okay</stem></mw><gra type="gra" index="1" head="0" relation="INCROOT"/></mor></w>
    <t type="e"><mor type="mor"><mt type="e"/><gra type="gra" index="2" head="1" relation="PUNCT"/></mor></t>
    <media
      start="681.437"
      end="685.611"
      unit="s"
    />
  </u>
  <u who="EXP" uID="u180">
    <e><action/><ga type="paralinguistics">muffled chatter</ga></e>
    <t type="p"></t>

  </u>
  <u who="EXP" uID="u181">
    <e><action/><ga type="paralinguistics">more laughter</ga></e>
    <t type="p"></t>
    <media
      start="685.611"
      end="689.887"
      unit="s"
    />
  </u>
</CHAT>